Workbook
Name l: #REF!
Name start_day: #REF!
Name 宿命: #REF!
Name 宿命2: #REF!

Sheet リバース占い鑑定結果
A1: リバース星座占い鑑定結果
A2: 生年月日 | B2: 年 | C2: 月 | D2: 日
B3: =リバース占い!I3 -> 1981 | C3: =リバース占い!K3 -> 9 | D3: =リバース占い!L3 -> 7
A5: 表星座 | B5: 私たちが普段意識している星座（太陽星座）は社会的な表の顔を示します。 | P5: イベント | Q5: 意味 | S5: 干合名 | T5: 化名 | U5: キャラ変
A6: =リバース占い!V43 -> おとめ座 | L6: 害 | M6: ストレス | N6: 病気注意 | P6: ストレス | Q6: 病気注意 | S6: 甲己干合 | T6: 土化 | U6: オカン化
A7: 全体運 | B7: =VLOOKUP($A$6, 表裏星座一覧!A:F, 2, FALSE) -> 完璧を求める鋭い分析力と、他者のために献身的に尽くす卓越した実務能力に秀でています。ルーペで物事を見るように細部まで目が行き届き、誰も気づかないような小さなミスや改善点を瞬時に見抜く才能があります。秩序と清潔を愛し、カオスな状況を美しく整理整頓していくことに喜びを感じます。自分にも他人にも厳しい傾向があるため、時には「まぁいいか」と許す大らかさを持つことで生きやすくなります。 | L7: 害刑 | M7: ストレス・バトル | N7: ストレスと揉め事 | P7: ストレス・バトル | Q7: ストレスと揉め事 | S7: 乙庚干合 | T7: 金化 | U7: クール化
A8: 仕事運 | B8: =VLOOKUP($A$6, 表裏星座一覧!A:F, 3, FALSE) -> 医療、データ分析、秘書、経理、プログラミングなど、正確性と緻密なスケジュール管理が求められる分野で右に出る者はいません。組織の中でトップに立つよりも、優秀なナンバーツーや参謀役として、リーダーの弱点を完璧にフォローするポジションで絶対的な評価を得ます。あなたの整然とした仕事ぶりと有能さは、どんな職場でも「絶対に手放せない人材」として重宝されます。 | L8: 刑 | M8: バトル | N8: 人間関係のトラブル | P8: バトル | Q8: 人間関係のトラブル | S8: 丙辛干合 | T8: 水化 | U8: デレ化
A9: 恋愛結婚運 | B9: =VLOOKUP($A$6, 表裏星座一覧!A:F, 4, FALSE) -> 純粋で潔癖なロマンチストであり、恋愛に対しても「完璧さ」を求めるため、非常に理想が高く、相手選びに慎重です。情熱だけで突っ走ることはなく、相手の生活態度や経済観念をしっかりと観察します。一度交際が始まると、相手の世話を焼き、献身的に尽くすことに深い愛情を感じます。結婚後は家計の管理や家事を完璧にこなし、清潔で規則正しい、非常に安定した模範的な家庭を築きます。 | L9: 刑破 | M9: バトル・フリーズ | N9: 揉め事と物事の停滞 | P9: バトル・フリーズ | Q9: 揉め事と物事の停滞 | S9: 丁壬干合 | T9: 木化 | U9: エロ化
A10: 金運 | B10: =VLOOKUP($A$6, 表裏星座一覧!A:F, 5, FALSE) -> 無駄な支出を極端に嫌い、1円単位までしっかりと家計を管理できる非常に優秀で堅実な金運の持ち主です。衝動買いはほとんどせず、コストパフォーマンスや実用性を徹底的にリサーチしてから買い物をします。リスクの高いギャンブルや投資には手を出さず、安全確実な預貯金や定額積立などで、気づけば大きな財産を形成しているという手堅さが最大の強みです。 | L10: 支合 | M10: バランス | N10: 結びつきやまとまり | P10: バランス | Q10: 結びつきやまとまり | S10: 戊癸干合 | T10: 火化 | U10: オトメ化
A11: 健康運 | B11: =VLOOKUP($A$6, 表裏星座一覧!A:F, 6, FALSE) -> 大腸や小腸などの消化器官が弱点で、精神的なストレスや心配事がダイレクトにお腹の調子に影響します。完璧主義ゆえに神経をすり減らしやすいため、規則正しい生活リズムと、無農薬野菜やオーガニック食品など身体に優しい食事を摂ることが健康の基本です。休日は部屋の掃除や整理整頓をすることで心がスッキリと浄化され、自律神経のバランスを取り戻すことができます。 | L11: 合刑 | M11: バランス・バトル | N11: まとまる中の揉め事 | P11: バランス・バトル | Q11: まとまる中の揉め事
L12: 合破 | M12: バランス・フリーズ | N12: まとまる中の停滞 | P12: バランス・フリーズ | Q12: まとまる中の停滞
A13: 裏星座 | B13: 東洋の宿命理論（算命学）を掛け合わせることで浮き彫りになるあなたの無意識の裏の顔 | L13: 冲刑 | M13: クラッシュ・バトル | N13: 衝突と対人トラブル | P13: クラッシュ・バトル | Q13: 衝突と対人トラブル
A14: =リバース占い!V42 -> 裏かに座 | L14: 冲破 | M14: クラッシュ・フリーズ | N14: 衝突と物事の停滞 | P14: クラッシュ・フリーズ | Q14: 衝突と物事の停滞
A15: 全体運 | B15: =VLOOKUP($A$14, 表裏星座一覧!A:F, 2, FALSE) -> 他人に決して無断で踏み込まれない、強固で神聖な「聖域」を心の奥底に持つ孤高の存在です。表面上は穏やかで周囲に合わせているように見えても、内面にはいかなる逆境にも屈しない底知れぬ忍耐力と、世間の理不尽に対する強い反骨精神を秘めています。自分のテリトリーや愛する人々を脅かすものに対しては、徹底的に戦い抜く防衛本能の強さを持っています。容易には人に本性を見せず、真の理解者を得るまでには時間がかかりますが、自らの聖域の中でじっくりと魂を磨き上げ、最終的には誰にも到達できないような深い精神性と実力を身につける大器晩成型の重厚な人生を歩みます。 | L15: 対冲 | M15: クラッシュ | N15: 真正面からの衝突 | P15: クラッシュ | Q15: 真正面からの衝突
A16: 仕事運 | B16: =VLOOKUP($A$14, 表裏星座一覧!A:F, 3, FALSE) -> 他人のペースや職場のノイズに巻き込まれることを嫌い、自分のペースで深く没頭できる専門分野や職人肌の仕事において、他の追随を許さない絶大な信頼を得ます。底知れぬ忍耐力と反骨精神を活かし、人が投げ出すような困難な課題や、緻密な集中力が求められる業務に黙々と取り組み、完璧な結果を出して見せます。表立って目立つポジションよりも、「この人に任せておけば絶対に間違いない」と言われるような、組織の裏大黒柱や専門家としての地位を確立することで、生涯にわたって揺るぎないキャリアと名誉を築き上げる仕事運です。 | L16: 対冲刑 | M16: メガクラッシュ | N16: 激しい衝突と争い | P16: メガクラッシュ | Q16: 激しい衝突と争い
A17: 恋愛結婚運 | B17: =VLOOKUP($A$14, 表裏星座一覧!A:F, 4, FALSE) -> 警戒心が強く、自らの聖域を守ろうとするため、他者に心を開くのには非常に長い時間を必要とします。しかし、厳しい審査を経て一度この人と決めて愛せば、見返りを一切求めない底知れぬ深い愛情を永遠に注ぎ続けるという、究極の愛情深さを持っています。恋愛の延長線上には常に「家族」や「絶対的な味方」としての絆を求めており、遊びの恋には見向きもしません。結婚後はパートナーや子供を自分の神聖なテリトリー内に迎え入れ、どんな自己犠牲を払ってでも家族を守り抜く、非常に強固で温かい愛情に満ちた家庭を築き上げます。 | L17: 大半会 | M17: フィーバー | N17: 異分野融合と大発展 | P17: フィーバー | Q17: 異分野融合と大発展
A18: 金運 | B18: =VLOOKUP($A$14, 表裏星座一覧!A:F, 5, FALSE) -> 他人に踏み込まれない聖域を持つ孤高の性質は、金銭感覚においても非常に保守的で防衛本能の強い形となって表れます。ギャンブルや不確実な投資には一切手を出さず、自分のペースで没頭できる専門分野で確実に稼いだお金を、将来の安心のためにコツコツと蓄積していく能力に並外れたものがあります。底知れぬ忍耐力を持って無駄遣いを徹底的に排除し、家族や自分の城（マイホームなど）を守るための強固な経済的基盤を長年かけて築き上げます。決して派手さはありませんが、晩年になるほど圧倒的な安心感を手にする手堅い金運です。 | L18: 同 | M18: ブースト | N18: 要素の強調や倍増 | P18: ブースト | Q18: 要素の強調や倍増
A19: 健康運 | B19: =VLOOKUP($A$14, 表裏星座一覧!A:F, 6, FALSE) -> 底知れぬ忍耐力を持つがゆえに、ストレスや疲労を限界の限界まで一人で耐え忍んでしまう傾向があり、それが健康面での最大の懸念事項です。他人に踏み込まれない聖域を侵されたり、人間関係で強いストレスを感じると、胃腸などの消化器官にダイレクトに不調が現れやすい体質を持っています。健康を維持するためには、絶対に誰にも邪魔されない自分だけのリラックス空間（自室や趣味の場所）を整え、そこに引きこもって感情を完全にリセットする時間を定期的に確保することが、心身のバランスを保つための最重要課題となります。 | L19: 納音 | M19: ブレーキ | N19: 白紙に戻る・停止 | P19: ブレーキ | Q19: 白紙に戻る・停止
L20: 律音 | M20: リスタート | N20: 再出発や新たな開始 | P20: リスタート | Q20: 再出発や新たな開始
A21: リバーシブル・アングル6分類：表と裏のワタシの交差点 | L21: 半会 | M21: シナジー | N21: 新たな広がりや発展 | P21: シナジー | Q21: 新たな広がりや発展
A22: あなたが社会で見せるオモテの顔（表星座）と、心の奥底に隠されたガチの素顔（裏星座）。この2つが12星座の円盤上で「どのくらいの角度（距離）」にあるかによって、あなたの心の中で起きる化学反応は6つの角度タイプ（①0°②30°③60°,120°④90°⑤150°⑥180°）に分類されます。 | L22: 準合 | M22: スタンバイ | N22: 発展や変化の準備 | P22: スタンバイ | Q22: 発展や変化の準備
A23: アングル （角度・アスペクト） | B23: =リバース占い!W43 -> 60°・120°（セクスタイル・トライン） | F23: =リバース占い!X43 -> 【ナチュラル・ハーモニー型】 | L23: 破 | M23: フリーズ | N23: 物事の停滞や破損 | P23: フリーズ | Q23: 物事の停滞や破損
A24: アングルの内容説明 | C24: =VLOOKUP($B$23, 表裏星座一覧!A:F, 3, FALSE) -> 表と裏が同じ、または相性の良い価値観（エレメント）で結ばれた調和の配置です。 | L24: 準方位 | M24: スクラム | N24: 強固な結びつき | P24: スクラム | Q24: 強固な結びつき
A25: 全体の特性 | C25: =VLOOKUP($B$23, 表裏星座一覧!A:F, 4, FALSE) -> 社会的な「表の顔」と深層の「裏の顔」が、お互いに協力し合い、自然にエネルギーを循環させる最もストレスの少ない配置です。アウターキャラのスキルを使って、インナーキャラの欲求をスムーズに満たすことができるため、人生において「無理をしている」という感覚が非常に薄いのが特徴です。生まれながらにして物事の要領を掴むのが上手く、周囲からは「天才肌」「いつも自然体で恵まれている人」として愛されます。人間関係の構築や才能の発揮において、摩擦ゼロで波に乗ることができる天性の才能と幸運の持ち主です。 | L25: 天剋地冲 | M25: ビックバン | N25: 強制的なリセット | P25: ビックバン | Q25: 強制的なリセット
A26: 葛藤パターン | C26: =VLOOKUP($B$23, 表裏星座一覧!A:F, 5, FALSE) -> 物事が比較的スムーズに運びやすいため、極限状態での「泥臭いハングリー精神」や「何がなんでも這い上がる執念」が育ちにくいのが最大の弱点です。想定外の巨大な壁や、理不尽な逆境に直面した時、戦う前に「まあ、別の楽な道に行けばいいか」と簡単に見切りをつけてしまう傾向があります。自分の中での摩擦や葛藤がない分、現状維持の「ぬるま湯（コンフォートゾーン）」に浸かりやすく、本来持っている莫大なポテンシャルの半分も発揮せずに人生を終えてしまうという、もったいないパターンの陥りやすさを持っています。 | L26: 自刑 | M26: セルフバトル | N26: 身内や自身との葛藤 | P26: セルフバトル | Q26: 身内や自身との葛藤
A27: 開運パターン | C27: =VLOOKUP($B$23, 表裏星座一覧!A:F, 6, FALSE) -> あなたに必要なのは、意図的に「コンフォートゾーン（安全地帯）から抜け出す」という意識です。生まれ持った才能と運の流れがすでに完璧に整っているため、あえて少しハードルの高い目標を設定し、汗をかいて努力した時の成功率は144パターンの中でトップクラスです。自分を甘やかさないために、少し厳しめの指導者や、あなたとは全く違う価値観で刺激を与えてくれるライバルを意図的に持ちましょう。恵まれた環境に甘んじず、自ら「挑戦の負荷」をかけることで、あなたの運命は一気にスケールアップします。 | L27: － | M27: － | N27: －
A30: 年天運 | N30: 家庭 | O30: 自分 | P30: 社会 | Q30: 家庭 | R30: 自分 | S30: 社会 | T30: 家庭 | U30: 自分 | V30: 社会
A31: =YEAR(TODAY())-3 -> 2023 | B31: =INDEX(リバース占い!AV:AV, MATCH(A31, INDEX(VALUE(TRIM(リバース占い!AG:AG)), 0), 0)) -> 有頂天 | C31: =INDEX(リバース占い!AW:AW, MATCH(A31, INDEX(VALUE(TRIM(リバース占い!AG:AG)), 0), 0)) -> 第2の絶頂期。過去の縁が繋がり、周囲を巻き込み大きな成果を出す。 | K31: =INDEX(リバース占い!AN:AN, MATCH($A31, INDEX(VALUE(TRIM(リバース占い!$AG:$AG)), 0), 0)) -> 刑 | L31: =INDEX(リバース占い!AO:AO, MATCH($A31, INDEX(VALUE(TRIM(リバース占い!$AG:$AG)), 0), 0)) -> － | M31: =INDEX(リバース占い!AP:AP, MATCH($A31, INDEX(VALUE(TRIM(リバース占い!$AG:$AG)), 0), 0)) -> 対冲 | N31: =VLOOKUP(K31,$L$6:$P$27,2,FALSE) -> バトル | O31: =VLOOKUP(L31,$L$6:$P$27,2,FALSE) -> － | P31: =VLOOKUP(M31,$L$6:$P$27,2,FALSE) -> クラッシュ | Q31: =INDEX(リバース占い!AR:AR, MATCH($A31, INDEX(VALUE(TRIM(リバース占い!$AG:$AG)), 0), 0)) -> 戊癸干合 | R31: =INDEX(リバース占い!AS:AS, MATCH($A31, INDEX(VALUE(TRIM(リバース占い!$AG:$AG)), 0), 0)) | S31: =INDEX(リバース占い!AT:AT, MATCH($A31, INDEX(VALUE(TRIM(リバース占い!$AG:$AG)), 0), 0)) | T31: =VLOOKUP(Q31,$S$5:$U$10,3,FALSE) -> オトメ化 | U31: =VLOOKUP(R31,$S$5:$U$10,3,FALSE) -> #N/A | V31: =VLOOKUP(S31,$S$5:$U$10,3,FALSE) -> #N/A
A32: =YEAR(TODAY())-2 -> 2024 | B32: =INDEX(リバース占い!AV:AV, MATCH(A32, INDEX(VALUE(TRIM(リバース占い!AG:AG)), 0), 0)) -> 満天 | C32: =INDEX(リバース占い!AW:AW, MATCH(A32, INDEX(VALUE(TRIM(リバース占い!AG:AG)), 0), 0)) -> 収穫の喜び。物質や人脈などあらゆる財を蓄積し、強固な基盤を作る。 | K32: =INDEX(リバース占い!AN:AN, MATCH($A32, INDEX(VALUE(TRIM(リバース占い!$AG:$AG)), 0), 0)) -> 半会 | L32: =INDEX(リバース占い!AO:AO, MATCH($A32, INDEX(VALUE(TRIM(リバース占い!$AG:$AG)), 0), 0)) -> 半会 | M32: =INDEX(リバース占い!AP:AP, MATCH($A32, INDEX(VALUE(TRIM(リバース占い!$AG:$AG)), 0), 0)) -> 支合 | N32: =VLOOKUP(K32,$L$6:$P$27,2,FALSE) -> シナジー | O32: =VLOOKUP(L32,$L$6:$P$27,2,FALSE) -> シナジー | P32: =VLOOKUP(M32,$L$6:$P$27,2,FALSE) -> バランス | Q32: =INDEX(リバース占い!AR:AR, MATCH($A32, INDEX(VALUE(TRIM(リバース占い!$AG:$AG)), 0), 0)) | R32: =INDEX(リバース占い!AS:AS, MATCH($A32, INDEX(VALUE(TRIM(リバース占い!$AG:$AG)), 0), 0)) | S32: =INDEX(リバース占い!AT:AT, MATCH($A32, INDEX(VALUE(TRIM(リバース占い!$AG:$AG)), 0), 0)) | T32: =VLOOKUP(Q32,$S$5:$U$10,3,FALSE) -> #N/A | U32: =VLOOKUP(R32,$S$5:$U$10,3,FALSE) -> #N/A | V32: =VLOOKUP(S32,$S$5:$U$10,3,FALSE) -> #N/A
A33: =YEAR(TODAY())-1 -> 2025 | B33: =INDEX(リバース占い!AV:AV, MATCH(A33, INDEX(VALUE(TRIM(リバース占い!AG:AG)), 0), 0)) -> 静天 | C33: =INDEX(リバース占い!AW:AW, MATCH(A33, INDEX(VALUE(TRIM(リバース占い!AG:AG)), 0), 0)) -> 成果が出揃う。精神的な安定と充実の中で平和に人生を俯瞰する時期。 | K33: =INDEX(リバース占い!AN:AN, MATCH($A33, INDEX(VALUE(TRIM(リバース占い!$AG:$AG)), 0), 0)) -> － | L33: =INDEX(リバース占い!AO:AO, MATCH($A33, INDEX(VALUE(TRIM(リバース占い!$AG:$AG)), 0), 0)) -> 支合 | M33: =INDEX(リバース占い!AP:AP, MATCH($A33, INDEX(VALUE(TRIM(リバース占い!$AG:$AG)), 0), 0)) -> 半会 | N33: =VLOOKUP(K33,$L$6:$P$27,2,FALSE) -> － | O33: =VLOOKUP(L33,$L$6:$P$27,2,FALSE) -> バランス | P33: =VLOOKUP(M33,$L$6:$P$27,2,FALSE) -> シナジー | Q33: =INDEX(リバース占い!AR:AR, MATCH($A33, INDEX(VALUE(TRIM(リバース占い!$AG:$AG)), 0), 0)) | R33: =INDEX(リバース占い!AS:AS, MATCH($A33, INDEX(VALUE(TRIM(リバース占い!$AG:$AG)), 0), 0)) | S33: =INDEX(リバース占い!AT:AT, MATCH($A33, INDEX(VALUE(TRIM(リバース占い!$AG:$AG)), 0), 0)) | T33: =VLOOKUP(Q33,$S$5:$U$10,3,FALSE) -> #N/A | U33: =VLOOKUP(R33,$S$5:$U$10,3,FALSE) -> #N/A | V33: =VLOOKUP(S33,$S$5:$U$10,3,FALSE) -> #N/A
A34: =YEAR(TODAY()) -> 2026 | B34: =INDEX(リバース占い!AV:AV, MATCH(A34, INDEX(VALUE(TRIM(リバース占い!AG:AG)), 0), 0)) -> 暗天 | C34: =INDEX(リバース占い!AW:AW, MATCH(A34, INDEX(VALUE(TRIM(リバース占い!AG:AG)), 0), 0)) -> 運気下降（運の冬入り）。孤独を感じやすいが水面下の自己鍛錬が必要。 | K34: =INDEX(リバース占い!AN:AN, MATCH($A34, INDEX(VALUE(TRIM(リバース占い!$AG:$AG)), 0), 0)) -> 対冲 | L34: =INDEX(リバース占い!AO:AO, MATCH($A34, INDEX(VALUE(TRIM(リバース占い!$AG:$AG)), 0), 0)) -> － | M34: =INDEX(リバース占い!AP:AP, MATCH($A34, INDEX(VALUE(TRIM(リバース占い!$AG:$AG)), 0), 0)) -> － | N34: =VLOOKUP(K34,$L$6:$P$27,2,FALSE) -> クラッシュ | O34: =VLOOKUP(L34,$L$6:$P$27,2,FALSE) -> － | P34: =VLOOKUP(M34,$L$6:$P$27,2,FALSE) -> － | Q34: =INDEX(リバース占い!AR:AR, MATCH($A34, INDEX(VALUE(TRIM(リバース占い!$AG:$AG)), 0), 0)) | R34: =INDEX(リバース占い!AS:AS, MATCH($A34, INDEX(VALUE(TRIM(リバース占い!$AG:$AG)), 0), 0)) | S34: =INDEX(リバース占い!AT:AT, MATCH($A34, INDEX(VALUE(TRIM(リバース占い!$AG:$AG)), 0), 0)) -> 丙辛干合 | T34: =VLOOKUP(Q34,$S$5:$U$10,3,FALSE) -> #N/A | U34: =VLOOKUP(R34,$S$5:$U$10,3,FALSE) -> #N/A | V34: =VLOOKUP(S34,$S$5:$U$10,3,FALSE) -> デレ化
A35: =YEAR(TODAY())+1 -> 2027 | B35: =INDEX(リバース占い!AV:AV, MATCH(A35, INDEX(VALUE(TRIM(リバース占い!AG:AG)), 0), 0)) -> 大曇天 | C35: =INDEX(リバース占い!AW:AW, MATCH(A35, INDEX(VALUE(TRIM(リバース占い!AG:AG)), 0), 0)) -> 運命の停止（運の真冬時期）。古い価値観を手放す究極の浄化期間。 | K35: =INDEX(リバース占い!AN:AN, MATCH($A35, INDEX(VALUE(TRIM(リバース占い!$AG:$AG)), 0), 0)) -> 害 | L35: =INDEX(リバース占い!AO:AO, MATCH($A35, INDEX(VALUE(TRIM(リバース占い!$AG:$AG)), 0), 0)) -> － | M35: =INDEX(リバース占い!AP:AP, MATCH($A35, INDEX(VALUE(TRIM(リバース占い!$AG:$AG)), 0), 0)) -> － | N35: =VLOOKUP(K35,$L$6:$P$27,2,FALSE) -> ストレス | O35: =VLOOKUP(L35,$L$6:$P$27,2,FALSE) -> － | P35: =VLOOKUP(M35,$L$6:$P$27,2,FALSE) -> － | Q35: =INDEX(リバース占い!AR:AR, MATCH($A35, INDEX(VALUE(TRIM(リバース占い!$AG:$AG)), 0), 0)) | R35: =INDEX(リバース占い!AS:AS, MATCH($A35, INDEX(VALUE(TRIM(リバース占い!$AG:$AG)), 0), 0)) | S35: =INDEX(リバース占い!AT:AT, MATCH($A35, INDEX(VALUE(TRIM(リバース占い!$AG:$AG)), 0), 0)) | T35: =VLOOKUP(Q35,$S$5:$U$10,3,FALSE) -> #N/A | U35: =VLOOKUP(R35,$S$5:$U$10,3,FALSE) -> #N/A | V35: =VLOOKUP(S35,$S$5:$U$10,3,FALSE) -> #N/A
A36: =YEAR(TODAY())+2 -> 2028 | B36: =INDEX(リバース占い!AV:AV, MATCH(A36, INDEX(VALUE(TRIM(リバース占い!AG:AG)), 0), 0)) -> 雨天 | C36: =INDEX(リバース占い!AW:AW, MATCH(A36, INDEX(VALUE(TRIM(リバース占い!AG:AG)), 0), 0)) -> カルマの精算。過去の執着をすべて洗い流し、次の春への準備を整える。 | K36: =INDEX(リバース占い!AN:AN, MATCH($A36, INDEX(VALUE(TRIM(リバース占い!$AG:$AG)), 0), 0)) -> 大半会 | L36: =INDEX(リバース占い!AO:AO, MATCH($A36, INDEX(VALUE(TRIM(リバース占い!$AG:$AG)), 0), 0)) -> 同 | M36: =INDEX(リバース占い!AP:AP, MATCH($A36, INDEX(VALUE(TRIM(リバース占い!$AG:$AG)), 0), 0)) -> 準方位 | N36: =VLOOKUP(K36,$L$6:$P$27,2,FALSE) -> フィーバー | O36: =VLOOKUP(L36,$L$6:$P$27,2,FALSE) -> ブースト | P36: =VLOOKUP(M36,$L$6:$P$27,2,FALSE) -> スクラム | Q36: =INDEX(リバース占い!AR:AR, MATCH($A36, INDEX(VALUE(TRIM(リバース占い!$AG:$AG)), 0), 0)) | R36: =INDEX(リバース占い!AS:AS, MATCH($A36, INDEX(VALUE(TRIM(リバース占い!$AG:$AG)), 0), 0)) | S36: =INDEX(リバース占い!AT:AT, MATCH($A36, INDEX(VALUE(TRIM(リバース占い!$AG:$AG)), 0), 0)) | T36: =VLOOKUP(Q36,$S$5:$U$10,3,FALSE) -> #N/A | U36: =VLOOKUP(R36,$S$5:$U$10,3,FALSE) -> #N/A | V36: =VLOOKUP(S36,$S$5:$U$10,3,FALSE) -> #N/A
A37: =YEAR(TODAY())+3 -> 2029 | B37: =INDEX(リバース占い!AV:AV, MATCH(A37, INDEX(VALUE(TRIM(リバース占い!AG:AG)), 0), 0)) -> 起天 | C37: =INDEX(リバース占い!AW:AW, MATCH(A37, INDEX(VALUE(TRIM(リバース占い!AG:AG)), 0), 0)) -> 運命の幕開け。過去を断ち切り新しい種をまく開拓期。 | K37: =INDEX(リバース占い!AN:AN, MATCH($A37, INDEX(VALUE(TRIM(リバース占い!$AG:$AG)), 0), 0)) -> 破 | L37: =INDEX(リバース占い!AO:AO, MATCH($A37, INDEX(VALUE(TRIM(リバース占い!$AG:$AG)), 0), 0)) -> 準方位 | M37: =INDEX(リバース占い!AP:AP, MATCH($A37, INDEX(VALUE(TRIM(リバース占い!$AG:$AG)), 0), 0)) -> 自刑 | N37: =VLOOKUP(K37,$L$6:$P$27,2,FALSE) -> フリーズ | O37: =VLOOKUP(L37,$L$6:$P$27,2,FALSE) -> スクラム | P37: =VLOOKUP(M37,$L$6:$P$27,2,FALSE) -> セルフバトル | Q37: =INDEX(リバース占い!AR:AR, MATCH($A37, INDEX(VALUE(TRIM(リバース占い!$AG:$AG)), 0), 0)) | R37: =INDEX(リバース占い!AS:AS, MATCH($A37, INDEX(VALUE(TRIM(リバース占い!$AG:$AG)), 0), 0)) | S37: =INDEX(リバース占い!AT:AT, MATCH($A37, INDEX(VALUE(TRIM(リバース占い!$AG:$AG)), 0), 0)) | T37: =VLOOKUP(Q37,$S$5:$U$10,3,FALSE) -> #N/A | U37: =VLOOKUP(R37,$S$5:$U$10,3,FALSE) -> #N/A | V37: =VLOOKUP(S37,$S$5:$U$10,3,FALSE) -> #N/A
A38: =YEAR(TODAY())+4 -> 2030 | B38: =INDEX(リバース占い!AV:AV, MATCH(A38, INDEX(VALUE(TRIM(リバース占い!AG:AG)), 0), 0)) -> 吉祥天 | C38: =INDEX(リバース占い!AW:AW, MATCH(A38, INDEX(VALUE(TRIM(リバース占い!AG:AG)), 0), 0)) -> まいた種が芽吹き、周囲の支援を受けて着実に育つ時期。 | K38: =INDEX(リバース占い!AN:AN, MATCH($A38, INDEX(VALUE(TRIM(リバース占い!$AG:$AG)), 0), 0)) -> － | L38: =INDEX(リバース占い!AO:AO, MATCH($A38, INDEX(VALUE(TRIM(リバース占い!$AG:$AG)), 0), 0)) -> 準方位 | M38: =INDEX(リバース占い!AP:AP, MATCH($A38, INDEX(VALUE(TRIM(リバース占い!$AG:$AG)), 0), 0)) -> 害 | N38: =VLOOKUP(K38,$L$6:$P$27,2,FALSE) -> － | O38: =VLOOKUP(L38,$L$6:$P$27,2,FALSE) -> スクラム | P38: =VLOOKUP(M38,$L$6:$P$27,2,FALSE) -> ストレス | Q38: =INDEX(リバース占い!AR:AR, MATCH($A38, INDEX(VALUE(TRIM(リバース占い!$AG:$AG)), 0), 0)) | R38: =INDEX(リバース占い!AS:AS, MATCH($A38, INDEX(VALUE(TRIM(リバース占い!$AG:$AG)), 0), 0)) | S38: =INDEX(リバース占い!AT:AT, MATCH($A38, INDEX(VALUE(TRIM(リバース占い!$AG:$AG)), 0), 0)) | T38: =VLOOKUP(Q38,$S$5:$U$10,3,FALSE) -> #N/A | U38: =VLOOKUP(R38,$S$5:$U$10,3,FALSE) -> #N/A | V38: =VLOOKUP(S38,$S$5:$U$10,3,FALSE) -> #N/A
A39: =YEAR(TODAY())+5 -> 2031 | B39: =INDEX(リバース占い!AV:AV, MATCH(A39, INDEX(VALUE(TRIM(リバース占い!AG:AG)), 0), 0)) -> 弁財天 | C39: =INDEX(リバース占い!AW:AW, MATCH(A39, INDEX(VALUE(TRIM(リバース占い!AG:AG)), 0), 0)) -> 才能がパッと花開き、今後の人生を左右する重要な決定を下す発展期。 | K39: =INDEX(リバース占い!AN:AN, MATCH($A39, INDEX(VALUE(TRIM(リバース占い!$AG:$AG)), 0), 0)) -> 準方位 | L39: =INDEX(リバース占い!AO:AO, MATCH($A39, INDEX(VALUE(TRIM(リバース占い!$AG:$AG)), 0), 0)) -> 害 | M39: =INDEX(リバース占い!AP:AP, MATCH($A39, INDEX(VALUE(TRIM(リバース占い!$AG:$AG)), 0), 0)) -> － | N39: =VLOOKUP(K39,$L$6:$P$27,2,FALSE) -> スクラム | O39: =VLOOKUP(L39,$L$6:$P$27,2,FALSE) -> ストレス | P39: =VLOOKUP(M39,$L$6:$P$27,2,FALSE) -> － | Q39: =INDEX(リバース占い!AR:AR, MATCH($A39, INDEX(VALUE(TRIM(リバース占い!$AG:$AG)), 0), 0)) | R39: =INDEX(リバース占い!AS:AS, MATCH($A39, INDEX(VALUE(TRIM(リバース占い!$AG:$AG)), 0), 0)) -> 丙辛干合 | S39: =INDEX(リバース占い!AT:AT, MATCH($A39, INDEX(VALUE(TRIM(リバース占い!$AG:$AG)), 0), 0)) | T39: =VLOOKUP(Q39,$S$5:$U$10,3,FALSE) -> #N/A | U39: =VLOOKUP(R39,$S$5:$U$10,3,FALSE) -> デレ化 | V39: =VLOOKUP(S39,$S$5:$U$10,3,FALSE) -> #N/A
A40: =YEAR(TODAY())+6 -> 2032 | B40: =INDEX(リバース占い!AV:AV, MATCH(A40, INDEX(VALUE(TRIM(リバース占い!AG:AG)), 0), 0)) -> 曇天 | C40: =INDEX(リバース占い!AW:AW, MATCH(A40, INDEX(VALUE(TRIM(リバース占い!AG:AG)), 0), 0)) -> 運気の勢いに心身が追いつかない小休止。自己治癒の時期。 | K40: =INDEX(リバース占い!AN:AN, MATCH($A40, INDEX(VALUE(TRIM(リバース占い!$AG:$AG)), 0), 0)) -> 同 | L40: =INDEX(リバース占い!AO:AO, MATCH($A40, INDEX(VALUE(TRIM(リバース占い!$AG:$AG)), 0), 0)) -> 半会 | M40: =INDEX(リバース占い!AP:AP, MATCH($A40, INDEX(VALUE(TRIM(リバース占い!$AG:$AG)), 0), 0)) -> 破 | N40: =VLOOKUP(K40,$L$6:$P$27,2,FALSE) -> ブースト | O40: =VLOOKUP(L40,$L$6:$P$27,2,FALSE) -> シナジー | P40: =VLOOKUP(M40,$L$6:$P$27,2,FALSE) -> フリーズ | Q40: =INDEX(リバース占い!AR:AR, MATCH($A40, INDEX(VALUE(TRIM(リバース占い!$AG:$AG)), 0), 0)) | R40: =INDEX(リバース占い!AS:AS, MATCH($A40, INDEX(VALUE(TRIM(リバース占い!$AG:$AG)), 0), 0)) | S40: =INDEX(リバース占い!AT:AT, MATCH($A40, INDEX(VALUE(TRIM(リバース占い!$AG:$AG)), 0), 0)) | T40: =VLOOKUP(Q40,$S$5:$U$10,3,FALSE) -> #N/A | U40: =VLOOKUP(R40,$S$5:$U$10,3,FALSE) -> #N/A | V40: =VLOOKUP(S40,$S$5:$U$10,3,FALSE) -> #N/A
A41: =YEAR(TODAY())+7 -> 2033 | B41: =INDEX(リバース占い!AV:AV, MATCH(A41, INDEX(VALUE(TRIM(リバース占い!AG:AG)), 0), 0)) -> 韋駄天 | C41: =INDEX(リバース占い!AW:AW, MATCH(A41, INDEX(VALUE(TRIM(リバース占い!AG:AG)), 0), 0)) -> 運気絶頂。これまでの努力が実を結び、最高のスポットライトを浴びる。 | K41: =INDEX(リバース占い!AN:AN, MATCH($A41, INDEX(VALUE(TRIM(リバース占い!$AG:$AG)), 0), 0)) -> 支合 | L41: =INDEX(リバース占い!AO:AO, MATCH($A41, INDEX(VALUE(TRIM(リバース占い!$AG:$AG)), 0), 0)) -> － | M41: =INDEX(リバース占い!AP:AP, MATCH($A41, INDEX(VALUE(TRIM(リバース占い!$AG:$AG)), 0), 0)) -> 半会 | N41: =VLOOKUP(K41,$L$6:$P$27,2,FALSE) -> バランス | O41: =VLOOKUP(L41,$L$6:$P$27,2,FALSE) -> － | P41: =VLOOKUP(M41,$L$6:$P$27,2,FALSE) -> シナジー | Q41: =INDEX(リバース占い!AR:AR, MATCH($A41, INDEX(VALUE(TRIM(リバース占い!$AG:$AG)), 0), 0)) -> 戊癸干合 | R41: =INDEX(リバース占い!AS:AS, MATCH($A41, INDEX(VALUE(TRIM(リバース占い!$AG:$AG)), 0), 0)) | S41: =INDEX(リバース占い!AT:AT, MATCH($A41, INDEX(VALUE(TRIM(リバース占い!$AG:$AG)), 0), 0)) | T41: =VLOOKUP(Q41,$S$5:$U$10,3,FALSE) -> オトメ化 | U41: =VLOOKUP(R41,$S$5:$U$10,3,FALSE) -> #N/A | V41: =VLOOKUP(S41,$S$5:$U$10,3,FALSE) -> #N/A
A42: =YEAR(TODAY())+8 -> 2034 | B42: =INDEX(リバース占い!AV:AV, MATCH(A42, INDEX(VALUE(TRIM(リバース占い!AG:AG)), 0), 0)) -> 伏魔天 | C42: =INDEX(リバース占い!AW:AW, MATCH(A42, INDEX(VALUE(TRIM(リバース占い!AG:AG)), 0), 0)) -> 強すぎる運気の反動で迷いや摩擦が生じる。理性と現状維持が必要な嵐。 | K42: =INDEX(リバース占い!AN:AN, MATCH($A42, INDEX(VALUE(TRIM(リバース占い!$AG:$AG)), 0), 0)) -> － | L42: =INDEX(リバース占い!AO:AO, MATCH($A42, INDEX(VALUE(TRIM(リバース占い!$AG:$AG)), 0), 0)) -> 対冲 | M42: =INDEX(リバース占い!AP:AP, MATCH($A42, INDEX(VALUE(TRIM(リバース占い!$AG:$AG)), 0), 0)) -> － | N42: =VLOOKUP(K42,$L$6:$P$27,2,FALSE) -> － | O42: =VLOOKUP(L42,$L$6:$P$27,2,FALSE) -> クラッシュ | P42: =VLOOKUP(M42,$L$6:$P$27,2,FALSE) -> － | Q42: =INDEX(リバース占い!AR:AR, MATCH($A42, INDEX(VALUE(TRIM(リバース占い!$AG:$AG)), 0), 0)) | R42: =INDEX(リバース占い!AS:AS, MATCH($A42, INDEX(VALUE(TRIM(リバース占い!$AG:$AG)), 0), 0)) | S42: =INDEX(リバース占い!AT:AT, MATCH($A42, INDEX(VALUE(TRIM(リバース占い!$AG:$AG)), 0), 0)) | T42: =VLOOKUP(Q42,$S$5:$U$10,3,FALSE) -> #N/A | U42: =VLOOKUP(R42,$S$5:$U$10,3,FALSE) -> #N/A | V42: =VLOOKUP(S42,$S$5:$U$10,3,FALSE) -> #N/A
A44: 月天運 | N44: 家庭 | O44: 自分 | P44: 社会 | Q44: 家庭 | R44: 自分 | S44: 社会 | T44: 家庭 | U44: 自分 | V44: 社会
A45: 2026/4 | B45: =INDEX(リバース占い!U:U, MATCH(TEXT(A45, "yyyy/m"), INDEX(TRIM(リバース占い!F:F), 0), 0)) -> 満天 | C45: =INDEX(リバース占い!V:V, MATCH(TEXT(A45, "yyyy/m"), INDEX(TRIM(リバース占い!F:F), 0), 0)) -> 収穫の喜び。物質や人脈などあらゆる財を蓄積し、強固な基盤を作る。 | K45: =INDEX(リバース占い!M:M, MATCH(TEXT($A45, "yyyy/m"), INDEX(TRIM(リバース占い!$F:$F), 0), 0)) -> 半会 | L45: =INDEX(リバース占い!N:N, MATCH(TEXT($A45, "yyyy/m"), INDEX(TRIM(リバース占い!$F:$F), 0), 0)) -> 半会 | M45: =INDEX(リバース占い!O:O, MATCH(TEXT($A45, "yyyy/m"), INDEX(TRIM(リバース占い!$F:$F), 0), 0)) -> 支合 | N45: =VLOOKUP(K45,$L$6:$P$27,2,FALSE) -> シナジー | O45: =VLOOKUP(L45,$L$6:$P$27,2,FALSE) -> シナジー | P45: =VLOOKUP(M45,$L$6:$P$27,2,FALSE) -> バランス | Q45: =INDEX(リバース占い!Q:Q, MATCH(TEXT($A45, "yyyy/m"), INDEX(TRIM(リバース占い!$F:$F), 0), 0)) | R45: =INDEX(リバース占い!R:R, MATCH(TEXT($A45, "yyyy/m"), INDEX(TRIM(リバース占い!$F:$F), 0), 0)) | S45: =INDEX(リバース占い!S:S, MATCH(TEXT($A45, "yyyy/m"), INDEX(TRIM(リバース占い!$F:$F), 0), 0)) | T45: =VLOOKUP(Q45,$S$5:$U$10,3,FALSE) -> #N/A | U45: =VLOOKUP(R45,$S$5:$U$10,3,FALSE) -> #N/A | V45: =VLOOKUP(S45,$S$5:$U$10,3,FALSE) -> #N/A
A46: =TEXT(EDATE(TODAY(), ROW(A2) - 3), "yyyy/m") -> 2026/5 | B46: =INDEX(リバース占い!U:U, MATCH(TEXT(A46, "yyyy/m"), INDEX(TRIM(リバース占い!F:F), 0), 0)) -> 静天 | C46: =INDEX(リバース占い!V:V, MATCH(TEXT(A46, "yyyy/m"), INDEX(TRIM(リバース占い!F:F), 0), 0)) -> 成果が出揃う。精神的な安定と充実の中で平和に人生を俯瞰する時期。 | K46: =INDEX(リバース占い!M:M, MATCH(TEXT($A46, "yyyy/m"), INDEX(TRIM(リバース占い!$F:$F), 0), 0)) -> － | L46: =INDEX(リバース占い!N:N, MATCH(TEXT($A46, "yyyy/m"), INDEX(TRIM(リバース占い!$F:$F), 0), 0)) -> 支合 | M46: =INDEX(リバース占い!O:O, MATCH(TEXT($A46, "yyyy/m"), INDEX(TRIM(リバース占い!$F:$F), 0), 0)) -> 半会 | N46: =VLOOKUP(K46,$L$6:$P$27,2,FALSE) -> － | O46: =VLOOKUP(L46,$L$6:$P$27,2,FALSE) -> バランス | P46: =VLOOKUP(M46,$L$6:$P$27,2,FALSE) -> シナジー | Q46: =INDEX(リバース占い!Q:Q, MATCH(TEXT($A46, "yyyy/m"), INDEX(TRIM(リバース占い!$F:$F), 0), 0)) -> 戊癸干合 | R46: =INDEX(リバース占い!R:R, MATCH(TEXT($A46, "yyyy/m"), INDEX(TRIM(リバース占い!$F:$F), 0), 0)) | S46: =INDEX(リバース占い!S:S, MATCH(TEXT($A46, "yyyy/m"), INDEX(TRIM(リバース占い!$F:$F), 0), 0)) | T46: =VLOOKUP(Q46,$S$5:$U$10,3,FALSE) -> オトメ化 | U46: =VLOOKUP(R46,$S$5:$U$10,3,FALSE) -> #N/A | V46: =VLOOKUP(S46,$S$5:$U$10,3,FALSE) -> #N/A
A47: =TEXT(EDATE(TODAY(), ROW(A3) - 3), "yyyy/m") -> 2026/6 | B47: =INDEX(リバース占い!U:U, MATCH(TEXT(A47, "yyyy/m"), INDEX(TRIM(リバース占い!F:F), 0), 0)) -> 暗天 | C47: =INDEX(リバース占い!V:V, MATCH(TEXT(A47, "yyyy/m"), INDEX(TRIM(リバース占い!F:F), 0), 0)) -> 運気下降（運の冬入り）。孤独を感じやすいが水面下の自己鍛錬が必要。 | K47: =INDEX(リバース占い!M:M, MATCH(TEXT($A47, "yyyy/m"), INDEX(TRIM(リバース占い!$F:$F), 0), 0)) -> 天剋地冲 | L47: =INDEX(リバース占い!N:N, MATCH(TEXT($A47, "yyyy/m"), INDEX(TRIM(リバース占い!$F:$F), 0), 0)) -> － | M47: =INDEX(リバース占い!O:O, MATCH(TEXT($A47, "yyyy/m"), INDEX(TRIM(リバース占い!$F:$F), 0), 0)) -> － | N47: =VLOOKUP(K47,$L$6:$P$27,2,FALSE) -> ビックバン | O47: =VLOOKUP(L47,$L$6:$P$27,2,FALSE) -> － | P47: =VLOOKUP(M47,$L$6:$P$27,2,FALSE) -> － | Q47: =INDEX(リバース占い!Q:Q, MATCH(TEXT($A47, "yyyy/m"), INDEX(TRIM(リバース占い!$F:$F), 0), 0)) | R47: =INDEX(リバース占い!R:R, MATCH(TEXT($A47, "yyyy/m"), INDEX(TRIM(リバース占い!$F:$F), 0), 0)) | S47: =INDEX(リバース占い!S:S, MATCH(TEXT($A47, "yyyy/m"), INDEX(TRIM(リバース占い!$F:$F), 0), 0)) | T47: =VLOOKUP(Q47,$S$5:$U$10,3,FALSE) -> #N/A | U47: =VLOOKUP(R47,$S$5:$U$10,3,FALSE) -> #N/A | V47: =VLOOKUP(S47,$S$5:$U$10,3,FALSE) -> #N/A
A48: =TEXT(EDATE(TODAY(), ROW(A4) - 3), "yyyy/m") -> 2026/7 | B48: =INDEX(リバース占い!U:U, MATCH(TEXT(A48, "yyyy/m"), INDEX(TRIM(リバース占い!F:F), 0), 0)) -> 大曇天 | C48: =INDEX(リバース占い!V:V, MATCH(TEXT(A48, "yyyy/m"), INDEX(TRIM(リバース占い!F:F), 0), 0)) -> 運命の停止（運の真冬時期）。古い価値観を手放す究極の浄化期間。 | K48: =INDEX(リバース占い!M:M, MATCH(TEXT($A48, "yyyy/m"), INDEX(TRIM(リバース占い!$F:$F), 0), 0)) -> 害 | L48: =INDEX(リバース占い!N:N, MATCH(TEXT($A48, "yyyy/m"), INDEX(TRIM(リバース占い!$F:$F), 0), 0)) -> － | M48: =INDEX(リバース占い!O:O, MATCH(TEXT($A48, "yyyy/m"), INDEX(TRIM(リバース占い!$F:$F), 0), 0)) -> － | N48: =VLOOKUP(K48,$L$6:$P$27,2,FALSE) -> ストレス | O48: =VLOOKUP(L48,$L$6:$P$27,2,FALSE) -> － | P48: =VLOOKUP(M48,$L$6:$P$27,2,FALSE) -> － | Q48: =INDEX(リバース占い!Q:Q, MATCH(TEXT($A48, "yyyy/m"), INDEX(TRIM(リバース占い!$F:$F), 0), 0)) | R48: =INDEX(リバース占い!R:R, MATCH(TEXT($A48, "yyyy/m"), INDEX(TRIM(リバース占い!$F:$F), 0), 0)) | S48: =INDEX(リバース占い!S:S, MATCH(TEXT($A48, "yyyy/m"), INDEX(TRIM(リバース占い!$F:$F), 0), 0)) | T48: =VLOOKUP(Q48,$S$5:$U$10,3,FALSE) -> #N/A | U48: =VLOOKUP(R48,$S$5:$U$10,3,FALSE) -> #N/A | V48: =VLOOKUP(S48,$S$5:$U$10,3,FALSE) -> #N/A
A49: =TEXT(EDATE(TODAY(), ROW(A5) - 3), "yyyy/m") -> 2026/8 | B49: =INDEX(リバース占い!U:U, MATCH(TEXT(A49, "yyyy/m"), INDEX(TRIM(リバース占い!F:F), 0), 0)) -> 雨天 | C49: =INDEX(リバース占い!V:V, MATCH(TEXT(A49, "yyyy/m"), INDEX(TRIM(リバース占い!F:F), 0), 0)) -> カルマの精算。過去の執着をすべて洗い流し、次の春への準備を整える。 | K49: =INDEX(リバース占い!M:M, MATCH(TEXT($A49, "yyyy/m"), INDEX(TRIM(リバース占い!$F:$F), 0), 0)) -> 半会 | L49: =INDEX(リバース占い!N:N, MATCH(TEXT($A49, "yyyy/m"), INDEX(TRIM(リバース占い!$F:$F), 0), 0)) -> 律音 | M49: =INDEX(リバース占い!O:O, MATCH(TEXT($A49, "yyyy/m"), INDEX(TRIM(リバース占い!$F:$F), 0), 0)) -> 準方位 | N49: =VLOOKUP(K49,$L$6:$P$27,2,FALSE) -> シナジー | O49: =VLOOKUP(L49,$L$6:$P$27,2,FALSE) -> リスタート | P49: =VLOOKUP(M49,$L$6:$P$27,2,FALSE) -> スクラム | Q49: =INDEX(リバース占い!Q:Q, MATCH(TEXT($A49, "yyyy/m"), INDEX(TRIM(リバース占い!$F:$F), 0), 0)) | R49: =INDEX(リバース占い!R:R, MATCH(TEXT($A49, "yyyy/m"), INDEX(TRIM(リバース占い!$F:$F), 0), 0)) | S49: =INDEX(リバース占い!S:S, MATCH(TEXT($A49, "yyyy/m"), INDEX(TRIM(リバース占い!$F:$F), 0), 0)) -> 丙辛干合 | T49: =VLOOKUP(Q49,$S$5:$U$10,3,FALSE) -> #N/A | U49: =VLOOKUP(R49,$S$5:$U$10,3,FALSE) -> #N/A | V49: =VLOOKUP(S49,$S$5:$U$10,3,FALSE) -> デレ化
A50: =TEXT(EDATE(TODAY(), ROW(A6) - 3), "yyyy/m") -> 2026/9 | B50: =INDEX(リバース占い!U:U, MATCH(TEXT(A50, "yyyy/m"), INDEX(TRIM(リバース占い!F:F), 0), 0)) -> 起天 | C50: =INDEX(リバース占い!V:V, MATCH(TEXT(A50, "yyyy/m"), INDEX(TRIM(リバース占い!F:F), 0), 0)) -> 運命の幕開け。過去を断ち切り新しい種をまく開拓期。 | K50: =INDEX(リバース占い!M:M, MATCH(TEXT($A50, "yyyy/m"), INDEX(TRIM(リバース占い!$F:$F), 0), 0)) -> 破 | L50: =INDEX(リバース占い!N:N, MATCH(TEXT($A50, "yyyy/m"), INDEX(TRIM(リバース占い!$F:$F), 0), 0)) -> 準方位 | M50: =INDEX(リバース占い!O:O, MATCH(TEXT($A50, "yyyy/m"), INDEX(TRIM(リバース占い!$F:$F), 0), 0)) -> 自刑 | N50: =VLOOKUP(K50,$L$6:$P$27,2,FALSE) -> フリーズ | O50: =VLOOKUP(L50,$L$6:$P$27,2,FALSE) -> スクラム | P50: =VLOOKUP(M50,$L$6:$P$27,2,FALSE) -> セルフバトル | Q50: =INDEX(リバース占い!Q:Q, MATCH(TEXT($A50, "yyyy/m"), INDEX(TRIM(リバース占い!$F:$F), 0), 0)) | R50: =INDEX(リバース占い!R:R, MATCH(TEXT($A50, "yyyy/m"), INDEX(TRIM(リバース占い!$F:$F), 0), 0)) | S50: =INDEX(リバース占い!S:S, MATCH(TEXT($A50, "yyyy/m"), INDEX(TRIM(リバース占い!$F:$F), 0), 0)) | T50: =VLOOKUP(Q50,$S$5:$U$10,3,FALSE) -> #N/A | U50: =VLOOKUP(R50,$S$5:$U$10,3,FALSE) -> #N/A | V50: =VLOOKUP(S50,$S$5:$U$10,3,FALSE) -> #N/A
A51: =TEXT(EDATE(TODAY(), ROW(A7) - 3), "yyyy/m") -> 2026/10 | B51: =INDEX(リバース占い!U:U, MATCH(TEXT(A51, "yyyy/m"), INDEX(TRIM(リバース占い!F:F), 0), 0)) -> 吉祥天 | C51: =INDEX(リバース占い!V:V, MATCH(TEXT(A51, "yyyy/m"), INDEX(TRIM(リバース占い!F:F), 0), 0)) -> まいた種が芽吹き、周囲の支援を受けて着実に育つ時期。 | K51: =INDEX(リバース占い!M:M, MATCH(TEXT($A51, "yyyy/m"), INDEX(TRIM(リバース占い!$F:$F), 0), 0)) -> － | L51: =INDEX(リバース占い!N:N, MATCH(TEXT($A51, "yyyy/m"), INDEX(TRIM(リバース占い!$F:$F), 0), 0)) -> 準方位 | M51: =INDEX(リバース占い!O:O, MATCH(TEXT($A51, "yyyy/m"), INDEX(TRIM(リバース占い!$F:$F), 0), 0)) -> 害 | N51: =VLOOKUP(K51,$L$6:$P$27,2,FALSE) -> － | O51: =VLOOKUP(L51,$L$6:$P$27,2,FALSE) -> スクラム | P51: =VLOOKUP(M51,$L$6:$P$27,2,FALSE) -> ストレス | Q51: =INDEX(リバース占い!Q:Q, MATCH(TEXT($A51, "yyyy/m"), INDEX(TRIM(リバース占い!$F:$F), 0), 0)) | R51: =INDEX(リバース占い!R:R, MATCH(TEXT($A51, "yyyy/m"), INDEX(TRIM(リバース占い!$F:$F), 0), 0)) | S51: =INDEX(リバース占い!S:S, MATCH(TEXT($A51, "yyyy/m"), INDEX(TRIM(リバース占い!$F:$F), 0), 0)) | T51: =VLOOKUP(Q51,$S$5:$U$10,3,FALSE) -> #N/A | U51: =VLOOKUP(R51,$S$5:$U$10,3,FALSE) -> #N/A | V51: =VLOOKUP(S51,$S$5:$U$10,3,FALSE) -> #N/A
A52: =TEXT(EDATE(TODAY(), ROW(A8) - 3), "yyyy/m") -> 2026/11 | B52: =INDEX(リバース占い!U:U, MATCH(TEXT(A52, "yyyy/m"), INDEX(TRIM(リバース占い!F:F), 0), 0)) -> 弁財天 | C52: =INDEX(リバース占い!V:V, MATCH(TEXT(A52, "yyyy/m"), INDEX(TRIM(リバース占い!F:F), 0), 0)) -> 才能がパッと花開き、今後の人生を左右する重要な決定を下す発展期。 | K52: =INDEX(リバース占い!M:M, MATCH(TEXT($A52, "yyyy/m"), INDEX(TRIM(リバース占い!$F:$F), 0), 0)) -> 準方位 | L52: =INDEX(リバース占い!N:N, MATCH(TEXT($A52, "yyyy/m"), INDEX(TRIM(リバース占い!$F:$F), 0), 0)) -> 害 | M52: =INDEX(リバース占い!O:O, MATCH(TEXT($A52, "yyyy/m"), INDEX(TRIM(リバース占い!$F:$F), 0), 0)) -> － | N52: =VLOOKUP(K52,$L$6:$P$27,2,FALSE) -> スクラム | O52: =VLOOKUP(L52,$L$6:$P$27,2,FALSE) -> ストレス | P52: =VLOOKUP(M52,$L$6:$P$27,2,FALSE) -> － | Q52: =INDEX(リバース占い!Q:Q, MATCH(TEXT($A52, "yyyy/m"), INDEX(TRIM(リバース占い!$F:$F), 0), 0)) | R52: =INDEX(リバース占い!R:R, MATCH(TEXT($A52, "yyyy/m"), INDEX(TRIM(リバース占い!$F:$F), 0), 0)) | S52: =INDEX(リバース占い!S:S, MATCH(TEXT($A52, "yyyy/m"), INDEX(TRIM(リバース占い!$F:$F), 0), 0)) | T52: =VLOOKUP(Q52,$S$5:$U$10,3,FALSE) -> #N/A | U52: =VLOOKUP(R52,$S$5:$U$10,3,FALSE) -> #N/A | V52: =VLOOKUP(S52,$S$5:$U$10,3,FALSE) -> #N/A
A53: =TEXT(EDATE(TODAY(), ROW(A9) - 3), "yyyy/m") -> 2026/12 | B53: =INDEX(リバース占い!U:U, MATCH(TEXT(A53, "yyyy/m"), INDEX(TRIM(リバース占い!F:F), 0), 0)) -> 曇天 | C53: =INDEX(リバース占い!V:V, MATCH(TEXT(A53, "yyyy/m"), INDEX(TRIM(リバース占い!F:F), 0), 0)) -> 運気の勢いに心身が追いつかない小休止。自己治癒の時期。 | K53: =INDEX(リバース占い!M:M, MATCH(TEXT($A53, "yyyy/m"), INDEX(TRIM(リバース占い!$F:$F), 0), 0)) -> 同 | L53: =INDEX(リバース占い!N:N, MATCH(TEXT($A53, "yyyy/m"), INDEX(TRIM(リバース占い!$F:$F), 0), 0)) -> 半会 | M53: =INDEX(リバース占い!O:O, MATCH(TEXT($A53, "yyyy/m"), INDEX(TRIM(リバース占い!$F:$F), 0), 0)) -> 破 | N53: =VLOOKUP(K53,$L$6:$P$27,2,FALSE) -> ブースト | O53: =VLOOKUP(L53,$L$6:$P$27,2,FALSE) -> シナジー | P53: =VLOOKUP(M53,$L$6:$P$27,2,FALSE) -> フリーズ | Q53: =INDEX(リバース占い!Q:Q, MATCH(TEXT($A53, "yyyy/m"), INDEX(TRIM(リバース占い!$F:$F), 0), 0)) | R53: =INDEX(リバース占い!R:R, MATCH(TEXT($A53, "yyyy/m"), INDEX(TRIM(リバース占い!$F:$F), 0), 0)) | S53: =INDEX(リバース占い!S:S, MATCH(TEXT($A53, "yyyy/m"), INDEX(TRIM(リバース占い!$F:$F), 0), 0)) | T53: =VLOOKUP(Q53,$S$5:$U$10,3,FALSE) -> #N/A | U53: =VLOOKUP(R53,$S$5:$U$10,3,FALSE) -> #N/A | V53: =VLOOKUP(S53,$S$5:$U$10,3,FALSE) -> #N/A
A54: =TEXT(EDATE(TODAY(), ROW(A10) - 3), "yyyy/m") -> 2027/1 | B54: =INDEX(リバース占い!U:U, MATCH(TEXT(A54, "yyyy/m"), INDEX(TRIM(リバース占い!F:F), 0), 0)) -> 韋駄天 | C54: =INDEX(リバース占い!V:V, MATCH(TEXT(A54, "yyyy/m"), INDEX(TRIM(リバース占い!F:F), 0), 0)) -> 運気絶頂。これまでの努力が実を結び、最高のスポットライトを浴びる。 | K54: =INDEX(リバース占い!M:M, MATCH(TEXT($A54, "yyyy/m"), INDEX(TRIM(リバース占い!$F:$F), 0), 0)) -> 支合 | L54: =INDEX(リバース占い!N:N, MATCH(TEXT($A54, "yyyy/m"), INDEX(TRIM(リバース占い!$F:$F), 0), 0)) -> － | M54: =INDEX(リバース占い!O:O, MATCH(TEXT($A54, "yyyy/m"), INDEX(TRIM(リバース占い!$F:$F), 0), 0)) -> 大半会 | N54: =VLOOKUP(K54,$L$6:$P$27,2,FALSE) -> バランス | O54: =VLOOKUP(L54,$L$6:$P$27,2,FALSE) -> － | P54: =VLOOKUP(M54,$L$6:$P$27,2,FALSE) -> フィーバー | Q54: =INDEX(リバース占い!Q:Q, MATCH(TEXT($A54, "yyyy/m"), INDEX(TRIM(リバース占い!$F:$F), 0), 0)) | R54: =INDEX(リバース占い!R:R, MATCH(TEXT($A54, "yyyy/m"), INDEX(TRIM(リバース占い!$F:$F), 0), 0)) -> 丙辛干合 | S54: =INDEX(リバース占い!S:S, MATCH(TEXT($A54, "yyyy/m"), INDEX(TRIM(リバース占い!$F:$F), 0), 0)) | T54: =VLOOKUP(Q54,$S$5:$U$10,3,FALSE) -> #N/A | U54: =VLOOKUP(R54,$S$5:$U$10,3,FALSE) -> デレ化 | V54: =VLOOKUP(S54,$S$5:$U$10,3,FALSE) -> #N/A
A55: =TEXT(EDATE(TODAY(), ROW(A11) - 3), "yyyy/m") -> 2027/2 | B55: =INDEX(リバース占い!U:U, MATCH(TEXT(A55, "yyyy/m"), INDEX(TRIM(リバース占い!F:F), 0), 0)) -> 伏魔天 | C55: =INDEX(リバース占い!V:V, MATCH(TEXT(A55, "yyyy/m"), INDEX(TRIM(リバース占い!F:F), 0), 0)) -> 強すぎる運気の反動で迷いや摩擦が生じる。理性と現状維持が必要な嵐。 | K55: =INDEX(リバース占い!M:M, MATCH(TEXT($A55, "yyyy/m"), INDEX(TRIM(リバース占い!$F:$F), 0), 0)) -> － | L55: =INDEX(リバース占い!N:N, MATCH(TEXT($A55, "yyyy/m"), INDEX(TRIM(リバース占い!$F:$F), 0), 0)) -> 天剋地冲 | M55: =INDEX(リバース占い!O:O, MATCH(TEXT($A55, "yyyy/m"), INDEX(TRIM(リバース占い!$F:$F), 0), 0)) -> － | N55: =VLOOKUP(K55,$L$6:$P$27,2,FALSE) -> － | O55: =VLOOKUP(L55,$L$6:$P$27,2,FALSE) -> ビックバン | P55: =VLOOKUP(M55,$L$6:$P$27,2,FALSE) -> － | Q55: =INDEX(リバース占い!Q:Q, MATCH(TEXT($A55, "yyyy/m"), INDEX(TRIM(リバース占い!$F:$F), 0), 0)) | R55: =INDEX(リバース占い!R:R, MATCH(TEXT($A55, "yyyy/m"), INDEX(TRIM(リバース占い!$F:$F), 0), 0)) | S55: =INDEX(リバース占い!S:S, MATCH(TEXT($A55, "yyyy/m"), INDEX(TRIM(リバース占い!$F:$F), 0), 0)) | T55: =VLOOKUP(Q55,$S$5:$U$10,3,FALSE) -> #N/A | U55: =VLOOKUP(R55,$S$5:$U$10,3,FALSE) -> #N/A | V55: =VLOOKUP(S55,$S$5:$U$10,3,FALSE) -> #N/A
A56: =TEXT(EDATE(TODAY(), ROW(A12) - 3), "yyyy/m") -> 2027/3 | B56: =INDEX(リバース占い!U:U, MATCH(TEXT(A56, "yyyy/m"), INDEX(TRIM(リバース占い!F:F), 0), 0)) -> 有頂天 | C56: =INDEX(リバース占い!V:V, MATCH(TEXT(A56, "yyyy/m"), INDEX(TRIM(リバース占い!F:F), 0), 0)) -> 第2の絶頂期。過去の縁が繋がり、周囲を巻き込み大きな成果を出す。 | K56: =INDEX(リバース占い!M:M, MATCH(TEXT($A56, "yyyy/m"), INDEX(TRIM(リバース占い!$F:$F), 0), 0)) -> 刑 | L56: =INDEX(リバース占い!N:N, MATCH(TEXT($A56, "yyyy/m"), INDEX(TRIM(リバース占い!$F:$F), 0), 0)) -> － | M56: =INDEX(リバース占い!O:O, MATCH(TEXT($A56, "yyyy/m"), INDEX(TRIM(リバース占い!$F:$F), 0), 0)) -> 対冲 | N56: =VLOOKUP(K56,$L$6:$P$27,2,FALSE) -> バトル | O56: =VLOOKUP(L56,$L$6:$P$27,2,FALSE) -> － | P56: =VLOOKUP(M56,$L$6:$P$27,2,FALSE) -> クラッシュ | Q56: =INDEX(リバース占い!Q:Q, MATCH(TEXT($A56, "yyyy/m"), INDEX(TRIM(リバース占い!$F:$F), 0), 0)) -> 戊癸干合 | R56: =INDEX(リバース占い!R:R, MATCH(TEXT($A56, "yyyy/m"), INDEX(TRIM(リバース占い!$F:$F), 0), 0)) | S56: =INDEX(リバース占い!S:S, MATCH(TEXT($A56, "yyyy/m"), INDEX(TRIM(リバース占い!$F:$F), 0), 0)) | T56: =VLOOKUP(Q56,$S$5:$U$10,3,FALSE) -> オトメ化 | U56: =VLOOKUP(R56,$S$5:$U$10,3,FALSE) -> #N/A | V56: =VLOOKUP(S56,$S$5:$U$10,3,FALSE) -> #N/A
A57: =TEXT(EDATE(TODAY(), ROW(A13) - 3), "yyyy/m") -> 2027/4 | B57: =INDEX(リバース占い!U:U, MATCH(TEXT(A57, "yyyy/m"), INDEX(TRIM(リバース占い!F:F), 0), 0)) -> 満天 | C57: =INDEX(リバース占い!V:V, MATCH(TEXT(A57, "yyyy/m"), INDEX(TRIM(リバース占い!F:F), 0), 0)) -> 収穫の喜び。物質や人脈などあらゆる財を蓄積し、強固な基盤を作る。 | K57: =INDEX(リバース占い!M:M, MATCH(TEXT($A57, "yyyy/m"), INDEX(TRIM(リバース占い!$F:$F), 0), 0)) -> 半会 | L57: =INDEX(リバース占い!N:N, MATCH(TEXT($A57, "yyyy/m"), INDEX(TRIM(リバース占い!$F:$F), 0), 0)) -> 半会 | M57: =INDEX(リバース占い!O:O, MATCH(TEXT($A57, "yyyy/m"), INDEX(TRIM(リバース占い!$F:$F), 0), 0)) -> 支合 | N57: =VLOOKUP(K57,$L$6:$P$27,2,FALSE) -> シナジー | O57: =VLOOKUP(L57,$L$6:$P$27,2,FALSE) -> シナジー | P57: =VLOOKUP(M57,$L$6:$P$27,2,FALSE) -> バランス | Q57: =INDEX(リバース占い!Q:Q, MATCH(TEXT($A57, "yyyy/m"), INDEX(TRIM(リバース占い!$F:$F), 0), 0)) | R57: =INDEX(リバース占い!R:R, MATCH(TEXT($A57, "yyyy/m"), INDEX(TRIM(リバース占い!$F:$F), 0), 0)) | S57: =INDEX(リバース占い!S:S, MATCH(TEXT($A57, "yyyy/m"), INDEX(TRIM(リバース占い!$F:$F), 0), 0)) | T57: =VLOOKUP(Q57,$S$5:$U$10,3,FALSE) -> #N/A | U57: =VLOOKUP(R57,$S$5:$U$10,3,FALSE) -> #N/A | V57: =VLOOKUP(S57,$S$5:$U$10,3,FALSE) -> #N/A
A59: 日天運 | N59: 家庭 | O59: 自分 | P59: 社会 | Q59: 家庭 | R59: 自分 | S59: 社会 | T59: 家庭 | U59: 自分 | V59: 社会
A60: =EOMONTH(TODAY(), -1) + 1 -> 46174 | B60: =INDEX(リバース占い!BM:BM, MATCH(A60, リバース占い!BA:BA, 0)) -> 暗天 | C60: =INDEX(リバース占い!BN:BN, MATCH(A60, リバース占い!BA:BA, 0)) -> 運気下降（運の冬入り）。孤独を感じやすいが水面下の自己鍛錬が必要。 | D60: =INDEX(リバース占い!BO:BO, MATCH(C60, リバース占い!BC:BC, 0)) -> #N/A | E60: =INDEX(リバース占い!BP:BP, MATCH(D60, リバース占い!BD:BD, 0)) -> #N/A | F60: =INDEX(リバース占い!BQ:BQ, MATCH(E60, リバース占い!BE:BE, 0)) -> #N/A | G60: =INDEX(リバース占い!BR:BR, MATCH(F60, リバース占い!BF:BF, 0)) -> #N/A | H60: =INDEX(リバース占い!BS:BS, MATCH(G60, リバース占い!BG:BG, 0)) -> #N/A | I60: =INDEX(リバース占い!BT:BT, MATCH(H60, リバース占い!BH:BH, 0)) -> #N/A | J60: =INDEX(リバース占い!BU:BU, MATCH(I60, リバース占い!BL:BL, 0)) -> #N/A | K60: =INDEX(リバース占い!BF:BF, MATCH($A60, リバース占い!$BA:$BA, 0)) -> 対冲 | L60: =INDEX(リバース占い!BG:BG, MATCH($A60, リバース占い!$BA:$BA, 0)) -> － | M60: =INDEX(リバース占い!BH:BH, MATCH($A60, リバース占い!$BA:$BA, 0)) -> － | N60: =VLOOKUP(K60,$L$6:$P$27,2,FALSE) -> クラッシュ | O60: =VLOOKUP(L60,$L$6:$P$27,2,FALSE) -> － | P60: =VLOOKUP(M60,$L$6:$P$27,2,FALSE) -> － | Q60: =INDEX(リバース占い!BI:BI, MATCH($A60, リバース占い!$BA:$BA, 0)) | R60: =INDEX(リバース占い!BJ:BJ, MATCH($A60, リバース占い!$BA:$BA, 0)) | S60: =INDEX(リバース占い!BK:BK, MATCH($A60, リバース占い!$BA:$BA, 0)) -> 丙辛干合 | T60: =VLOOKUP(Q60,$S$5:$U$10,3,FALSE) -> #N/A | U60: =VLOOKUP(R60,$S$5:$U$10,3,FALSE) -> #N/A | V60: =VLOOKUP(S60,$S$5:$U$10,3,FALSE) -> デレ化
A61: =IF(A60="","",IF(A60>=EOMONTH(TODAY(), 1),"",A60+1)) -> 46175 | B61: =INDEX(リバース占い!BM:BM, MATCH(A61, リバース占い!BA:BA, 0)) -> 大曇天 | C61: =INDEX(リバース占い!BN:BN, MATCH(A61, リバース占い!BA:BA, 0)) -> 運命の停止（運の真冬時期）。古い価値観を手放す究極の浄化期間。 | D61: =INDEX(リバース占い!BO:BO, MATCH(C61, リバース占い!BC:BC, 0)) -> #N/A | E61: =INDEX(リバース占い!BP:BP, MATCH(D61, リバース占い!BD:BD, 0)) -> #N/A | F61: =INDEX(リバース占い!BQ:BQ, MATCH(E61, リバース占い!BE:BE, 0)) -> #N/A | G61: =INDEX(リバース占い!BR:BR, MATCH(F61, リバース占い!BF:BF, 0)) -> #N/A | H61: =INDEX(リバース占い!BS:BS, MATCH(G61, リバース占い!BG:BG, 0)) -> #N/A | I61: =INDEX(リバース占い!BT:BT, MATCH(H61, リバース占い!BH:BH, 0)) -> #N/A | J61: =INDEX(リバース占い!BU:BU, MATCH(I61, リバース占い!BL:BL, 0)) -> #N/A | K61: =INDEX(リバース占い!BF:BF, MATCH($A61, リバース占い!$BA:$BA, 0)) -> 害 | L61: =INDEX(リバース占い!BG:BG, MATCH($A61, リバース占い!$BA:$BA, 0)) -> － | M61: =INDEX(リバース占い!BH:BH, MATCH($A61, リバース占い!$BA:$BA, 0)) -> － | N61: =VLOOKUP(K61,$L$6:$P$27,2,FALSE) -> ストレス | O61: =VLOOKUP(L61,$L$6:$P$27,2,FALSE) -> － | P61: =VLOOKUP(M61,$L$6:$P$27,2,FALSE) -> － | Q61: =INDEX(リバース占い!BI:BI, MATCH($A61, リバース占い!$BA:$BA, 0)) | R61: =INDEX(リバース占い!BJ:BJ, MATCH($A61, リバース占い!$BA:$BA, 0)) | S61: =INDEX(リバース占い!BK:BK, MATCH($A61, リバース占い!$BA:$BA, 0)) | T61: =VLOOKUP(Q61,$S$5:$U$10,3,FALSE) -> #N/A | U61: =VLOOKUP(R61,$S$5:$U$10,3,FALSE) -> #N/A | V61: =VLOOKUP(S61,$S$5:$U$10,3,FALSE) -> #N/A
A62: =IF(A61="","",IF(A61>=EOMONTH(TODAY(), 1),"",A61+1)) -> 46176 | B62: =INDEX(リバース占い!BM:BM, MATCH(A62, リバース占い!BA:BA, 0)) -> 雨天 | C62: =INDEX(リバース占い!BN:BN, MATCH(A62, リバース占い!BA:BA, 0)) -> カルマの精算。過去の執着をすべて洗い流し、次の春への準備を整える。 | D62: =INDEX(リバース占い!BO:BO, MATCH(C62, リバース占い!BC:BC, 0)) -> #N/A | E62: =INDEX(リバース占い!BP:BP, MATCH(D62, リバース占い!BD:BD, 0)) -> #N/A | F62: =INDEX(リバース占い!BQ:BQ, MATCH(E62, リバース占い!BE:BE, 0)) -> #N/A | G62: =INDEX(リバース占い!BR:BR, MATCH(F62, リバース占い!BF:BF, 0)) -> #N/A | H62: =INDEX(リバース占い!BS:BS, MATCH(G62, リバース占い!BG:BG, 0)) -> #N/A | I62: =INDEX(リバース占い!BT:BT, MATCH(H62, リバース占い!BH:BH, 0)) -> #N/A | J62: =INDEX(リバース占い!BU:BU, MATCH(I62, リバース占い!BL:BL, 0)) -> #N/A | K62: =INDEX(リバース占い!BF:BF, MATCH($A62, リバース占い!$BA:$BA, 0)) -> 大半会 | L62: =INDEX(リバース占い!BG:BG, MATCH($A62, リバース占い!$BA:$BA, 0)) -> 同 | M62: =INDEX(リバース占い!BH:BH, MATCH($A62, リバース占い!$BA:$BA, 0)) -> 準方位 | N62: =VLOOKUP(K62,$L$6:$P$27,2,FALSE) -> フィーバー | O62: =VLOOKUP(L62,$L$6:$P$27,2,FALSE) -> ブースト | P62: =VLOOKUP(M62,$L$6:$P$27,2,FALSE) -> スクラム | Q62: =INDEX(リバース占い!BI:BI, MATCH($A62, リバース占い!$BA:$BA, 0)) | R62: =INDEX(リバース占い!BJ:BJ, MATCH($A62, リバース占い!$BA:$BA, 0)) | S62: =INDEX(リバース占い!BK:BK, MATCH($A62, リバース占い!$BA:$BA, 0)) | T62: =VLOOKUP(Q62,$S$5:$U$10,3,FALSE) -> #N/A | U62: =VLOOKUP(R62,$S$5:$U$10,3,FALSE) -> #N/A | V62: =VLOOKUP(S62,$S$5:$U$10,3,FALSE) -> #N/A
A63: =IF(A62="","",IF(A62>=EOMONTH(TODAY(), 1),"",A62+1)) -> 46177 | B63: =INDEX(リバース占い!BM:BM, MATCH(A63, リバース占い!BA:BA, 0)) -> 起天 | C63: =INDEX(リバース占い!BN:BN, MATCH(A63, リバース占い!BA:BA, 0)) -> 運命の幕開け。過去を断ち切り新しい種をまく開拓期。 | D63: =INDEX(リバース占い!BO:BO, MATCH(C63, リバース占い!BC:BC, 0)) -> #N/A | E63: =INDEX(リバース占い!BP:BP, MATCH(D63, リバース占い!BD:BD, 0)) -> #N/A | F63: =INDEX(リバース占い!BQ:BQ, MATCH(E63, リバース占い!BE:BE, 0)) -> #N/A | G63: =INDEX(リバース占い!BR:BR, MATCH(F63, リバース占い!BF:BF, 0)) -> #N/A | H63: =INDEX(リバース占い!BS:BS, MATCH(G63, リバース占い!BG:BG, 0)) -> #N/A | I63: =INDEX(リバース占い!BT:BT, MATCH(H63, リバース占い!BH:BH, 0)) -> #N/A | J63: =INDEX(リバース占い!BU:BU, MATCH(I63, リバース占い!BL:BL, 0)) -> #N/A | K63: =INDEX(リバース占い!BF:BF, MATCH($A63, リバース占い!$BA:$BA, 0)) -> 破 | L63: =INDEX(リバース占い!BG:BG, MATCH($A63, リバース占い!$BA:$BA, 0)) -> 準方位 | M63: =INDEX(リバース占い!BH:BH, MATCH($A63, リバース占い!$BA:$BA, 0)) -> 自刑 | N63: =VLOOKUP(K63,$L$6:$P$27,2,FALSE) -> フリーズ | O63: =VLOOKUP(L63,$L$6:$P$27,2,FALSE) -> スクラム | P63: =VLOOKUP(M63,$L$6:$P$27,2,FALSE) -> セルフバトル | Q63: =INDEX(リバース占い!BI:BI, MATCH($A63, リバース占い!$BA:$BA, 0)) | R63: =INDEX(リバース占い!BJ:BJ, MATCH($A63, リバース占い!$BA:$BA, 0)) | S63: =INDEX(リバース占い!BK:BK, MATCH($A63, リバース占い!$BA:$BA, 0)) | T63: =VLOOKUP(Q63,$S$5:$U$10,3,FALSE) -> #N/A | U63: =VLOOKUP(R63,$S$5:$U$10,3,FALSE) -> #N/A | V63: =VLOOKUP(S63,$S$5:$U$10,3,FALSE) -> #N/A
A64: =IF(A63="","",IF(A63>=EOMONTH(TODAY(), 1),"",A63+1)) -> 46178 | B64: =INDEX(リバース占い!BM:BM, MATCH(A64, リバース占い!BA:BA, 0)) -> 吉祥天 | C64: =INDEX(リバース占い!BN:BN, MATCH(A64, リバース占い!BA:BA, 0)) -> まいた種が芽吹き、周囲の支援を受けて着実に育つ時期。 | D64: =INDEX(リバース占い!BO:BO, MATCH(C64, リバース占い!BC:BC, 0)) -> #N/A | E64: =INDEX(リバース占い!BP:BP, MATCH(D64, リバース占い!BD:BD, 0)) -> #N/A | F64: =INDEX(リバース占い!BQ:BQ, MATCH(E64, リバース占い!BE:BE, 0)) -> #N/A | G64: =INDEX(リバース占い!BR:BR, MATCH(F64, リバース占い!BF:BF, 0)) -> #N/A | H64: =INDEX(リバース占い!BS:BS, MATCH(G64, リバース占い!BG:BG, 0)) -> #N/A | I64: =INDEX(リバース占い!BT:BT, MATCH(H64, リバース占い!BH:BH, 0)) -> #N/A | J64: =INDEX(リバース占い!BU:BU, MATCH(I64, リバース占い!BL:BL, 0)) -> #N/A | K64: =INDEX(リバース占い!BF:BF, MATCH($A64, リバース占い!$BA:$BA, 0)) -> － | L64: =INDEX(リバース占い!BG:BG, MATCH($A64, リバース占い!$BA:$BA, 0)) -> 準方位 | M64: =INDEX(リバース占い!BH:BH, MATCH($A64, リバース占い!$BA:$BA, 0)) -> 害 | N64: =VLOOKUP(K64,$L$6:$P$27,2,FALSE) -> － | O64: =VLOOKUP(L64,$L$6:$P$27,2,FALSE) -> スクラム | P64: =VLOOKUP(M64,$L$6:$P$27,2,FALSE) -> ストレス | Q64: =INDEX(リバース占い!BI:BI, MATCH($A64, リバース占い!$BA:$BA, 0)) | R64: =INDEX(リバース占い!BJ:BJ, MATCH($A64, リバース占い!$BA:$BA, 0)) | S64: =INDEX(リバース占い!BK:BK, MATCH($A64, リバース占い!$BA:$BA, 0)) | T64: =VLOOKUP(Q64,$S$5:$U$10,3,FALSE) -> #N/A | U64: =VLOOKUP(R64,$S$5:$U$10,3,FALSE) -> #N/A | V64: =VLOOKUP(S64,$S$5:$U$10,3,FALSE) -> #N/A
A65: =IF(A64="","",IF(A64>=EOMONTH(TODAY(), 1),"",A64+1)) -> 46179 | B65: =INDEX(リバース占い!BM:BM, MATCH(A65, リバース占い!BA:BA, 0)) -> 弁財天 | C65: =INDEX(リバース占い!BN:BN, MATCH(A65, リバース占い!BA:BA, 0)) -> 才能がパッと花開き、今後の人生を左右する重要な決定を下す発展期。 | D65: =INDEX(リバース占い!BO:BO, MATCH(C65, リバース占い!BC:BC, 0)) -> #N/A | E65: =INDEX(リバース占い!BP:BP, MATCH(D65, リバース占い!BD:BD, 0)) -> #N/A | F65: =INDEX(リバース占い!BQ:BQ, MATCH(E65, リバース占い!BE:BE, 0)) -> #N/A | G65: =INDEX(リバース占い!BR:BR, MATCH(F65, リバース占い!BF:BF, 0)) -> #N/A | H65: =INDEX(リバース占い!BS:BS, MATCH(G65, リバース占い!BG:BG, 0)) -> #N/A | I65: =INDEX(リバース占い!BT:BT, MATCH(H65, リバース占い!BH:BH, 0)) -> #N/A | J65: =INDEX(リバース占い!BU:BU, MATCH(I65, リバース占い!BL:BL, 0)) -> #N/A | K65: =INDEX(リバース占い!BF:BF, MATCH($A65, リバース占い!$BA:$BA, 0)) -> 準方位 | L65: =INDEX(リバース占い!BG:BG, MATCH($A65, リバース占い!$BA:$BA, 0)) -> 害 | M65: =INDEX(リバース占い!BH:BH, MATCH($A65, リバース占い!$BA:$BA, 0)) -> － | N65: =VLOOKUP(K65,$L$6:$P$27,2,FALSE) -> スクラム | O65: =VLOOKUP(L65,$L$6:$P$27,2,FALSE) -> ストレス | P65: =VLOOKUP(M65,$L$6:$P$27,2,FALSE) -> － | Q65: =INDEX(リバース占い!BI:BI, MATCH($A65, リバース占い!$BA:$BA, 0)) | R65: =INDEX(リバース占い!BJ:BJ, MATCH($A65, リバース占い!$BA:$BA, 0)) -> 丙辛干合 | S65: =INDEX(リバース占い!BK:BK, MATCH($A65, リバース占い!$BA:$BA, 0)) | T65: =VLOOKUP(Q65,$S$5:$U$10,3,FALSE) -> #N/A | U65: =VLOOKUP(R65,$S$5:$U$10,3,FALSE) -> デレ化 | V65: =VLOOKUP(S65,$S$5:$U$10,3,FALSE) -> #N/A
A66: =IF(A65="","",IF(A65>=EOMONTH(TODAY(), 1),"",A65+1)) -> 46180 | B66: =INDEX(リバース占い!BM:BM, MATCH(A66, リバース占い!BA:BA, 0)) -> 曇天 | C66: =INDEX(リバース占い!BN:BN, MATCH(A66, リバース占い!BA:BA, 0)) -> 運気の勢いに心身が追いつかない小休止。自己治癒の時期。 | D66: =INDEX(リバース占い!BO:BO, MATCH(C66, リバース占い!BC:BC, 0)) -> #N/A | E66: =INDEX(リバース占い!BP:BP, MATCH(D66, リバース占い!BD:BD, 0)) -> #N/A | F66: =INDEX(リバース占い!BQ:BQ, MATCH(E66, リバース占い!BE:BE, 0)) -> #N/A | G66: =INDEX(リバース占い!BR:BR, MATCH(F66, リバース占い!BF:BF, 0)) -> #N/A | H66: =INDEX(リバース占い!BS:BS, MATCH(G66, リバース占い!BG:BG, 0)) -> #N/A | I66: =INDEX(リバース占い!BT:BT, MATCH(H66, リバース占い!BH:BH, 0)) -> #N/A | J66: =INDEX(リバース占い!BU:BU, MATCH(I66, リバース占い!BL:BL, 0)) -> #N/A | K66: =INDEX(リバース占い!BF:BF, MATCH($A66, リバース占い!$BA:$BA, 0)) -> 同 | L66: =INDEX(リバース占い!BG:BG, MATCH($A66, リバース占い!$BA:$BA, 0)) -> 半会 | M66: =INDEX(リバース占い!BH:BH, MATCH($A66, リバース占い!$BA:$BA, 0)) -> 破 | N66: =VLOOKUP(K66,$L$6:$P$27,2,FALSE) -> ブースト | O66: =VLOOKUP(L66,$L$6:$P$27,2,FALSE) -> シナジー | P66: =VLOOKUP(M66,$L$6:$P$27,2,FALSE) -> フリーズ | Q66: =INDEX(リバース占い!BI:BI, MATCH($A66, リバース占い!$BA:$BA, 0)) | R66: =INDEX(リバース占い!BJ:BJ, MATCH($A66, リバース占い!$BA:$BA, 0)) | S66: =INDEX(リバース占い!BK:BK, MATCH($A66, リバース占い!$BA:$BA, 0)) | T66: =VLOOKUP(Q66,$S$5:$U$10,3,FALSE) -> #N/A | U66: =VLOOKUP(R66,$S$5:$U$10,3,FALSE) -> #N/A | V66: =VLOOKUP(S66,$S$5:$U$10,3,FALSE) -> #N/A
A67: =IF(A66="","",IF(A66>=EOMONTH(TODAY(), 1),"",A66+1)) -> 46181 | B67: =INDEX(リバース占い!BM:BM, MATCH(A67, リバース占い!BA:BA, 0)) -> 韋駄天 | C67: =INDEX(リバース占い!BN:BN, MATCH(A67, リバース占い!BA:BA, 0)) -> 運気絶頂。これまでの努力が実を結び、最高のスポットライトを浴びる。 | D67: =INDEX(リバース占い!BO:BO, MATCH(C67, リバース占い!BC:BC, 0)) -> #N/A | E67: =INDEX(リバース占い!BP:BP, MATCH(D67, リバース占い!BD:BD, 0)) -> #N/A | F67: =INDEX(リバース占い!BQ:BQ, MATCH(E67, リバース占い!BE:BE, 0)) -> #N/A | G67: =INDEX(リバース占い!BR:BR, MATCH(F67, リバース占い!BF:BF, 0)) -> #N/A | H67: =INDEX(リバース占い!BS:BS, MATCH(G67, リバース占い!BG:BG, 0)) -> #N/A | I67: =INDEX(リバース占い!BT:BT, MATCH(H67, リバース占い!BH:BH, 0)) -> #N/A | J67: =INDEX(リバース占い!BU:BU, MATCH(I67, リバース占い!BL:BL, 0)) -> #N/A | K67: =INDEX(リバース占い!BF:BF, MATCH($A67, リバース占い!$BA:$BA, 0)) -> 支合 | L67: =INDEX(リバース占い!BG:BG, MATCH($A67, リバース占い!$BA:$BA, 0)) -> － | M67: =INDEX(リバース占い!BH:BH, MATCH($A67, リバース占い!$BA:$BA, 0)) -> 半会 | N67: =VLOOKUP(K67,$L$6:$P$27,2,FALSE) -> バランス | O67: =VLOOKUP(L67,$L$6:$P$27,2,FALSE) -> － | P67: =VLOOKUP(M67,$L$6:$P$27,2,FALSE) -> シナジー | Q67: =INDEX(リバース占い!BI:BI, MATCH($A67, リバース占い!$BA:$BA, 0)) -> 戊癸干合 | R67: =INDEX(リバース占い!BJ:BJ, MATCH($A67, リバース占い!$BA:$BA, 0)) | S67: =INDEX(リバース占い!BK:BK, MATCH($A67, リバース占い!$BA:$BA, 0)) | T67: =VLOOKUP(Q67,$S$5:$U$10,3,FALSE) -> オトメ化 | U67: =VLOOKUP(R67,$S$5:$U$10,3,FALSE) -> #N/A | V67: =VLOOKUP(S67,$S$5:$U$10,3,FALSE) -> #N/A
A68: =IF(A67="","",IF(A67>=EOMONTH(TODAY(), 1),"",A67+1)) -> 46182 | B68: =INDEX(リバース占い!BM:BM, MATCH(A68, リバース占い!BA:BA, 0)) -> 伏魔天 | C68: =INDEX(リバース占い!BN:BN, MATCH(A68, リバース占い!BA:BA, 0)) -> 強すぎる運気の反動で迷いや摩擦が生じる。理性と現状維持が必要な嵐。 | D68: =INDEX(リバース占い!BO:BO, MATCH(C68, リバース占い!BC:BC, 0)) -> #N/A | E68: =INDEX(リバース占い!BP:BP, MATCH(D68, リバース占い!BD:BD, 0)) -> #N/A | F68: =INDEX(リバース占い!BQ:BQ, MATCH(E68, リバース占い!BE:BE, 0)) -> #N/A | G68: =INDEX(リバース占い!BR:BR, MATCH(F68, リバース占い!BF:BF, 0)) -> #N/A | H68: =INDEX(リバース占い!BS:BS, MATCH(G68, リバース占い!BG:BG, 0)) -> #N/A | I68: =INDEX(リバース占い!BT:BT, MATCH(H68, リバース占い!BH:BH, 0)) -> #N/A | J68: =INDEX(リバース占い!BU:BU, MATCH(I68, リバース占い!BL:BL, 0)) -> #N/A | K68: =INDEX(リバース占い!BF:BF, MATCH($A68, リバース占い!$BA:$BA, 0)) -> － | L68: =INDEX(リバース占い!BG:BG, MATCH($A68, リバース占い!$BA:$BA, 0)) -> 対冲 | M68: =INDEX(リバース占い!BH:BH, MATCH($A68, リバース占い!$BA:$BA, 0)) -> － | N68: =VLOOKUP(K68,$L$6:$P$27,2,FALSE) -> － | O68: =VLOOKUP(L68,$L$6:$P$27,2,FALSE) -> クラッシュ | P68: =VLOOKUP(M68,$L$6:$P$27,2,FALSE) -> － | Q68: =INDEX(リバース占い!BI:BI, MATCH($A68, リバース占い!$BA:$BA, 0)) | R68: =INDEX(リバース占い!BJ:BJ, MATCH($A68, リバース占い!$BA:$BA, 0)) | S68: =INDEX(リバース占い!BK:BK, MATCH($A68, リバース占い!$BA:$BA, 0)) | T68: =VLOOKUP(Q68,$S$5:$U$10,3,FALSE) -> #N/A | U68: =VLOOKUP(R68,$S$5:$U$10,3,FALSE) -> #N/A | V68: =VLOOKUP(S68,$S$5:$U$10,3,FALSE) -> #N/A
A69: =IF(A68="","",IF(A68>=EOMONTH(TODAY(), 1),"",A68+1)) -> 46183 | B69: =INDEX(リバース占い!BM:BM, MATCH(A69, リバース占い!BA:BA, 0)) -> 有頂天 | C69: =INDEX(リバース占い!BN:BN, MATCH(A69, リバース占い!BA:BA, 0)) -> 第2の絶頂期。過去の縁が繋がり、周囲を巻き込み大きな成果を出す。 | D69: =INDEX(リバース占い!BO:BO, MATCH(C69, リバース占い!BC:BC, 0)) -> #N/A | E69: =INDEX(リバース占い!BP:BP, MATCH(D69, リバース占い!BD:BD, 0)) -> #N/A | F69: =INDEX(リバース占い!BQ:BQ, MATCH(E69, リバース占い!BE:BE, 0)) -> #N/A | G69: =INDEX(リバース占い!BR:BR, MATCH(F69, リバース占い!BF:BF, 0)) -> #N/A | H69: =INDEX(リバース占い!BS:BS, MATCH(G69, リバース占い!BG:BG, 0)) -> #N/A | I69: =INDEX(リバース占い!BT:BT, MATCH(H69, リバース占い!BH:BH, 0)) -> #N/A | J69: =INDEX(リバース占い!BU:BU, MATCH(I69, リバース占い!BL:BL, 0)) -> #N/A | K69: =INDEX(リバース占い!BF:BF, MATCH($A69, リバース占い!$BA:$BA, 0)) -> 刑 | L69: =INDEX(リバース占い!BG:BG, MATCH($A69, リバース占い!$BA:$BA, 0)) -> － | M69: =INDEX(リバース占い!BH:BH, MATCH($A69, リバース占い!$BA:$BA, 0)) -> 天剋地冲 | N69: =VLOOKUP(K69,$L$6:$P$27,2,FALSE) -> バトル | O69: =VLOOKUP(L69,$L$6:$P$27,2,FALSE) -> － | P69: =VLOOKUP(M69,$L$6:$P$27,2,FALSE) -> ビックバン | Q69: =INDEX(リバース占い!BI:BI, MATCH($A69, リバース占い!$BA:$BA, 0)) | R69: =INDEX(リバース占い!BJ:BJ, MATCH($A69, リバース占い!$BA:$BA, 0)) | S69: =INDEX(リバース占い!BK:BK, MATCH($A69, リバース占い!$BA:$BA, 0)) | T69: =VLOOKUP(Q69,$S$5:$U$10,3,FALSE) -> #N/A | U69: =VLOOKUP(R69,$S$5:$U$10,3,FALSE) -> #N/A | V69: =VLOOKUP(S69,$S$5:$U$10,3,FALSE) -> #N/A
A70: =IF(A69="","",IF(A69>=EOMONTH(TODAY(), 1),"",A69+1)) -> 46184 | B70: =INDEX(リバース占い!BM:BM, MATCH(A70, リバース占い!BA:BA, 0)) -> 満天 | C70: =INDEX(リバース占い!BN:BN, MATCH(A70, リバース占い!BA:BA, 0)) -> 収穫の喜び。物質や人脈などあらゆる財を蓄積し、強固な基盤を作る。 | D70: =INDEX(リバース占い!BO:BO, MATCH(C70, リバース占い!BC:BC, 0)) -> #N/A | E70: =INDEX(リバース占い!BP:BP, MATCH(D70, リバース占い!BD:BD, 0)) -> #N/A | F70: =INDEX(リバース占い!BQ:BQ, MATCH(E70, リバース占い!BE:BE, 0)) -> #N/A | G70: =INDEX(リバース占い!BR:BR, MATCH(F70, リバース占い!BF:BF, 0)) -> #N/A | H70: =INDEX(リバース占い!BS:BS, MATCH(G70, リバース占い!BG:BG, 0)) -> #N/A | I70: =INDEX(リバース占い!BT:BT, MATCH(H70, リバース占い!BH:BH, 0)) -> #N/A | J70: =INDEX(リバース占い!BU:BU, MATCH(I70, リバース占い!BL:BL, 0)) -> #N/A | K70: =INDEX(リバース占い!BF:BF, MATCH($A70, リバース占い!$BA:$BA, 0)) -> 半会 | L70: =INDEX(リバース占い!BG:BG, MATCH($A70, リバース占い!$BA:$BA, 0)) -> 大半会 | M70: =INDEX(リバース占い!BH:BH, MATCH($A70, リバース占い!$BA:$BA, 0)) -> 支合 | N70: =VLOOKUP(K70,$L$6:$P$27,2,FALSE) -> シナジー | O70: =VLOOKUP(L70,$L$6:$P$27,2,FALSE) -> フィーバー | P70: =VLOOKUP(M70,$L$6:$P$27,2,FALSE) -> バランス | Q70: =INDEX(リバース占い!BI:BI, MATCH($A70, リバース占い!$BA:$BA, 0)) | R70: =INDEX(リバース占い!BJ:BJ, MATCH($A70, リバース占い!$BA:$BA, 0)) | S70: =INDEX(リバース占い!BK:BK, MATCH($A70, リバース占い!$BA:$BA, 0)) -> 丙辛干合 | T70: =VLOOKUP(Q70,$S$5:$U$10,3,FALSE) -> #N/A | U70: =VLOOKUP(R70,$S$5:$U$10,3,FALSE) -> #N/A | V70: =VLOOKUP(S70,$S$5:$U$10,3,FALSE) -> デレ化
A71: =IF(A70="","",IF(A70>=EOMONTH(TODAY(), 1),"",A70+1)) -> 46185 | B71: =INDEX(リバース占い!BM:BM, MATCH(A71, リバース占い!BA:BA, 0)) -> 静天 | C71: =INDEX(リバース占い!BN:BN, MATCH(A71, リバース占い!BA:BA, 0)) -> 成果が出揃う。精神的な安定と充実の中で平和に人生を俯瞰する時期。 | D71: =INDEX(リバース占い!BO:BO, MATCH(C71, リバース占い!BC:BC, 0)) -> #N/A | E71: =INDEX(リバース占い!BP:BP, MATCH(D71, リバース占い!BD:BD, 0)) -> #N/A | F71: =INDEX(リバース占い!BQ:BQ, MATCH(E71, リバース占い!BE:BE, 0)) -> #N/A | G71: =INDEX(リバース占い!BR:BR, MATCH(F71, リバース占い!BF:BF, 0)) -> #N/A | H71: =INDEX(リバース占い!BS:BS, MATCH(G71, リバース占い!BG:BG, 0)) -> #N/A | I71: =INDEX(リバース占い!BT:BT, MATCH(H71, リバース占い!BH:BH, 0)) -> #N/A | J71: =INDEX(リバース占い!BU:BU, MATCH(I71, リバース占い!BL:BL, 0)) -> #N/A | K71: =INDEX(リバース占い!BF:BF, MATCH($A71, リバース占い!$BA:$BA, 0)) -> － | L71: =INDEX(リバース占い!BG:BG, MATCH($A71, リバース占い!$BA:$BA, 0)) -> 支合 | M71: =INDEX(リバース占い!BH:BH, MATCH($A71, リバース占い!$BA:$BA, 0)) -> 半会 | N71: =VLOOKUP(K71,$L$6:$P$27,2,FALSE) -> － | O71: =VLOOKUP(L71,$L$6:$P$27,2,FALSE) -> バランス | P71: =VLOOKUP(M71,$L$6:$P$27,2,FALSE) -> シナジー | Q71: =INDEX(リバース占い!BI:BI, MATCH($A71, リバース占い!$BA:$BA, 0)) | R71: =INDEX(リバース占い!BJ:BJ, MATCH($A71, リバース占い!$BA:$BA, 0)) | S71: =INDEX(リバース占い!BK:BK, MATCH($A71, リバース占い!$BA:$BA, 0)) | T71: =VLOOKUP(Q71,$S$5:$U$10,3,FALSE) -> #N/A | U71: =VLOOKUP(R71,$S$5:$U$10,3,FALSE) -> #N/A | V71: =VLOOKUP(S71,$S$5:$U$10,3,FALSE) -> #N/A
A72: =IF(A71="","",IF(A71>=EOMONTH(TODAY(), 1),"",A71+1)) -> 46186 | B72: =INDEX(リバース占い!BM:BM, MATCH(A72, リバース占い!BA:BA, 0)) -> 暗天 | C72: =INDEX(リバース占い!BN:BN, MATCH(A72, リバース占い!BA:BA, 0)) -> 運気下降（運の冬入り）。孤独を感じやすいが水面下の自己鍛錬が必要。 | D72: =INDEX(リバース占い!BO:BO, MATCH(C72, リバース占い!BC:BC, 0)) -> #N/A | E72: =INDEX(リバース占い!BP:BP, MATCH(D72, リバース占い!BD:BD, 0)) -> #N/A | F72: =INDEX(リバース占い!BQ:BQ, MATCH(E72, リバース占い!BE:BE, 0)) -> #N/A | G72: =INDEX(リバース占い!BR:BR, MATCH(F72, リバース占い!BF:BF, 0)) -> #N/A | H72: =INDEX(リバース占い!BS:BS, MATCH(G72, リバース占い!BG:BG, 0)) -> #N/A | I72: =INDEX(リバース占い!BT:BT, MATCH(H72, リバース占い!BH:BH, 0)) -> #N/A | J72: =INDEX(リバース占い!BU:BU, MATCH(I72, リバース占い!BL:BL, 0)) -> #N/A | K72: =INDEX(リバース占い!BF:BF, MATCH($A72, リバース占い!$BA:$BA, 0)) -> 納音 | L72: =INDEX(リバース占い!BG:BG, MATCH($A72, リバース占い!$BA:$BA, 0)) -> － | M72: =INDEX(リバース占い!BH:BH, MATCH($A72, リバース占い!$BA:$BA, 0)) -> － | N72: =VLOOKUP(K72,$L$6:$P$27,2,FALSE) -> ブレーキ | O72: =VLOOKUP(L72,$L$6:$P$27,2,FALSE) -> － | P72: =VLOOKUP(M72,$L$6:$P$27,2,FALSE) -> － | Q72: =INDEX(リバース占い!BI:BI, MATCH($A72, リバース占い!$BA:$BA, 0)) | R72: =INDEX(リバース占い!BJ:BJ, MATCH($A72, リバース占い!$BA:$BA, 0)) | S72: =INDEX(リバース占い!BK:BK, MATCH($A72, リバース占い!$BA:$BA, 0)) | T72: =VLOOKUP(Q72,$S$5:$U$10,3,FALSE) -> #N/A | U72: =VLOOKUP(R72,$S$5:$U$10,3,FALSE) -> #N/A | V72: =VLOOKUP(S72,$S$5:$U$10,3,FALSE) -> #N/A
... A124: =IF(A123="","",IF(A123>=EOMONTH(TODAY(), 1),"",A123+1)) | B124: =INDEX(リバース占い!BM:BM, MATCH(A124, リバース占い!BA:BA, 0)) -> #N/A | C124: =INDEX(リバース占い!BN:BN, MATCH(A124, リバース占い!BA:BA, 0)) -> #N/A | D124: =INDEX(リバース占い!BO:BO, MATCH(C124, リバース占い!BC:BC, 0)) -> #N/A | E124: =INDEX(リバース占い!BP:BP, MATCH(D124, リバース占い!BD:BD, 0)) -> #N/A | F124: =INDEX(リバース占い!BQ:BQ, MATCH(E124, リバース占い!BE:BE, 0)) -> #N/A | G124: =INDEX(リバース占い!BR:BR, MATCH(F124, リバース占い!BF:BF, 0)) -> #N/A | H124: =INDEX(リバース占い!BS:BS, MATCH(G124, リバース占い!BG:BG, 0)) -> #N/A | I124: =INDEX(リバース占い!BT:BT, MATCH(H124, リバース占い!BH:BH, 0)) -> #N/A | J124: =INDEX(リバース占い!BU:BU, MATCH(I124, リバース占い!BL:BL, 0)) -> #N/A | K124: =INDEX(リバース占い!BF:BF, MATCH($A124, リバース占い!$BA:$BA, 0)) -> #N/A | L124: =INDEX(リバース占い!BG:BG, MATCH($A124, リバース占い!$BA:$BA, 0)) -> #N/A | M124: =INDEX(リバース占い!BH:BH, MATCH($A124, リバース占い!$BA:$BA, 0)) -> #N/A | N124: =VLOOKUP(K124,$L$6:$P$27,2,FALSE) -> #N/A | O124: =VLOOKUP(L124,$L$6:$P$27,2,FALSE) -> #N/A | P124: =VLOOKUP(M124,$L$6:$P$27,2,FALSE) -> #N/A | Q124: =INDEX(リバース占い!BI:BI, MATCH($A124, リバース占い!$BA:$BA, 0)) -> #N/A | R124: =INDEX(リバース占い!BJ:BJ, MATCH($A124, リバース占い!$BA:$BA, 0)) -> #N/A | S124: =INDEX(リバース占い!BK:BK, MATCH($A124, リバース占い!$BA:$BA, 0)) -> #N/A | T124: =VLOOKUP(Q124,$S$5:$U$10,3,FALSE) -> #N/A | U124: =VLOOKUP(R124,$S$5:$U$10,3,FALSE) -> #N/A | V124: =VLOOKUP(S124,$S$5:$U$10,3,FALSE) -> #N/A
Q125: =INDEX(リバース占い!BI:BI, MATCH($A125, リバース占い!$BA:$BA, 0)) -> #N/A | R125: =INDEX(リバース占い!BJ:BJ, MATCH($A125, リバース占い!$BA:$BA, 0)) -> #N/A | S125: =INDEX(リバース占い!BK:BK, MATCH($A125, リバース占い!$BA:$BA, 0)) -> #N/A | T125: =VLOOKUP(Q125,$S$5:$U$10,3,FALSE) -> #N/A | U125: =VLOOKUP(R125,$S$5:$U$10,3,FALSE) -> #N/A | V125: =VLOOKUP(S125,$S$5:$U$10,3,FALSE) -> #N/A
B128: 干合名 | C128: 化気 | D128: キャラ変 | E128: ステータス | F128: 【日干】相手・関係性の変化（現実のパートナーシップ） | G128: 【月干】自分・心境の変化（恋愛観・精神面） | H128: 【年干】出会い・社会面の変化（出会いの場・外からの見え方） | I128: 【変化の根拠】なぜそうなるのか
B129: 甲己干合 | C129: 土化 | D129: オカン化 | E129: 未婚(相手無) | F129: 「真面目な相手をロックオン」堅実で浮気しないタイプを選ぶ | G129: 「遊びは卒業！ド安定志向」刺激より安心感と誠実さを求める | H129: 「手堅い出会いと信用アップ」職場など真面目な場での出会い | I129: 木と土が交わり「不動の土」になるため。浮ついた気が消え、保護者のような保守性が強まる。
B130: 甲己干合 | C130: 土化 | D130: オカン化 | E130: 未婚(相手有) | F130: 「恋人から人生の相棒へ」同棲など生活の基盤が固まる | G130: 「プロポーズ待ち！結婚願望」恋人から「家族」になりたい | H130: 「親や会社への公式な紹介」交際を公にし社会的な信用を得る | I130: 恋愛という流動的な状態から、法的・社会的な「定着・固定」へと向かうため。
B131: 甲己干合 | C131: 土化 | D131: オカン化 | E131: 既婚(夫婦) | F131: 「盤石！揺るがない家族の絆」生活ルールが整った安全地帯に | G131: 「マイホーム第一主義へ」個人の楽しみより家庭の平和を優先 | H131: 「おしどり夫婦認定」世間から安定した夫婦と評価される | I131: 土性が極まり、変化や刺激を嫌う「現状維持と安定の防衛本能」が強く働くため。
B132: 乙庚干合 | C132: 金化 | D132: ツンツン化 | E132: 未婚(相手無) | F132: 「信頼度100%の相手確保」有言実行でスジの通った人との縁 | G132: 「無駄撃ち終了！本気モード」この人以外はバッサリ斬る | H132: 「義理と約束の出会い」信頼できる人からの確実な紹介 | I132: 柔軟な草木が「鋼（金）」になるため。迷いや妥協を刃物で断ち切り、本物だけを鋭く見極める。
B133: 乙庚干合 | C133: 金化 | D133: ツンツン化 | E133: 未婚(相手有) | F133: 「白黒ハッキリ！運命のジャッジ」結婚か別れかズルズルを清算 | G133: 「優柔不断終了！覚悟完了」この人と生きるという強い決意 | H133: 「婚約など公的な契約を結ぶ」後戻りできない確固たる約束を交わす | I133: 刃物の性質が発揮され、曖昧な状態を許さず白黒つけるシビアな決断力が宿るため。
B134: 乙庚干合 | C134: 金化 | D134: ツンツン化 | E134: 既婚(夫婦) | F134: 「なぁなぁ解消！絆の再構築」悪習慣を断ち切りルールを再徹底 | G134: 「伴侶への義理堅さ再確認」家族を守り抜くという鋼の信念 | H134: 「夫婦揃っての社会的責任」夫婦で協力して社会的な義務を果たす | I134: 金性が持つ義理・責任が強調され、一度結んだ契約を鋼のように硬く守り抜くため。
B135: 丙辛干合 | C135: 水化 | D135: デレ化 | E135: 未婚(相手無) | F135: 「素を見せられる相手との遭遇」見栄を張らない等身大の相手と惹かれ合う | G135: 「強がり解除！甘えん坊化」エゴが消え、自分を委ねられる恋へ | H135: 「玉の輿！ステータス激変」華やかな場でのセレブな恋の展開 | I135: 太陽と宝石が「柔軟な水」に溶けるため。強い自我やプライドが消え、相手の器にスッポリ収まる。
B136: 丙辛干合 | C136: 水化 | D136: デレ化 | E136: 未婚(相手有) | F136: 「主導権争い終了！深い愛情」勝ち負けのない思いやりの関係へ | G136: 「プライド崩壊！どっぷり尽くす」意地を張るのをやめ相手に尽くす | H136: 「誰もが羨む美男美女カップル」SNS等で映える華やかな交際 | I136: 融和・浸透のエネルギーが働き、互いの境界線が溶けて損得勘定のない情愛で混ざり合うため。
B137: 丙辛干合 | C137: 水化 | D137: デレ化 | E137: 既婚(夫婦) | F137: 「潤い復活！思いやりの生活」ギスギスした空気が消え優しさに満ちる | G137: 「意地っ張りからデレ顔へ」配偶者に対して驚くほど素直になる | H137: 「憧れのパワーカップル化」洗練された夫婦として周囲の憧れを集める | I137: 乾いた関係に「潤い」が戻り、形やルールにこだわらない思いやりのある関係へと柔軟に変化するため。
B138: 丁壬干合 | C138: 木化 | D138: エロ化 | E138: 未婚(相手無) | F138: 「フェロモン全開でターゲット確保」強烈な色気で大恋愛を引き寄せる | G138: 「恋に落ちたい！恋愛至上主義」理屈より運命的な引力を渇望する | H138: 「ドラマチック＆危険な引力」非日常空間での出会いや危険な恋 | I138: 炎と水が交わり「生命（木）」が誕生するため。理性を超えた本能的な男女の引力（エロス）が爆発する。
B139: 丁壬干合 | C139: 木化 | D139: エロ化 | E139: 未婚(相手有) | F139: 「四六時中ベッタリ！一心同体」相手の色に染まり深く絡み合う | G139: 「理性喪失！盲目的な愛」周りが見えないほどドップリ沼る | H139: 「周囲を巻き込む大熱愛」良くも悪くもドラマチックな展開が波及 | I139: ツル草のように絡みつく性質が発揮され、互いの領域に深く根を張り、理屈では離れられなくなるため。
... B143: 戊癸干合 | C143: 火化 | D143: オトメ化 | E143: 既婚(夫婦) | F143: 「まさかの熱愛！マンネリ打破」冷え切った関係に火がつき劇的に盛り上がる | G143: 「事務的ルーティンに革命を」冷めた日常に飽き突発的な変化を仕掛ける | H143: 「夫婦で大飛躍のサプライズ」突然の抜擢や成功など予測不能な展開 | I143: 燃焼・起爆のエネルギーが、ルーティン化した日常を破壊し、劇的な変化や情熱を強制的に生み出すため。

Sheet リバース占い
E2: 氏名 | I2: 生年 | K2: 生月 | L2: 生日 | M2: 性別 | O2: 28828 | AJ2: 数理法（％）
I3: 1981 | K3: 9 | L3: 7 | M3: 男 | AJ3: 干 | AK3: 干 数 | AL3: 星 | AN3: 日干入 単価 | AO3: 日干入 合計 | AP3: 日干 なし | AQ3: 剋線
F5: =I139 -> 25 | G5: =I141 -> 33 | H5: =H137 -> 58 | L5: =I129 -> 調舒星 | N5: =VLOOKUP(I133,$BQ$191:$BT$202,2,FALSE) -> 0 | AG5: =VLOOKUP(LEFT(L5,3),$AN$220:$AO$229,2,FALSE) -> 火 | AJ5: =VLOOKUP(AL5&$F$6,$A$155:$D$254,4,FALSE) -> 甲 | AK5: =HLOOKUP(AJ5,$BV$136:$CG$146,11,FALSE) -> 0 | AL5: =B150 -> 車騎星 | AN5: =ROUND(HLOOKUP(AJ5,$BV$147:$CG$157,11,FALSE)/$CH$157*100/IF(AK5=0,1,AK5),0) -> 0 | AO5: =ROUND(HLOOKUP(AJ5,$BV$147:$CG$157,11,FALSE)/$CH$157*100/IF(AK5=0,1,AK5),0)*AK5 -> 0 | AP5: =ROUND(HLOOKUP(AJ5,$BV$147:$CG$155,9,FALSE)/$CH$155*100,0) -> 0 | AQ5: =[1]意識と無意識!G4 -> 0 | BW5: ↓誕生日入力↓ | BX5: 性別
E6: =IF(F5<11,"戌",IF(F5<21,"申",IF(F5<31,"午",IF(F5<41,"辰",IF(F5<51,"寅","子"))))) -> 午 | F6: =VLOOKUP($F$5,$AG$140:$AN$200,8,FALSE) -> 戊 | G6: =VLOOKUP($G$5,$AG$140:$AN$200,8,FALSE) -> 丙 | H6: =VLOOKUP($H$5,$AG$140:$AN$200,8,FALSE) -> 辛 | J6: =IF(AL202=1,G130,IF(AL202=2,G131,G132)) -> 司禄星 | L6: =IF(AM202=1,H130,IF(AM202=2,H131,H132)) -> 鳳閣星 | N6: =IF(AN202=1,I130,IF(AN202=2,I131,I132)) -> 調舒星 | V6: １２天運 | W6: 内容 | AF6: =VLOOKUP(LEFT(J6,3),$AN$220:$AO$229,2,FALSE) -> 土 | AG6: =VLOOKUP(LEFT(L6,3),AN$220:$AO$229,2,FALSE) -> 火 | AH6: =VLOOKUP(LEFT(N6,3),$AN$220:$AO$229,2,FALSE) -> 火 | AJ6: =VLOOKUP(AL6&$F$6,$A$155:$D$254,4,FALSE) -> 乙 | AK6: =HLOOKUP(AJ6,$BV$136:$CG$146,11,FALSE) -> 0 | AL6: =B149 -> 牽牛星 | AN6: =ROUND(HLOOKUP(AJ6,$BV$147:$CG$157,11,FALSE)/$CH$157*100/IF(AK6=0,1,AK6),0) -> 0 | AO6: =ROUND(HLOOKUP(AJ6,$BV$147:$CG$157,11,FALSE)/$CH$157*100/IF(AK6=0,1,AK6),0)*AK6 -> 0 | AP6: =ROUND(HLOOKUP(AJ6,$BV$147:$CG$155,9,FALSE)/$CH$155*100,0) -> 0 | AQ6: =[1]意識と無意識!G5 -> 0 | BW6: =[1]五指裏干支占い!D2 -> 29836 | BX6: =[1]五指裏干支占い!E2 -> 男
E7: =IF(F5<11,"亥",IF(F5<21,"酉",IF(F5<31,"未",IF(F5<41,"巳",IF(F5<51,"卯","丑"))))) -> 未 | F7: =VLOOKUP($F$5,$AG$140:$AM$199,6,FALSE) -> 子 | G7: =VLOOKUP($G$5,$AG$140:$AM$199,6,FALSE) -> 申 | H7: =VLOOKUP($H$5,$AG$140:$AM$199,6,FALSE) -> 酉 | J7: =VLOOKUP(G133,$BQ$191:$BT$202,2,FALSE) -> 0 | L7: =H129 -> 龍高星 | N7: =VLOOKUP(H133,$BQ$191:$BT$202,2,FALSE) -> 0 | V7: 起天 | W7: 運命の幕開け。過去を断ち切り新しい種をまく開拓期。 | AG7: =VLOOKUP(LEFT(L7,3),$AN$220:$AO$229,2,FALSE) -> 水 | AJ7: =VLOOKUP(AL7&$F$6,$A$155:$D$254,4,FALSE) -> 丙 | AK7: =HLOOKUP(AJ7,$BV$136:$CG$146,11,FALSE) -> 1 | AL7: =B152 -> 龍高星 | AN7: =ROUND(HLOOKUP(AJ7,$BV$147:$CG$157,11,FALSE)/$CH$157*100/IF(AK7=0,1,AK7),0) -> 6 | AO7: =ROUND(HLOOKUP(AJ7,$BV$147:$CG$157,11,FALSE)/$CH$157*100/IF(AK7=0,1,AK7),0)*AK7 -> 6 | AP7: =ROUND(HLOOKUP(AJ7,$BV$147:$CG$155,9,FALSE)/$CH$155*100,0) -> 6 | AQ7: =[1]意識と無意識!G6 -> 5
E8: =E6&E7 -> 午未 | F8: =IF(VLOOKUP($F$5,$AG$140:$BT$200,9,FALSE)="","-",VLOOKUP($F$5,$AG$140:$BT$200,9,FALSE)) -> - | G8: =IF(VLOOKUP($G$5,$AG$140:$BT$200,9,FALSE)="","-",VLOOKUP($G$5,$AG$140:$BT$200,9,FALSE)) -> 戊 | H8: =IF(VLOOKUP($H$5,$AG$140:$BT$200,9,FALSE)="","-",VLOOKUP($H$5,$AG$140:$BT$200,9,FALSE)) -> - | K8: 父系祖父母 | O8: 母系祖父母 | V8: 吉祥天 | W8: まいた種が芽吹き、周囲の支援を受けて着実に育つ時期。 | AF8: 止まる星 | AH8: =IF(LEFT(BT138,3)="",O120,LEFT(BT138,3)) -> 司禄星 | AJ8: =VLOOKUP(AL8&$F$6,$A$155:$D$254,4,FALSE) -> 丁 | AK8: =HLOOKUP(AJ8,$BV$136:$CG$146,11,FALSE) -> 0 | AL8: =B151 -> 玉堂星 | AN8: =ROUND(HLOOKUP(AJ8,$BV$147:$CG$157,11,FALSE)/$CH$157*100/IF(AK8=0,1,AK8),0) -> 0 | AO8: =ROUND(HLOOKUP(AJ8,$BV$147:$CG$157,11,FALSE)/$CH$157*100/IF(AK8=0,1,AK8),0)*AK8 -> 0 | AP8: =ROUND(HLOOKUP(AJ8,$BV$147:$CG$155,9,FALSE)/$CH$155*100,0) -> 0 | AQ8: =[1]意識と無意識!G7 -> 0
F9: =IF(VLOOKUP($F$5,$AG$140:$BT$200,10,FALSE)="","-",VLOOKUP($F$5,$AG$140:$BT$200,10,FALSE)) -> - | G9: =IF(VLOOKUP($G$5,$AG$140:$BT$200,10,FALSE)="","-",VLOOKUP($G$5,$AG$140:$BT$200,10,FALSE)) -> 壬 | H9: =IF(VLOOKUP($H$5,$AG$140:$BT$200,10,FALSE)="","-",VLOOKUP($H$5,$AG$140:$BT$200,10,FALSE)) -> - | J9: =M126&N126 -> #N/A | K9: =IF(N126="×","",HLOOKUP(RIGHT(J9,1),BV147:CG154,8,FALSE)&" -") -> #N/A | L9: =P126&AF126 -> #N/A | M9: =IF(AF126="×","",HLOOKUP(RIGHT(L9,1),BV147:CG154,8,FALSE)) -> #N/A | N9: =AH126&AI126 -> #N/A | O9: =IF(AI126="×","",HLOOKUP(RIGHT(N9,1),BV147:CG154,8,FALSE)&" -") -> #N/A | P9: =AK126&AL126 -> #N/A | V9: 弁財天 | W9: 才能がパッと花開き、今後の人生を左右する重要な決定を下す発展期。 | AF9: =IF(AL126="×","",HLOOKUP(AL126,BV147:CG154,8,FALSE)&" -") -> #N/A | AJ9: =VLOOKUP(AL9&$F$6,$A$155:$D$254,4,FALSE) -> 戊 | AK9: =HLOOKUP(AJ9,$BV$136:$CG$146,11,FALSE) -> 2 | AL9: =B144 -> 貫索星 | AN9: =ROUND(HLOOKUP(AJ9,$BV$147:$CG$157,11,FALSE)/$CH$157*100/IF(AK9=0,1,AK9),0) -> 6 | AO9: =ROUND(HLOOKUP(AJ9,$BV$147:$CG$157,11,FALSE)/$CH$157*100/IF(AK9=0,1,AK9),0)*AK9 -> 12 | AP9: =ROUND(HLOOKUP(AJ9,$BV$147:$CG$155,9,FALSE)/$CH$155*100,0) -> 6 | AQ9: =[1]意識と無意識!G8 -> 2
F10: =VLOOKUP($F$5,$AG$140:$BT$200,11,FALSE) -> 癸 | G10: =VLOOKUP($G$5,$AG$140:$BT$200,11,FALSE) -> 庚 | H10: =VLOOKUP($H$5,$AG$140:$BT$200,11,FALSE) -> 辛 | L10: | | M10: 両親 | N10: | | V10: 曇天 | W10: 運気の勢いに心身が追いつかない小休止。自己治癒の時期。 | AF10: 義理の両親 | AJ10: =VLOOKUP(AL10&$F$6,$A$155:$D$254,4,FALSE) -> 己 | AK10: =HLOOKUP(AJ10,$BV$136:$CG$146,11,FALSE) -> 0 | AL10: =B143 -> 石門星 | AN10: =ROUND(HLOOKUP(AJ10,$BV$147:$CG$157,11,FALSE)/$CH$157*100/IF(AK10=0,1,AK10),0) -> 0 | AO10: =ROUND(HLOOKUP(AJ10,$BV$147:$CG$157,11,FALSE)/$CH$157*100/IF(AK10=0,1,AK10),0)*AK10 -> 0 | AP10: =ROUND(HLOOKUP(AJ10,$BV$147:$CG$155,9,FALSE)/$CH$155*100,0) -> 0 | AQ10: =[1]意識と無意識!G9 -> 0
E11: =E8&H11&G11 -> 午未 | G11: =IF(OR(E6=G7,E7=G7),"生月天中殺","") | H11: =IF(E6=H7,"生年天中殺",IF(E7=H7,"生年天中殺","")) | L11: =P128&AF128 -> #N/A | M11: =HLOOKUP(RIGHT(L11,1),BV147:CG154,8,FALSE)&" -" -> #N/A | N11: =AH128&AI128 -> 丁0 | O11: =HLOOKUP(RIGHT(N11,1),BV147:CG154,8,FALSE) -> #N/A | P11: =AK128&AL128 -> #N/A | V11: 韋駄天 | W11: 運気絶頂。これまでの努力が実を結び、最高のスポットライトを浴びる。 | AF11: =IF(AL128="×","",HLOOKUP(AL128,BV147:CG154,8,FALSE)&" -") -> #N/A | AG11: =AN128&AO128 -> #N/A | AH11: =IF(AO128="×","",HLOOKUP(AO128,BV147:CG154,8,FALSE)) -> #N/A | AJ11: =VLOOKUP(AL11&$F$6,$A$155:$D$254,4,FALSE) -> 庚 | AK11: =HLOOKUP(AJ11,$BV$136:$CG$146,11,FALSE) -> 1 | AL11: =B146 -> 鳳閣星 | AN11: =ROUND(HLOOKUP(AJ11,$BV$147:$CG$157,11,FALSE)/$CH$157*100/IF(AK11=0,1,AK11),0) -> 16 | AO11: =ROUND(HLOOKUP(AJ11,$BV$147:$CG$157,11,FALSE)/$CH$157*100/IF(AK11=0,1,AK11),0)*AK11 -> 16 | AP11: =ROUND(HLOOKUP(AJ11,$BV$147:$CG$155,9,FALSE)/$CH$155*100,0) -> 16 | AQ11: =[1]意識と無意識!G10 -> 1 | CF11: 1
N12: |自分 | P12: |配偶者 | V12: 伏魔天 | W12: 強すぎる運気の反動で迷いや摩擦が生じる。理性と現状維持が必要な嵐。 | AJ12: =VLOOKUP(AL12&$F$6,$A$155:$D$254,4,FALSE) -> 辛 | AK12: =HLOOKUP(AJ12,$BV$136:$CG$146,11,FALSE) -> 2 | AL12: =B145 -> 調舒星 | AN12: =ROUND(HLOOKUP(AJ12,$BV$147:$CG$157,11,FALSE)/$CH$157*100/IF(AK12=0,1,AK12),0) -> 20 | AO12: =ROUND(HLOOKUP(AJ12,$BV$147:$CG$157,11,FALSE)/$CH$157*100/IF(AK12=0,1,AK12),0)*AK12 -> 40 | AP12: =ROUND(HLOOKUP(AJ12,$BV$147:$CG$155,9,FALSE)/$CH$155*100,0) -> 42 | AQ12: =[1]意識と無意識!G11 -> 1 | CF12: 2
F13: =VLOOKUP(F5&"+"&G5,[1]大運!$H$45:$K$3644,2,FALSE) -> 半会 | G13: =VLOOKUP(F5&"+"&H5,[1]大運!$H$45:$K$3644,2,FALSE) -> 破 | H13: =VLOOKUP(H5&"+"&G5,[1]大運!$H$45:$K$3644,2,FALSE) -> 準方位 | I13: =IF(I3<1902,"誕生日が違います","") | N13: =AI130 -> 戊 | O13: =HLOOKUP(RIGHT(N13,1),BV147:CG154,8,FALSE)&" -" -> 9 - | P13: =AK130&AL130 -> 辛0 | V13: 有頂天 | W13: 第2の絶頂期。過去の縁が繋がり、周囲を巻き込み大きな成果を出す。 | AF13: =HLOOKUP(RIGHT(P13,1),BV147:CG154,8,FALSE) -> #N/A | AJ13: =VLOOKUP(AL13&$F$6,$A$155:$D$254,4,FALSE) -> 壬 | AK13: =HLOOKUP(AJ13,$BV$136:$CG$146,11,FALSE) -> 1 | AL13: =B148 -> 禄存星 | AN13: =ROUND(HLOOKUP(AJ13,$BV$147:$CG$157,11,FALSE)/$CH$157*100/IF(AK13=0,1,AK13),0) -> 17 | AO13: =ROUND(HLOOKUP(AJ13,$BV$147:$CG$157,11,FALSE)/$CH$157*100/IF(AK13=0,1,AK13),0)*AK13 -> 17 | AP13: =ROUND(HLOOKUP(AJ13,$BV$147:$CG$155,9,FALSE)/$CH$155*100,0) -> 18 | AQ13: =[1]意識と無意識!G12 -> 3 | CF13: 3
F14: =IF(OR(AND(MOD(F5,2)=0,G5-F5=1),AND(MOD(F5,2)=1,G5-F5=13),AND(MOD(F5,2)=0,H5-F5=1),AND(MOD(F5,2)=1,H5-F5=13)),"連唐","-") -> - | G14: =IF(OR(AND(MOD(G5,2)=0,F5-G5=1),AND(MOD(G5,2)=1,F5-G5=13),AND(MOD(G5,2)=0,H5-G5=1),AND(MOD(G5,2)=1,H5-G5=13)),"連唐","-") -> - | H14: =IF(OR(AND(MOD(H5,2)=0,F5-H5=1),AND(MOD(H5,2)=1,F5-H5=13),AND(MOD(H5,2)=0,G5-H5=1),AND(MOD(H5,2)=1,G5-H5=13)),"連唐","-") -> - | N14: |子供 | P14: |子供 | V14: 満天 | W14: 収穫の喜び。物質や人脈などあらゆる財を蓄積し、強固な基盤を作る。 | AJ14: =VLOOKUP(AL14&$F$6,$A$155:$D$254,4,FALSE) -> 癸 | AK14: =HLOOKUP(AJ14,$BV$136:$CG$146,11,FALSE) -> 1 | AL14: =B147 -> 司禄星 | AN14: =ROUND(HLOOKUP(AJ14,$BV$147:$CG$157,11,FALSE)/$CH$157*100/IF(AK14=0,1,AK14),0) -> 11 | AO14: =ROUND(HLOOKUP(AJ14,$BV$147:$CG$157,11,FALSE)/$CH$157*100/IF(AK14=0,1,AK14),0)*AK14 -> 11 | AP14: =ROUND(HLOOKUP(AJ14,$BV$147:$CG$155,9,FALSE)/$CH$155*100,0) -> 11 | AQ14: =[1]意識と無意識!G13 -> 3 | CF14: 4
L15: =P132&AF132 -> . | M15: =IF(OR(AF132="×",AF132="."),"",HLOOKUP(AF132,BV147:CG154,8,FALSE)&" -") | N15: =AH132&AI132 -> . | O15: =IF(OR(AI132="×",AI132=""),"",HLOOKUP(AI132,BV147:CG154,8,FALSE)&" -") | P15: =AK132&AL132 -> #N/A | V15: 静天 | W15: 成果が出揃う。精神的な安定と充実の中で平和に人生を俯瞰する時期。 | AF15: =IF(OR(AL132="×",AL132="."),"",HLOOKUP(AL132,BV147:CG154,8,FALSE)&" -") -> #N/A | AG15: =AN132&AO132 -> #N/A | AH15: =IF(OR(AO132="×",AO132="."),"",HLOOKUP(AO132,BV147:CG154,8,FALSE)) -> #N/A | AK15: =10-COUNTIF(AK5:AK14,0) -> 6 | AL15: 主観 | AN15: =AP6+AP8+AP10+AP12+AP14 -> 53 | AO15: 客観 | AP15: =AP5+AP7+AP9+AP11+AP13 -> 46 | AQ15: =SUM(BX17:BX26) -> 161 | CF15: 5
V16: 暗天 | W16: 運気下降（運の冬入り）。孤独を感じやすいが水面下の自己鍛錬が必要。 | BA16: 日運 | CA16: 構成比 | CB16: 欲求度 | CC16: 五大欲求 | CF16: 6
F17: =[1]大運!F6 -> 大１ | G17: =[1]大運!G6 -> 乙未 | H17: =[1]大運!H6 -> 1991 | I17: =[1]大運!I6 -> 10 | J17: =[1]大運!J6 -> 牽牛星 | K17: =[1]大運!K6 -> 天堂星 | L17: =[1]大運!L6 -> 害 | M17: =[1]大運!M6 -> － | ... P17: =[1]大運!P6 | V17: 大曇天 | W17: 運命の停止（運の真冬時期）。古い価値観を手放す究極の浄化期間。 | AE17: =RIGHT(AH17, 1) -> 戌 | AF17: =IF(OR($E$6=RIGHT(AM17,1),$E$7=RIGHT(AM17,1)),"殺",AG17-$I$3) -> 1 | AG17: =I3+1 -> 1982 | AH17: =VLOOKUP(AM17,[1]大運!$B$31:$C$90,2,FALSE) -> 壬戌 | AI17: =VLOOKUP($F$5&"+"&AM17,[1]大運!$H$45:$K$3644,3,FALSE) -> 禄存星 | AK17: =VLOOKUP($F$5&"+"&AM17,[1]大運!$H$45:$K$3644,4,FALSE) -> 天庫星 | AM17: =IF(MOD((AG17-1900+37),60)=0,60,MOD((AG17-1900+37),60)) -> 59 | AN17: =VLOOKUP($F$5&"+"&AM17,[1]大運!$H$45:$K$3644,2,FALSE) -> － | AO17: =VLOOKUP($G$5&"+"&AM17,[1]大運!$H$45:$K$3644,2,FALSE) -> 準方位 | AP17: =VLOOKUP($H$5&"+"&AM17,[1]大運!$H$45:$K$3644,2,FALSE) -> 害 | AQ17: =IF(OR(RIGHT(AH17,1)=$E$6,RIGHT(AH17,1)=$E$7),"殺","")&IF(ABS(RIGHT(AM17,1)-RIGHT($F$5,1))=5,"日","")&IF(ABS(RIGHT(AM17,1)-RIGHT($G$5,1))=5,"月","")&IF(ABS(RIGHT(AM17,1)-RIGHT($H$5,1))=5,"年","") | AR17: =IF($AH17="","", IFERROR(IF(COUNTIF($F$6, MID("己庚辛壬癸甲乙丙丁戊", FIND(LEFT($AH17,1), "甲乙丙丁戊己庚辛壬癸"), 1))>0, CHOOSE(INT((FIND(LEFT($AH17,1), "甲己乙庚丙辛丁壬戊癸")+1)/2), "甲己干合", "乙庚干合", "丙辛干合", "丁壬干合", "戊癸干合"), ""), "")) | AS17: =IF($AH17="","", IFERROR(IF(COUNTIF($G$6, MID("己庚辛壬癸甲乙丙丁戊", FIND(LEFT($AH17,1), "甲乙丙丁戊己庚辛壬癸"), 1))>0, CHOOSE(INT((FIND(LEFT($AH17,1), "甲己乙庚丙辛丁壬戊癸")+1)/2), "甲己干合", "乙庚干合", "丙辛干合", "丁壬干合", "戊癸干合"), ""), "")) | AT17: =IF($AH17="","", IFERROR(IF(COUNTIF($H$6, MID("己庚辛壬癸甲乙丙丁戊", FIND(LEFT($AH17,1), "甲乙丙丁戊己庚辛壬癸"), 1))>0, CHOOSE(INT((FIND(LEFT($AH17,1), "甲己乙庚丙辛丁壬戊癸")+1)/2), "甲己干合", "乙庚干合", "丙辛干合", "丁壬干合", "戊癸干合"), ""), "")) | AU17: =INDEX('12運シート'!C:C, MATCH(1, INDEX(('12運シート'!A:A=TRIM($T$42)) * ('12運シート'!B:B=TRIM(RIGHT(AE17, 1))), 0), 0)) -> 緑生 | AV17: =INDEX('12運シート'!$E:$E, MATCH(1, INDEX((TRIM('12運シート'!$A:$A)=TRIM($T$42)) * (TRIM('12運シート'!$B:$B)=TRIM(AE17)), 0), 0)) -> 吉祥天 | AW17: =VLOOKUP(AV17,$V$6:$W$18, 2, FALSE) -> まいた種が芽吹き、周囲の支援を受けて着実に育つ時期。 | AZ17: =RIGHT(BC17, 1) -> 亥 | BA17: =EOMONTH(TODAY(), -2) + 1 -> 46143 | BB17: =MOD(BA17 - DATE(2024, 1, 1), 60) + 1 -> 12 | BC17: =VLOOKUP(BB17,[1]大運!$B$31:$C$90,2,FALSE) -> 乙亥 | BD17: =VLOOKUP($F$5 & "+" & (MOD(BA17 - DATE(2024, 1, 1), 60) + 1), [1]大運!$H$45:$K$3644, 3, FALSE) -> 牽牛星 | BE17: =VLOOKUP($F$5 & "+" & (MOD(BA17 - DATE(2024, 1, 1), 60) + 1), [1]大運!$H$45:$K$3644, 4, FALSE) -> 天馳星 | BF17: =VLOOKUP($F$5 & "+" & (MOD(BA17 - DATE(2024, 1, 1), 60) + 1), [1]大運!$H$45:$K$3644, 2, FALSE) -> 準方位 | BG17: =VLOOKUP($G$5 & "+" & (MOD(BA17 - DATE(2024, 1, 1), 60) + 1), [1]大運!$H$45:$K$3644, 2, FALSE) -> 害 | BH17: =VLOOKUP($H$5 & "+" & (MOD(BA17 - DATE(2024, 1, 1), 60) + 1), [1]大運!$H$45:$K$3644, 2, FALSE) -> － | BI17: =IF($BC17="","", IFERROR(IF(COUNTIF($F$6, MID("己庚辛壬癸甲乙丙丁戊", FIND(LEFT($BC17,1), "甲乙丙丁戊己庚辛壬癸"), 1))>0, CHOOSE(INT((FIND(LEFT($BC17,1), "甲己乙庚丙辛丁壬戊癸")+1)/2), "甲己干合", "乙庚干合", "丙辛干合", "丁壬干合", "戊癸干合"), ""), "")) | BJ17: =IF($BC17="","", IFERROR(IF(COUNTIF($G$6, MID("己庚辛壬癸甲乙丙丁戊", FIND(LEFT($BC17,1), "甲乙丙丁戊己庚辛壬癸"), 1))>0, CHOOSE(INT((FIND(LEFT($BC17,1), "甲己乙庚丙辛丁壬戊癸")+1)/2), "甲己干合", "乙庚干合", "丙辛干合", "丁壬干合", "戊癸干合"), ""), "")) | BK17: =IF($BC17="","", IFERROR(IF(COUNTIF($H$6, MID("己庚辛壬癸甲乙丙丁戊", FIND(LEFT($BC17,1), "甲乙丙丁戊己庚辛壬癸"), 1))>0, CHOOSE(INT((FIND(LEFT($BC17,1), "甲己乙庚丙辛丁壬戊癸")+1)/2), "甲己干合", "乙庚干合", "丙辛干合", "丁壬干合", "戊癸干合"), ""), "")) | BL17: =INDEX('12運シート'!C:C, MATCH(1, INDEX(('12運シート'!A:A=TRIM($T$42)) * ('12運シート'!B:B=TRIM(RIGHT(AZ17, 1))), 0), 0)) -> 立花 | BM17: =INDEX('12運シート'!$E:$E, MATCH(1, INDEX((TRIM('12運シート'!$A:$A)=TRIM($T$42)) * (TRIM('12運シート'!$B:$B)=TRIM(AZ17)), 0), 0)) -> 弁財天 | BN17: =VLOOKUP(BM17,$V$6:$W$18, 2, FALSE) -> 才能がパッと花開き、今後の人生を左右する重要な決定を下す発展期。 | BQ17: 甲 | BT17: =COUNTIF($F$6:$H$10, "*"&BQ17&"*") -> 0 | BU17: =IFERROR(__xludf.DUMMYFUNCTION("IFERROR(VLOOKUP(""*""&AQ17&""*"", {""甲"",7,10,11,12,8,4,2,5,1,3,6,9;""乙"",4,8,12,11,10,7,9,6,3,1,5,2;""丙"",3,6,9,7,10,11,12,8,4,2,5,1;""丁"",1,5,2,4,8,12,11,10,7,9,6,3;""戊"",3,6,9,7,10,11,12,8,4,2,5,1;""己"",1,5,2,4,8,12,11,10,7,9,6,3;""庚"",2,5,1,3,6,9,7,10"&",11,12,8,4;""辛"",9,6,3,1,5,2,4,8,12,11,10,7;""壬"",12,8,4,2,5,1,3,6,9,7,10,11;""癸"",11,10,7,9,6,3,1,5,2,4,8,12}, FIND(REGEXREPLACE($H$7,""[^子丑寅卯辰巳午未申酉戌亥]"",""""), ""子丑寅卯辰巳午未申酉戌亥"")+1, FALSE), 0)"),3) -> 3 | BV17: =IFERROR(__xludf.DUMMYFUNCTION("IFERROR(VLOOKUP(""*""&AQ17&""*"", {""甲"",7,10,11,12,8,4,2,5,1,3,6,9;""乙"",4,8,12,11,10,7,9,6,3,1,5,2;""丙"",3,6,9,7,10,11,12,8,4,2,5,1;""丁"",1,5,2,4,8,12,11,10,7,9,6,3;""戊"",3,6,9,7,10,11,12,8,4,2,5,1;""己"",1,5,2,4,8,12,11,10,7,9,6,3;""庚"",2,5,1,3,6,9,7,10"&",11,12,8,4;""辛"",9,6,3,1,5,2,4,8,12,11,10,7;""壬"",12,8,4,2,5,1,3,6,9,7,10,11;""癸"",11,10,7,9,6,3,1,5,2,4,8,12}, FIND(REGEXREPLACE($G$7,""[^子丑寅卯辰巳午未申酉戌亥]"",""""), ""子丑寅卯辰巳午未申酉戌亥"")+1, FALSE), 0)"),1) -> 1 | BW17: =IFERROR(__xludf.DUMMYFUNCTION("IFERROR(VLOOKUP(""*""&AQ17&""*"", {""甲"",7,10,11,12,8,4,2,5,1,3,6,9;""乙"",4,8,12,11,10,7,9,6,3,1,5,2;""丙"",3,6,9,7,10,11,12,8,4,2,5,1;""丁"",1,5,2,4,8,12,11,10,7,9,6,3;""戊"",3,6,9,7,10,11,12,8,4,2,5,1;""己"",1,5,2,4,8,12,11,10,7,9,6,3;""庚"",2,5,1,3,6,9,7,10"&",11,12,8,4;""辛"",9,6,3,1,5,2,4,8,12,11,10,7;""壬"",12,8,4,2,5,1,3,6,9,7,10,11;""癸"",11,10,7,9,6,3,1,5,2,4,8,12}, FIND(REGEXREPLACE($F$7,""[^子丑寅卯辰巳午未申酉戌亥]"",""""), ""子丑寅卯辰巳午未申酉戌亥"")+1, FALSE), 0)"),7) -> 7 | BX17: =BT17 * (BU17 + BV17 + BW17) -> 0 | BY17: 木 | BZ17: =SUM(BX17:BX18) -> 0 | CA17: =BZ17/$BZ$22*100 -> 0 | CB17: =ROUND((BZ17 / MAX($BZ$17:$BZ$21)) * 10, 0) -> 0 | CC17: 生存の欲求 | CD17: システムの安全維持・リスク回避・保守 | CF17: 7
F18: =[1]大運!F7 -> 大２ | G18: =[1]大運!G7 -> 甲午 | H18: =[1]大運!H7 -> 2001 | I18: =[1]大運!I7 -> 20 | J18: =[1]大運!J7 -> 車騎星 | K18: =[1]大運!K7 -> 天将星 | L18: =[1]大運!L7 -> 天剋地冲 | M18: =[1]大運!M7 -> － | ... P18: =[1]大運!P7 | V18: 雨天 | W18: カルマの精算。過去の執着をすべて洗い流し、次の春への準備を整える。 | AE18: =RIGHT(AH18, 1) -> 亥 | AF18: =IF(OR($E$6=RIGHT(AM18,1),$E$7=RIGHT(AM18,1)),"殺",AG18-$I$3) -> 2 | AG18: =AG17+1 -> 1983 | AH18: =VLOOKUP(AM18,[1]大運!$B$31:$C$90,2,FALSE) -> 癸亥 | AI18: =VLOOKUP($F$5&"+"&AM18,[1]大運!$H$45:$K$3644,3,FALSE) -> 司禄星 | AK18: =VLOOKUP($F$5&"+"&AM18,[1]大運!$H$45:$K$3644,4,FALSE) -> 天馳星 | AM18: =IF(MOD((AG18-1900+37),60)=0,60,MOD((AG18-1900+37),60)) -> 60 | AN18: =VLOOKUP($F$5&"+"&AM18,[1]大運!$H$45:$K$3644,2,FALSE) -> 準方位 | AO18: =VLOOKUP($G$5&"+"&AM18,[1]大運!$H$45:$K$3644,2,FALSE) -> 害 | AP18: =VLOOKUP($H$5&"+"&AM18,[1]大運!$H$45:$K$3644,2,FALSE) -> － | AQ18: =IF(OR(RIGHT(AH19,1)=$E$6,RIGHT(AH19,1)=$E$7),"殺","")&IF(ABS(RIGHT(AM19,1)-RIGHT($F$5,1))=5,"日","")&IF(ABS(RIGHT(AM19,1)-RIGHT($G$5,1))=5,"月","")&IF(ABS(RIGHT(AM19,1)-RIGHT($H$5,1))=5,"年","") | AR18: =IF($AH18="","", IFERROR(IF(COUNTIF($F$6, MID("己庚辛壬癸甲乙丙丁戊", FIND(LEFT($AH18,1), "甲乙丙丁戊己庚辛壬癸"), 1))>0, CHOOSE(INT((FIND(LEFT($AH18,1), "甲己乙庚丙辛丁壬戊癸")+1)/2), "甲己干合", "乙庚干合", "丙辛干合", "丁壬干合", "戊癸干合"), ""), "")) -> 戊癸干合 | AS18: =IF($AH18="","", IFERROR(IF(COUNTIF($G$6, MID("己庚辛壬癸甲乙丙丁戊", FIND(LEFT($AH18,1), "甲乙丙丁戊己庚辛壬癸"), 1))>0, CHOOSE(INT((FIND(LEFT($AH18,1), "甲己乙庚丙辛丁壬戊癸")+1)/2), "甲己干合", "乙庚干合", "丙辛干合", "丁壬干合", "戊癸干合"), ""), "")) | AT18: =IF($AH18="","", IFERROR(IF(COUNTIF($H$6, MID("己庚辛壬癸甲乙丙丁戊", FIND(LEFT($AH18,1), "甲乙丙丁戊己庚辛壬癸"), 1))>0, CHOOSE(INT((FIND(LEFT($AH18,1), "甲己乙庚丙辛丁壬戊癸")+1)/2), "甲己干合", "乙庚干合", "丙辛干合", "丁壬干合", "戊癸干合"), ""), "")) | AU18: =INDEX('12運シート'!C:C, MATCH(1, INDEX(('12運シート'!A:A=TRIM($T$42)) * ('12運シート'!B:B=TRIM(RIGHT(AE18, 1))), 0), 0)) -> 立花 | AV18: =INDEX('12運シート'!$E:$E, MATCH(1, INDEX((TRIM('12運シート'!$A:$A)=TRIM($T$42)) * (TRIM('12運シート'!$B:$B)=TRIM(AE18)), 0), 0)) -> 弁財天 | AW18: =VLOOKUP(AV18,$V$6:$W$18, 2, FALSE) -> 才能がパッと花開き、今後の人生を左右する重要な決定を下す発展期。 | AZ18: =RIGHT(BC18, 1) -> 子 | BA18: =BA17+1 -> 46144 | BB18: =MOD(BA18 - DATE(2024, 1, 1), 60) + 1 -> 13 | BC18: =VLOOKUP(BB18,[1]大運!$B$31:$C$90,2,FALSE) -> 丙子 | BD18: =VLOOKUP($F$5 & "+" & (MOD(BA18 - DATE(2024, 1, 1), 60) + 1), [1]大運!$H$45:$K$3644, 3, FALSE) -> 龍高星 | BE18: =VLOOKUP($F$5 & "+" & (MOD(BA18 - DATE(2024, 1, 1), 60) + 1), [1]大運!$H$45:$K$3644, 4, FALSE) -> 天報星 | BF18: =VLOOKUP($F$5 & "+" & (MOD(BA18 - DATE(2024, 1, 1), 60) + 1), [1]大運!$H$45:$K$3644, 2, FALSE) -> 同 | BG18: =VLOOKUP($G$5 & "+" & (MOD(BA18 - DATE(2024, 1, 1), 60) + 1), [1]大運!$H$45:$K$3644, 2, FALSE) -> 大半会 | BH18: =VLOOKUP($H$5 & "+" & (MOD(BA18 - DATE(2024, 1, 1), 60) + 1), [1]大運!$H$45:$K$3644, 2, FALSE) -> 破 | BI18: =IF($BC18="","", IFERROR(IF(COUNTIF($F$6, MID("己庚辛壬癸甲乙丙丁戊", FIND(LEFT($BC18,1), "甲乙丙丁戊己庚辛壬癸"), 1))>0, CHOOSE(INT((FIND(LEFT($BC18,1), "甲己乙庚丙辛丁壬戊癸")+1)/2), "甲己干合", "乙庚干合", "丙辛干合", "丁壬干合", "戊癸干合"), ""), "")) | BJ18: =IF($BC18="","", IFERROR(IF(COUNTIF($G$6, MID("己庚辛壬癸甲乙丙丁戊", FIND(LEFT($BC18,1), "甲乙丙丁戊己庚辛壬癸"), 1))>0, CHOOSE(INT((FIND(LEFT($BC18,1), "甲己乙庚丙辛丁壬戊癸")+1)/2), "甲己干合", "乙庚干合", "丙辛干合", "丁壬干合", "戊癸干合"), ""), "")) | BK18: =IF($BC18="","", IFERROR(IF(COUNTIF($H$6, MID("己庚辛壬癸甲乙丙丁戊", FIND(LEFT($BC18,1), "甲乙丙丁戊己庚辛壬癸"), 1))>0, CHOOSE(INT((FIND(LEFT($BC18,1), "甲己乙庚丙辛丁壬戊癸")+1)/2), "甲己干合", "乙庚干合", "丙辛干合", "丁壬干合", "戊癸干合"), ""), "")) -> 丙辛干合 | BL18: =INDEX('12運シート'!C:C, MATCH(1, INDEX(('12運シート'!A:A=TRIM($T$42)) * ('12運シート'!B:B=TRIM(RIGHT(AZ18, 1))), 0), 0)) -> 健弱 | BM18: =INDEX('12運シート'!$E:$E, MATCH(1, INDEX((TRIM('12運シート'!$A:$A)=TRIM($T$42)) * (TRIM('12運シート'!$B:$B)=TRIM(AZ18)), 0), 0)) -> 曇天 | BN18: =VLOOKUP(BM18,$V$6:$W$18, 2, FALSE) -> 運気の勢いに心身が追いつかない小休止。自己治癒の時期。 | BQ18: 乙 | BT18: =COUNTIF($F$6:$H$10, "*"&BQ18&"*") -> 0 | BU18: =IFERROR(__xludf.DUMMYFUNCTION("IFERROR(VLOOKUP(""*""&AQ18&""*"", {""甲"",7,10,11,12,8,4,2,5,1,3,6,9;""乙"",4,8,12,11,10,7,9,6,3,1,5,2;""丙"",3,6,9,7,10,11,12,8,4,2,5,1;""丁"",1,5,2,4,8,12,11,10,7,9,6,3;""戊"",3,6,9,7,10,11,12,8,4,2,5,1;""己"",1,5,2,4,8,12,11,10,7,9,6,3;""庚"",2,5,1,3,6,9,7,10"&",11,12,8,4;""辛"",9,6,3,1,5,2,4,8,12,11,10,7;""壬"",12,8,4,2,5,1,3,6,9,7,10,11;""癸"",11,10,7,9,6,3,1,5,2,4,8,12}, FIND(REGEXREPLACE($H$7,""[^子丑寅卯辰巳午未申酉戌亥]"",""""), ""子丑寅卯辰巳午未申酉戌亥"")+1, FALSE), 0)"),1) -> 1 | BV18: =IFERROR(__xludf.DUMMYFUNCTION("IFERROR(VLOOKUP(""*""&AQ18&""*"", {""甲"",7,10,11,12,8,4,2,5,1,3,6,9;""乙"",4,8,12,11,10,7,9,6,3,1,5,2;""丙"",3,6,9,7,10,11,12,8,4,2,5,1;""丁"",1,5,2,4,8,12,11,10,7,9,6,3;""戊"",3,6,9,7,10,11,12,8,4,2,5,1;""己"",1,5,2,4,8,12,11,10,7,9,6,3;""庚"",2,5,1,3,6,9,7,10"&",11,12,8,4;""辛"",9,6,3,1,5,2,4,8,12,11,10,7;""壬"",12,8,4,2,5,1,3,6,9,7,10,11;""癸"",11,10,7,9,6,3,1,5,2,4,8,12}, FIND(REGEXREPLACE($G$7,""[^子丑寅卯辰巳午未申酉戌亥]"",""""), ""子丑寅卯辰巳午未申酉戌亥"")+1, FALSE), 0)"),3) -> 3 | BW18: =IFERROR(__xludf.DUMMYFUNCTION("IFERROR(VLOOKUP(""*""&AQ18&""*"", {""甲"",7,10,11,12,8,4,2,5,1,3,6,9;""乙"",4,8,12,11,10,7,9,6,3,1,5,2;""丙"",3,6,9,7,10,11,12,8,4,2,5,1;""丁"",1,5,2,4,8,12,11,10,7,9,6,3;""戊"",3,6,9,7,10,11,12,8,4,2,5,1;""己"",1,5,2,4,8,12,11,10,7,9,6,3;""庚"",2,5,1,3,6,9,7,10"&",11,12,8,4;""辛"",9,6,3,1,5,2,4,8,12,11,10,7;""壬"",12,8,4,2,5,1,3,6,9,7,10,11;""癸"",11,10,7,9,6,3,1,5,2,4,8,12}, FIND(REGEXREPLACE($F$7,""[^子丑寅卯辰巳午未申酉戌亥]"",""""), ""子丑寅卯辰巳午未申酉戌亥"")+1, FALSE), 0)"),4) -> 4 | BX18: =BT18 * (BU18 + BV18 + BW18) -> 0 | BY18: 火 | BZ18: =SUM(BX19:BX20) -> 9 | CA18: =BZ18/$BZ$22*100 -> 5.5900621 | CB18: =ROUND((BZ18 / MAX($BZ$17:$BZ$21)) * 10, 0) -> 1 | CC18: 楽しみの欲求 | CD18: 自己表現・遊び・学習の喜び・共鳴 | CF18: 8
F19: =[1]大運!F8 -> 大３ | G19: =[1]大運!G8 -> 癸巳 | H19: =[1]大運!H8 -> 2011 | I19: =[1]大運!I8 -> 30 | J19: =[1]大運!J8 -> 司禄星 | K19: =[1]大運!K8 -> 天禄星 | L19: =[1]大運!L8 -> － | M19: =[1]大運!M8 -> 支合 | ... P19: =[1]大運!P8 -> 日干 | AE19: =RIGHT(AH19, 1) -> 子 | AF19: =IF(OR($E$6=RIGHT(AM19,1),$E$7=RIGHT(AM19,1)),"殺",AG19-$I$3) -> 3 | AG19: =AG18+1 -> 1984 | AH19: =VLOOKUP(AM19,[1]大運!$B$31:$C$90,2,FALSE) -> 甲子 | AI19: =VLOOKUP($F$5&"+"&AM19,[1]大運!$H$45:$K$3644,3,FALSE) -> 車騎星 | AK19: =VLOOKUP($F$5&"+"&AM19,[1]大運!$H$45:$K$3644,4,FALSE) -> 天報星 | AM19: =IF(MOD((AG19-1900+37),60)=0,60,MOD((AG19-1900+37),60)) -> 1 | AN19: =VLOOKUP($F$5&"+"&AM19,[1]大運!$H$45:$K$3644,2,FALSE) -> 同 | AO19: =VLOOKUP($G$5&"+"&AM19,[1]大運!$H$45:$K$3644,2,FALSE) -> 半会 | AP19: =VLOOKUP($H$5&"+"&AM19,[1]大運!$H$45:$K$3644,2,FALSE) -> 破 | AQ19: =IF(OR(RIGHT(AH20,1)=$E$6,RIGHT(AH20,1)=$E$7),"殺","")&IF(ABS(RIGHT(AM20,1)-RIGHT($F$5,1))=5,"日","")&IF(ABS(RIGHT(AM20,1)-RIGHT($G$5,1))=5,"月","")&IF(ABS(RIGHT(AM20,1)-RIGHT($H$5,1))=5,"年","") | AR19: =IF($AH19="","", IFERROR(IF(COUNTIF($F$6, MID("己庚辛壬癸甲乙丙丁戊", FIND(LEFT($AH19,1), "甲乙丙丁戊己庚辛壬癸"), 1))>0, CHOOSE(INT((FIND(LEFT($AH19,1), "甲己乙庚丙辛丁壬戊癸")+1)/2), "甲己干合", "乙庚干合", "丙辛干合", "丁壬干合", "戊癸干合"), ""), "")) | AS19: =IF($AH19="","", IFERROR(IF(COUNTIF($G$6, MID("己庚辛壬癸甲乙丙丁戊", FIND(LEFT($AH19,1), "甲乙丙丁戊己庚辛壬癸"), 1))>0, CHOOSE(INT((FIND(LEFT($AH19,1), "甲己乙庚丙辛丁壬戊癸")+1)/2), "甲己干合", "乙庚干合", "丙辛干合", "丁壬干合", "戊癸干合"), ""), "")) | AT19: =IF($AH19="","", IFERROR(IF(COUNTIF($H$6, MID("己庚辛壬癸甲乙丙丁戊", FIND(LEFT($AH19,1), "甲乙丙丁戊己庚辛壬癸"), 1))>0, CHOOSE(INT((FIND(LEFT($AH19,1), "甲己乙庚丙辛丁壬戊癸")+1)/2), "甲己干合", "乙庚干合", "丙辛干合", "丁壬干合", "戊癸干合"), ""), "")) | AU19: =INDEX('12運シート'!C:C, MATCH(1, INDEX(('12運シート'!A:A=TRIM($T$42)) * ('12運シート'!B:B=TRIM(RIGHT(AE19, 1))), 0), 0)) -> 健弱 | AV19: =INDEX('12運シート'!$E:$E, MATCH(1, INDEX((TRIM('12運シート'!$A:$A)=TRIM($T$42)) * (TRIM('12運シート'!$B:$B)=TRIM(AE19)), 0), 0)) -> 曇天 | AW19: =VLOOKUP(AV19,$V$6:$W$18, 2, FALSE) -> 運気の勢いに心身が追いつかない小休止。自己治癒の時期。 | AZ19: =RIGHT(BC19, 1) -> 丑 | BA19: =BA18+1 -> 46145 | BB19: =MOD(BA19 - DATE(2024, 1, 1), 60) + 1 -> 14 | BC19: =VLOOKUP(BB19,[1]大運!$B$31:$C$90,2,FALSE) -> 丁丑 | BD19: =VLOOKUP($F$5 & "+" & (MOD(BA19 - DATE(2024, 1, 1), 60) + 1), [1]大運!$H$45:$K$3644, 3, FALSE) -> 玉堂星 | BE19: =VLOOKUP($F$5 & "+" & (MOD(BA19 - DATE(2024, 1, 1), 60) + 1), [1]大運!$H$45:$K$3644, 4, FALSE) -> 天印星 | BF19: =VLOOKUP($F$5 & "+" & (MOD(BA19 - DATE(2024, 1, 1), 60) + 1), [1]大運!$H$45:$K$3644, 2, FALSE) -> 支合 | BG19: =VLOOKUP($G$5 & "+" & (MOD(BA19 - DATE(2024, 1, 1), 60) + 1), [1]大運!$H$45:$K$3644, 2, FALSE) -> － | BH19: =VLOOKUP($H$5 & "+" & (MOD(BA19 - DATE(2024, 1, 1), 60) + 1), [1]大運!$H$45:$K$3644, 2, FALSE) -> 半会 | BI19: =IF($BC19="","", IFERROR(IF(COUNTIF($F$6, MID("己庚辛壬癸甲乙丙丁戊", FIND(LEFT($BC19,1), "甲乙丙丁戊己庚辛壬癸"), 1))>0, CHOOSE(INT((FIND(LEFT($BC19,1), "甲己乙庚丙辛丁壬戊癸")+1)/2), "甲己干合", "乙庚干合", "丙辛干合", "丁壬干合", "戊癸干合"), ""), "")) | BJ19: =IF($BC19="","", IFERROR(IF(COUNTIF($G$6, MID("己庚辛壬癸甲乙丙丁戊", FIND(LEFT($BC19,1), "甲乙丙丁戊己庚辛壬癸"), 1))>0, CHOOSE(INT((FIND(LEFT($BC19,1), "甲己乙庚丙辛丁壬戊癸")+1)/2), "甲己干合", "乙庚干合", "丙辛干合", "丁壬干合", "戊癸干合"), ""), "")) | BK19: =IF($BC19="","", IFERROR(IF(COUNTIF($H$6, MID("己庚辛壬癸甲乙丙丁戊", FIND(LEFT($BC19,1), "甲乙丙丁戊己庚辛壬癸"), 1))>0, CHOOSE(INT((FIND(LEFT($BC19,1), "甲己乙庚丙辛丁壬戊癸")+1)/2), "甲己干合", "乙庚干合", "丙辛干合", "丁壬干合", "戊癸干合"), ""), "")) | BL19: =INDEX('12運シート'!C:C, MATCH(1, INDEX(('12運シート'!A:A=TRIM($T$42)) * ('12運シート'!B:B=TRIM(RIGHT(AZ19, 1))), 0), 0)) -> 達成 | BM19: =INDEX('12運シート'!$E:$E, MATCH(1, INDEX((TRIM('12運シート'!$A:$A)=TRIM($T$42)) * (TRIM('12運シート'!$B:$B)=TRIM(AZ19)), 0), 0)) -> 韋駄天 | BN19: =VLOOKUP(BM19,$V$6:$W$18, 2, FALSE) -> 運気絶頂。これまでの努力が実を結び、最高のスポットライトを浴びる。 | BQ19: 丙 | BT19: =COUNTIF($F$6:$H$10, "*"&BQ19&"*") -> 1 | BU19: =IFERROR(__xludf.DUMMYFUNCTION("IFERROR(VLOOKUP(""*""&AQ19&""*"", {""甲"",7,10,11,12,8,4,2,5,1,3,6,9;""乙"",4,8,12,11,10,7,9,6,3,1,5,2;""丙"",3,6,9,7,10,11,12,8,4,2,5,1;""丁"",1,5,2,4,8,12,11,10,7,9,6,3;""戊"",3,6,9,7,10,11,12,8,4,2,5,1;""己"",1,5,2,4,8,12,11,10,7,9,6,3;""庚"",2,5,1,3,6,9,7,10"&",11,12,8,4;""辛"",9,6,3,1,5,2,4,8,12,11,10,7;""壬"",12,8,4,2,5,1,3,6,9,7,10,11;""癸"",11,10,7,9,6,3,1,5,2,4,8,12}, FIND(REGEXREPLACE($H$7,""[^子丑寅卯辰巳午未申酉戌亥]"",""""), ""子丑寅卯辰巳午未申酉戌亥"")+1, FALSE), 0)"),2) -> 2 | BV19: =IFERROR(__xludf.DUMMYFUNCTION("IFERROR(VLOOKUP(""*""&AQ19&""*"", {""甲"",7,10,11,12,8,4,2,5,1,3,6,9;""乙"",4,8,12,11,10,7,9,6,3,1,5,2;""丙"",3,6,9,7,10,11,12,8,4,2,5,1;""丁"",1,5,2,4,8,12,11,10,7,9,6,3;""戊"",3,6,9,7,10,11,12,8,4,2,5,1;""己"",1,5,2,4,8,12,11,10,7,9,6,3;""庚"",2,5,1,3,6,9,7,10"&",11,12,8,4;""辛"",9,6,3,1,5,2,4,8,12,11,10,7;""壬"",12,8,4,2,5,1,3,6,9,7,10,11;""癸"",11,10,7,9,6,3,1,5,2,4,8,12}, FIND(REGEXREPLACE($G$7,""[^子丑寅卯辰巳午未申酉戌亥]"",""""), ""子丑寅卯辰巳午未申酉戌亥"")+1, FALSE), 0)"),4) -> 4 | BW19: =IFERROR(__xludf.DUMMYFUNCTION("IFERROR(VLOOKUP(""*""&AQ19&""*"", {""甲"",7,10,11,12,8,4,2,5,1,3,6,9;""乙"",4,8,12,11,10,7,9,6,3,1,5,2;""丙"",3,6,9,7,10,11,12,8,4,2,5,1;""丁"",1,5,2,4,8,12,11,10,7,9,6,3;""戊"",3,6,9,7,10,11,12,8,4,2,5,1;""己"",1,5,2,4,8,12,11,10,7,9,6,3;""庚"",2,5,1,3,6,9,7,10"&",11,12,8,4;""辛"",9,6,3,1,5,2,4,8,12,11,10,7;""壬"",12,8,4,2,5,1,3,6,9,7,10,11;""癸"",11,10,7,9,6,3,1,5,2,4,8,12}, FIND(REGEXREPLACE($F$7,""[^子丑寅卯辰巳午未申酉戌亥]"",""""), ""子丑寅卯辰巳午未申酉戌亥"")+1, FALSE), 0)"),3) -> 3 | BX19: =BT19 * (BU19 + BV19 + BW19) -> 9 | BY19: 土 | BZ19: =SUM(BX21:BX22) -> 18 | CA19: =BZ19/$BZ$22*100 -> 11.180124 | CB19: =ROUND((BZ19 / MAX($BZ$17:$BZ$21)) * 10, 0) -> 2 | CC19: 愛・所属の欲求 | CD19: 蓄積・集団への帰属・他者との繋がり | CF19: 9
F20: =[1]大運!F9 -> 大４ | G20: =[1]大運!G9 -> 壬辰 | H20: =[1]大運!H9 -> 2021 | I20: =[1]大運!I9 -> 40 | J20: =[1]大運!J9 -> 禄存星 | K20: =[1]大運!K9 -> 天南星 | L20: =[1]大運!L9 -> 半会 | M20: =[1]大運!M9 -> 半会 | ... P20: =[1]大運!P9 | AE20: =RIGHT(AH20, 1) -> 丑 | AF20: =IF(OR($E$6=RIGHT(AM20,1),$E$7=RIGHT(AM20,1)),"殺",AG20-$I$3) -> 4 | AG20: =AG19+1 -> 1985 | AH20: =VLOOKUP(AM20,[1]大運!$B$31:$C$90,2,FALSE) -> 乙丑 | AI20: =VLOOKUP($F$5&"+"&AM20,[1]大運!$H$45:$K$3644,3,FALSE) -> 牽牛星 | AK20: =VLOOKUP($F$5&"+"&AM20,[1]大運!$H$45:$K$3644,4,FALSE) -> 天印星 | AM20: =IF(MOD((AG20-1900+37),60)=0,60,MOD((AG20-1900+37),60)) -> 2 | AN20: =VLOOKUP($F$5&"+"&AM20,[1]大運!$H$45:$K$3644,2,FALSE) -> 支合 | AO20: =VLOOKUP($G$5&"+"&AM20,[1]大運!$H$45:$K$3644,2,FALSE) -> － | AP20: =VLOOKUP($H$5&"+"&AM20,[1]大運!$H$45:$K$3644,2,FALSE) -> 半会 | AQ20: =IF(OR(RIGHT(AH21,1)=$E$6,RIGHT(AH21,1)=$E$7),"殺","")&IF(ABS(RIGHT(AM21,1)-RIGHT($F$5,1))=5,"日","")&IF(ABS(RIGHT(AM21,1)-RIGHT($G$5,1))=5,"月","")&IF(ABS(RIGHT(AM21,1)-RIGHT($H$5,1))=5,"年","") -> 年 | AR20: =IF($AH20="","", IFERROR(IF(COUNTIF($F$6, MID("己庚辛壬癸甲乙丙丁戊", FIND(LEFT($AH20,1), "甲乙丙丁戊己庚辛壬癸"), 1))>0, CHOOSE(INT((FIND(LEFT($AH20,1), "甲己乙庚丙辛丁壬戊癸")+1)/2), "甲己干合", "乙庚干合", "丙辛干合", "丁壬干合", "戊癸干合"), ""), "")) | AS20: =IF($AH20="","", IFERROR(IF(COUNTIF($G$6, MID("己庚辛壬癸甲乙丙丁戊", FIND(LEFT($AH20,1), "甲乙丙丁戊己庚辛壬癸"), 1))>0, CHOOSE(INT((FIND(LEFT($AH20,1), "甲己乙庚丙辛丁壬戊癸")+1)/2), "甲己干合", "乙庚干合", "丙辛干合", "丁壬干合", "戊癸干合"), ""), "")) | AT20: =IF($AH20="","", IFERROR(IF(COUNTIF($H$6, MID("己庚辛壬癸甲乙丙丁戊", FIND(LEFT($AH20,1), "甲乙丙丁戊己庚辛壬癸"), 1))>0, CHOOSE(INT((FIND(LEFT($AH20,1), "甲己乙庚丙辛丁壬戊癸")+1)/2), "甲己干合", "乙庚干合", "丙辛干合", "丁壬干合", "戊癸干合"), ""), "")) | AU20: =INDEX('12運シート'!C:C, MATCH(1, INDEX(('12運シート'!A:A=TRIM($T$42)) * ('12運シート'!B:B=TRIM(RIGHT(AE20, 1))), 0), 0)) -> 達成 | AV20: =INDEX('12運シート'!$E:$E, MATCH(1, INDEX((TRIM('12運シート'!$A:$A)=TRIM($T$42)) * (TRIM('12運シート'!$B:$B)=TRIM(AE20)), 0), 0)) -> 韋駄天 | AW20: =VLOOKUP(AV20,$V$6:$W$18, 2, FALSE) -> 運気絶頂。これまでの努力が実を結び、最高のスポットライトを浴びる。 | AZ20: =RIGHT(BC20, 1) -> 寅 | BA20: =BA19+1 -> 46146 | BB20: =MOD(BA20 - DATE(2024, 1, 1), 60) + 1 -> 15 | BC20: =VLOOKUP(BB20,[1]大運!$B$31:$C$90,2,FALSE) -> 戊寅 | BD20: =VLOOKUP($F$5 & "+" & (MOD(BA20 - DATE(2024, 1, 1), 60) + 1), [1]大運!$H$45:$K$3644, 3, FALSE) -> 貫索星 | BE20: =VLOOKUP($F$5 & "+" & (MOD(BA20 - DATE(2024, 1, 1), 60) + 1), [1]大運!$H$45:$K$3644, 4, FALSE) -> 天貴星 | BF20: =VLOOKUP($F$5 & "+" & (MOD(BA20 - DATE(2024, 1, 1), 60) + 1), [1]大運!$H$45:$K$3644, 2, FALSE) -> － | BG20: =VLOOKUP($G$5 & "+" & (MOD(BA20 - DATE(2024, 1, 1), 60) + 1), [1]大運!$H$45:$K$3644, 2, FALSE) -> 対冲 | BH20: =VLOOKUP($H$5 & "+" & (MOD(BA20 - DATE(2024, 1, 1), 60) + 1), [1]大運!$H$45:$K$3644, 2, FALSE) -> － | BI20: =IF($BC20="","", IFERROR(IF(COUNTIF($F$6, MID("己庚辛壬癸甲乙丙丁戊", FIND(LEFT($BC20,1), "甲乙丙丁戊己庚辛壬癸"), 1))>0, CHOOSE(INT((FIND(LEFT($BC20,1), "甲己乙庚丙辛丁壬戊癸")+1)/2), "甲己干合", "乙庚干合", "丙辛干合", "丁壬干合", "戊癸干合"), ""), "")) | BJ20: =IF($BC20="","", IFERROR(IF(COUNTIF($G$6, MID("己庚辛壬癸甲乙丙丁戊", FIND(LEFT($BC20,1), "甲乙丙丁戊己庚辛壬癸"), 1))>0, CHOOSE(INT((FIND(LEFT($BC20,1), "甲己乙庚丙辛丁壬戊癸")+1)/2), "甲己干合", "乙庚干合", "丙辛干合", "丁壬干合", "戊癸干合"), ""), "")) | BK20: =IF($BC20="","", IFERROR(IF(COUNTIF($H$6, MID("己庚辛壬癸甲乙丙丁戊", FIND(LEFT($BC20,1), "甲乙丙丁戊己庚辛壬癸"), 1))>0, CHOOSE(INT((FIND(LEFT($BC20,1), "甲己乙庚丙辛丁壬戊癸")+1)/2), "甲己干合", "乙庚干合", "丙辛干合", "丁壬干合", "戊癸干合"), ""), "")) | BL20: =INDEX('12運シート'!C:C, MATCH(1, INDEX(('12運シート'!A:A=TRIM($T$42)) * ('12運シート'!B:B=TRIM(RIGHT(AZ20, 1))), 0), 0)) -> 乱気 | BM20: =INDEX('12運シート'!$E:$E, MATCH(1, INDEX((TRIM('12運シート'!$A:$A)=TRIM($T$42)) * (TRIM('12運シート'!$B:$B)=TRIM(AZ20)), 0), 0)) -> 伏魔天 | BN20: =VLOOKUP(BM20,$V$6:$W$18, 2, FALSE) -> 強すぎる運気の反動で迷いや摩擦が生じる。理性と現状維持が必要な嵐。 | BQ20: 丁 | BT20: =COUNTIF($F$6:$H$10, "*"&BQ20&"*") -> 0 | BU20: =IFERROR(__xludf.DUMMYFUNCTION("IFERROR(VLOOKUP(""*""&AQ20&""*"", {""甲"",7,10,11,12,8,4,2,5,1,3,6,9;""乙"",4,8,12,11,10,7,9,6,3,1,5,2;""丙"",3,6,9,7,10,11,12,8,4,2,5,1;""丁"",1,5,2,4,8,12,11,10,7,9,6,3;""戊"",3,6,9,7,10,11,12,8,4,2,5,1;""己"",1,5,2,4,8,12,11,10,7,9,6,3;""庚"",2,5,1,3,6,9,7,10"&",11,12,8,4;""辛"",9,6,3,1,5,2,4,8,12,11,10,7;""壬"",12,8,4,2,5,1,3,6,9,7,10,11;""癸"",11,10,7,9,6,3,1,5,2,4,8,12}, FIND(REGEXREPLACE($H$7,""[^子丑寅卯辰巳午未申酉戌亥]"",""""), ""子丑寅卯辰巳午未申酉戌亥"")+1, FALSE), 0)"),9) -> 9 | BV20: =IFERROR(__xludf.DUMMYFUNCTION("IFERROR(VLOOKUP(""*""&AQ20&""*"", {""甲"",7,10,11,12,8,4,2,5,1,3,6,9;""乙"",4,8,12,11,10,7,9,6,3,1,5,2;""丙"",3,6,9,7,10,11,12,8,4,2,5,1;""丁"",1,5,2,4,8,12,11,10,7,9,6,3;""戊"",3,6,9,7,10,11,12,8,4,2,5,1;""己"",1,5,2,4,8,12,11,10,7,9,6,3;""庚"",2,5,1,3,6,9,7,10"&",11,12,8,4;""辛"",9,6,3,1,5,2,4,8,12,11,10,7;""壬"",12,8,4,2,5,1,3,6,9,7,10,11;""癸"",11,10,7,9,6,3,1,5,2,4,8,12}, FIND(REGEXREPLACE($G$7,""[^子丑寅卯辰巳午未申酉戌亥]"",""""), ""子丑寅卯辰巳午未申酉戌亥"")+1, FALSE), 0)"),7) -> 7 | BW20: =IFERROR(__xludf.DUMMYFUNCTION("IFERROR(VLOOKUP(""*""&AQ20&""*"", {""甲"",7,10,11,12,8,4,2,5,1,3,6,9;""乙"",4,8,12,11,10,7,9,6,3,1,5,2;""丙"",3,6,9,7,10,11,12,8,4,2,5,1;""丁"",1,5,2,4,8,12,11,10,7,9,6,3;""戊"",3,6,9,7,10,11,12,8,4,2,5,1;""己"",1,5,2,4,8,12,11,10,7,9,6,3;""庚"",2,5,1,3,6,9,7,10"&",11,12,8,4;""辛"",9,6,3,1,5,2,4,8,12,11,10,7;""壬"",12,8,4,2,5,1,3,6,9,7,10,11;""癸"",11,10,7,9,6,3,1,5,2,4,8,12}, FIND(REGEXREPLACE($F$7,""[^子丑寅卯辰巳午未申酉戌亥]"",""""), ""子丑寅卯辰巳午未申酉戌亥"")+1, FALSE), 0)"),1) -> 1 | BX20: =BT20 * (BU20 + BV20 + BW20) -> 0 | BY20: 金 | BZ20: =SUM(BX23:BX24) -> 89 | CA20: =BZ20/$BZ$22*100 -> 55.279503 | CB20: =ROUND((BZ20 / MAX($BZ$17:$BZ$21)) * 10, 0) -> 10 | CC20: 力の欲求 | CD20: 達成・承認・競争・課題の打破 | CF20: 10
F21: =[1]大運!F10 -> 大５ | G21: =[1]大運!G10 -> 辛卯 | H21: =[1]大運!H10 -> 2031 | I21: =[1]大運!I10 -> 50 | J21: =[1]大運!J10 -> 調舒星 | K21: =[1]大運!K10 -> 天恍星 | L21: =[1]大運!L10 -> 刑 | M21: =[1]大運!M10 -> － | ... P21: =[1]大運!P10 -> 月干 | AE21: =RIGHT(AH21, 1) -> 寅 | AF21: =IF(OR($E$6=RIGHT(AM21,1),$E$7=RIGHT(AM21,1)),"殺",AG21-$I$3) -> 5 | AG21: =AG20+1 -> 1986 | AH21: =VLOOKUP(AM21,[1]大運!$B$31:$C$90,2,FALSE) -> 丙寅 | AI21: =VLOOKUP($F$5&"+"&AM21,[1]大運!$H$45:$K$3644,3,FALSE) -> 龍高星 | AK21: =VLOOKUP($F$5&"+"&AM21,[1]大運!$H$45:$K$3644,4,FALSE) -> 天貴星 | AM21: =IF(MOD((AG21-1900+37),60)=0,60,MOD((AG21-1900+37),60)) -> 3 | AN21: =VLOOKUP($F$5&"+"&AM21,[1]大運!$H$45:$K$3644,2,FALSE) -> － | AO21: =VLOOKUP($G$5&"+"&AM21,[1]大運!$H$45:$K$3644,2,FALSE) -> 納音 | AP21: =VLOOKUP($H$5&"+"&AM21,[1]大運!$H$45:$K$3644,2,FALSE) -> － | AQ21: =IF(OR(RIGHT(AH22,1)=$E$6,RIGHT(AH22,1)=$E$7),"殺","")&IF(ABS(RIGHT(AM22,1)-RIGHT($F$5,1))=5,"日","")&IF(ABS(RIGHT(AM22,1)-RIGHT($G$5,1))=5,"月","")&IF(ABS(RIGHT(AM22,1)-RIGHT($H$5,1))=5,"年","") | AR21: =IF($AH21="","", IFERROR(IF(COUNTIF($F$6, MID("己庚辛壬癸甲乙丙丁戊", FIND(LEFT($AH21,1), "甲乙丙丁戊己庚辛壬癸"), 1))>0, CHOOSE(INT((FIND(LEFT($AH21,1), "甲己乙庚丙辛丁壬戊癸")+1)/2), "甲己干合", "乙庚干合", "丙辛干合", "丁壬干合", "戊癸干合"), ""), "")) | AS21: =IF($AH21="","", IFERROR(IF(COUNTIF($G$6, MID("己庚辛壬癸甲乙丙丁戊", FIND(LEFT($AH21,1), "甲乙丙丁戊己庚辛壬癸"), 1))>0, CHOOSE(INT((FIND(LEFT($AH21,1), "甲己乙庚丙辛丁壬戊癸")+1)/2), "甲己干合", "乙庚干合", "丙辛干合", "丁壬干合", "戊癸干合"), ""), "")) | AT21: =IF($AH21="","", IFERROR(IF(COUNTIF($H$6, MID("己庚辛壬癸甲乙丙丁戊", FIND(LEFT($AH21,1), "甲乙丙丁戊己庚辛壬癸"), 1))>0, CHOOSE(INT((FIND(LEFT($AH21,1), "甲己乙庚丙辛丁壬戊癸")+1)/2), "甲己干合", "乙庚干合", "丙辛干合", "丁壬干合", "戊癸干合"), ""), "")) -> 丙辛干合 | AU21: =INDEX('12運シート'!C:C, MATCH(1, INDEX(('12運シート'!A:A=TRIM($T$42)) * ('12運シート'!B:B=TRIM(RIGHT(AE21, 1))), 0), 0)) -> 乱気 | AV21: =INDEX('12運シート'!$E:$E, MATCH(1, INDEX((TRIM('12運シート'!$A:$A)=TRIM($T$42)) * (TRIM('12運シート'!$B:$B)=TRIM(AE21)), 0), 0)) -> 伏魔天 | AW21: =VLOOKUP(AV21,$V$6:$W$18, 2, FALSE) -> 強すぎる運気の反動で迷いや摩擦が生じる。理性と現状維持が必要な嵐。 | AZ21: =RIGHT(BC21, 1) -> 卯 | BA21: =BA20+1 -> 46147 | BB21: =MOD(BA21 - DATE(2024, 1, 1), 60) + 1 -> 16 | BC21: =VLOOKUP(BB21,[1]大運!$B$31:$C$90,2,FALSE) -> 己卯 | BD21: =VLOOKUP($F$5 & "+" & (MOD(BA21 - DATE(2024, 1, 1), 60) + 1), [1]大運!$H$45:$K$3644, 3, FALSE) -> 石門星 | BE21: =VLOOKUP($F$5 & "+" & (MOD(BA21 - DATE(2024, 1, 1), 60) + 1), [1]大運!$H$45:$K$3644, 4, FALSE) -> 天恍星 | BF21: =VLOOKUP($F$5 & "+" & (MOD(BA21 - DATE(2024, 1, 1), 60) + 1), [1]大運!$H$45:$K$3644, 2, FALSE) -> 刑 | BG21: =VLOOKUP($G$5 & "+" & (MOD(BA21 - DATE(2024, 1, 1), 60) + 1), [1]大運!$H$45:$K$3644, 2, FALSE) -> － | BH21: =VLOOKUP($H$5 & "+" & (MOD(BA21 - DATE(2024, 1, 1), 60) + 1), [1]大運!$H$45:$K$3644, 2, FALSE) -> 対冲 | BI21: =IF($BC21="","", IFERROR(IF(COUNTIF($F$6, MID("己庚辛壬癸甲乙丙丁戊", FIND(LEFT($BC21,1), "甲乙丙丁戊己庚辛壬癸"), 1))>0, CHOOSE(INT((FIND(LEFT($BC21,1), "甲己乙庚丙辛丁壬戊癸")+1)/2), "甲己干合", "乙庚干合", "丙辛干合", "丁壬干合", "戊癸干合"), ""), "")) | BJ21: =IF($BC21="","", IFERROR(IF(COUNTIF($G$6, MID("己庚辛壬癸甲乙丙丁戊", FIND(LEFT($BC21,1), "甲乙丙丁戊己庚辛壬癸"), 1))>0, CHOOSE(INT((FIND(LEFT($BC21,1), "甲己乙庚丙辛丁壬戊癸")+1)/2), "甲己干合", "乙庚干合", "丙辛干合", "丁壬干合", "戊癸干合"), ""), "")) | BK21: =IF($BC21="","", IFERROR(IF(COUNTIF($H$6, MID("己庚辛壬癸甲乙丙丁戊", FIND(LEFT($BC21,1), "甲乙丙丁戊己庚辛壬癸"), 1))>0, CHOOSE(INT((FIND(LEFT($BC21,1), "甲己乙庚丙辛丁壬戊癸")+1)/2), "甲己干合", "乙庚干合", "丙辛干合", "丁壬干合", "戊癸干合"), ""), "")) | BL21: =INDEX('12運シート'!C:C, MATCH(1, INDEX(('12運シート'!A:A=TRIM($T$42)) * ('12運シート'!B:B=TRIM(RIGHT(AZ21, 1))), 0), 0)) -> 再会 | BM21: =INDEX('12運シート'!$E:$E, MATCH(1, INDEX((TRIM('12運シート'!$A:$A)=TRIM($T$42)) * (TRIM('12運シート'!$B:$B)=TRIM(AZ21)), 0), 0)) -> 有頂天 | BN21: =VLOOKUP(BM21,$V$6:$W$18, 2, FALSE) -> 第2の絶頂期。過去の縁が繋がり、周囲を巻き込み大きな成果を出す。 | BQ21: 戊 | BT21: =COUNTIF($F$6:$H$10, "*"&BQ21&"*") -> 2 | BU21: =IFERROR(__xludf.DUMMYFUNCTION("IFERROR(VLOOKUP(""*""&AQ21&""*"", {""甲"",7,10,11,12,8,4,2,5,1,3,6,9;""乙"",4,8,12,11,10,7,9,6,3,1,5,2;""丙"",3,6,9,7,10,11,12,8,4,2,5,1;""丁"",1,5,2,4,8,12,11,10,7,9,6,3;""戊"",3,6,9,7,10,11,12,8,4,2,5,1;""己"",1,5,2,4,8,12,11,10,7,9,6,3;""庚"",2,5,1,3,6,9,7,10"&",11,12,8,4;""辛"",9,6,3,1,5,2,4,8,12,11,10,7;""壬"",12,8,4,2,5,1,3,6,9,7,10,11;""癸"",11,10,7,9,6,3,1,5,2,4,8,12}, FIND(REGEXREPLACE($H$7,""[^子丑寅卯辰巳午未申酉戌亥]"",""""), ""子丑寅卯辰巳午未申酉戌亥"")+1, FALSE), 0)"),2) -> 2 | BV21: =IFERROR(__xludf.DUMMYFUNCTION("IFERROR(VLOOKUP(""*""&AQ21&""*"", {""甲"",7,10,11,12,8,4,2,5,1,3,6,9;""乙"",4,8,12,11,10,7,9,6,3,1,5,2;""丙"",3,6,9,7,10,11,12,8,4,2,5,1;""丁"",1,5,2,4,8,12,11,10,7,9,6,3;""戊"",3,6,9,7,10,11,12,8,4,2,5,1;""己"",1,5,2,4,8,12,11,10,7,9,6,3;""庚"",2,5,1,3,6,9,7,10"&",11,12,8,4;""辛"",9,6,3,1,5,2,4,8,12,11,10,7;""壬"",12,8,4,2,5,1,3,6,9,7,10,11;""癸"",11,10,7,9,6,3,1,5,2,4,8,12}, FIND(REGEXREPLACE($G$7,""[^子丑寅卯辰巳午未申酉戌亥]"",""""), ""子丑寅卯辰巳午未申酉戌亥"")+1, FALSE), 0)"),4) -> 4 | BW21: =IFERROR(__xludf.DUMMYFUNCTION("IFERROR(VLOOKUP(""*""&AQ21&""*"", {""甲"",7,10,11,12,8,4,2,5,1,3,6,9;""乙"",4,8,12,11,10,7,9,6,3,1,5,2;""丙"",3,6,9,7,10,11,12,8,4,2,5,1;""丁"",1,5,2,4,8,12,11,10,7,9,6,3;""戊"",3,6,9,7,10,11,12,8,4,2,5,1;""己"",1,5,2,4,8,12,11,10,7,9,6,3;""庚"",2,5,1,3,6,9,7,10"&",11,12,8,4;""辛"",9,6,3,1,5,2,4,8,12,11,10,7;""壬"",12,8,4,2,5,1,3,6,9,7,10,11;""癸"",11,10,7,9,6,3,1,5,2,4,8,12}, FIND(REGEXREPLACE($F$7,""[^子丑寅卯辰巳午未申酉戌亥]"",""""), ""子丑寅卯辰巳午未申酉戌亥"")+1, FALSE), 0)"),3) -> 3 | BX21: =BT21 * (BU21 + BV21 + BW21) -> 18 | BY21: 水 | BZ21: =SUM(BX25:BX26) -> 45 | CA21: =BZ21/$BZ$22*100 -> 27.950311 | CB21: =ROUND((BZ21 / MAX($BZ$17:$BZ$21)) * 10, 0) -> 5 | CC21: 自由の欲求 | CD21: 独創性・独立・物理的／精神的制約の解放 | CF21: 11
F22: =[1]大運!F11 -> 大６ | G22: =[1]大運!G11 -> 庚寅 | H22: =[1]大運!H11 -> 2041 | I22: =[1]大運!I11 -> 60 | J22: =[1]大運!J11 -> 鳳閣星 | K22: =[1]大運!K11 -> 天貴星 | L22: =[1]大運!L11 -> － | M22: =[1]大運!M11 -> 天剋地冲 | ... P22: =[1]大運!P11 | AE22: =RIGHT(AH22, 1) -> 卯 | AF22: =IF(OR($E$6=RIGHT(AM22,1),$E$7=RIGHT(AM22,1)),"殺",AG22-$I$3) -> 6 | AG22: =AG21+1 -> 1987 | AH22: =VLOOKUP(AM22,[1]大運!$B$31:$C$90,2,FALSE) -> 丁卯 | AI22: =VLOOKUP($F$5&"+"&AM22,[1]大運!$H$45:$K$3644,3,FALSE) -> 玉堂星 | AK22: =VLOOKUP($F$5&"+"&AM22,[1]大運!$H$45:$K$3644,4,FALSE) -> 天恍星 | AM22: =IF(MOD((AG22-1900+37),60)=0,60,MOD((AG22-1900+37),60)) -> 4 | AN22: =VLOOKUP($F$5&"+"&AM22,[1]大運!$H$45:$K$3644,2,FALSE) -> 刑 | AO22: =VLOOKUP($G$5&"+"&AM22,[1]大運!$H$45:$K$3644,2,FALSE) -> － | AP22: =VLOOKUP($H$5&"+"&AM22,[1]大運!$H$45:$K$3644,2,FALSE) -> 天剋地冲 | AQ22: =IF(OR(RIGHT(AH23,1)=$E$6,RIGHT(AH23,1)=$E$7),"殺","")&IF(ABS(RIGHT(AM23,1)-RIGHT($F$5,1))=5,"日","")&IF(ABS(RIGHT(AM23,1)-RIGHT($G$5,1))=5,"月","")&IF(ABS(RIGHT(AM23,1)-RIGHT($H$5,1))=5,"年","") | AR22: =IF($AH22="","", IFERROR(IF(COUNTIF($F$6, MID("己庚辛壬癸甲乙丙丁戊", FIND(LEFT($AH22,1), "甲乙丙丁戊己庚辛壬癸"), 1))>0, CHOOSE(INT((FIND(LEFT($AH22,1), "甲己乙庚丙辛丁壬戊癸")+1)/2), "甲己干合", "乙庚干合", "丙辛干合", "丁壬干合", "戊癸干合"), ""), "")) | AS22: =IF($AH22="","", IFERROR(IF(COUNTIF($G$6, MID("己庚辛壬癸甲乙丙丁戊", FIND(LEFT($AH22,1), "甲乙丙丁戊己庚辛壬癸"), 1))>0, CHOOSE(INT((FIND(LEFT($AH22,1), "甲己乙庚丙辛丁壬戊癸")+1)/2), "甲己干合", "乙庚干合", "丙辛干合", "丁壬干合", "戊癸干合"), ""), "")) | AT22: =IF($AH22="","", IFERROR(IF(COUNTIF($H$6, MID("己庚辛壬癸甲乙丙丁戊", FIND(LEFT($AH22,1), "甲乙丙丁戊己庚辛壬癸"), 1))>0, CHOOSE(INT((FIND(LEFT($AH22,1), "甲己乙庚丙辛丁壬戊癸")+1)/2), "甲己干合", "乙庚干合", "丙辛干合", "丁壬干合", "戊癸干合"), ""), "")) | AU22: =INDEX('12運シート'!C:C, MATCH(1, INDEX(('12運シート'!A:A=TRIM($T$42)) * ('12運シート'!B:B=TRIM(RIGHT(AE22, 1))), 0), 0)) -> 再会 | AV22: =INDEX('12運シート'!$E:$E, MATCH(1, INDEX((TRIM('12運シート'!$A:$A)=TRIM($T$42)) * (TRIM('12運シート'!$B:$B)=TRIM(AE22)), 0), 0)) -> 有頂天 | AW22: =VLOOKUP(AV22,$V$6:$W$18, 2, FALSE) -> 第2の絶頂期。過去の縁が繋がり、周囲を巻き込み大きな成果を出す。 | AZ22: =RIGHT(BC22, 1) -> 辰 | BA22: =BA21+1 -> 46148 | BB22: =MOD(BA22 - DATE(2024, 1, 1), 60) + 1 -> 17 | BC22: =VLOOKUP(BB22,[1]大運!$B$31:$C$90,2,FALSE) -> 庚辰 | BD22: =VLOOKUP($F$5 & "+" & (MOD(BA22 - DATE(2024, 1, 1), 60) + 1), [1]大運!$H$45:$K$3644, 3, FALSE) -> 鳳閣星 | BE22: =VLOOKUP($F$5 & "+" & (MOD(BA22 - DATE(2024, 1, 1), 60) + 1), [1]大運!$H$45:$K$3644, 4, FALSE) -> 天南星 | BF22: =VLOOKUP($F$5 & "+" & (MOD(BA22 - DATE(2024, 1, 1), 60) + 1), [1]大運!$H$45:$K$3644, 2, FALSE) -> 半会 | BG22: =VLOOKUP($G$5 & "+" & (MOD(BA22 - DATE(2024, 1, 1), 60) + 1), [1]大運!$H$45:$K$3644, 2, FALSE) -> 半会 | BH22: =VLOOKUP($H$5 & "+" & (MOD(BA22 - DATE(2024, 1, 1), 60) + 1), [1]大運!$H$45:$K$3644, 2, FALSE) -> 支合 | BI22: =IF($BC22="","", IFERROR(IF(COUNTIF($F$6, MID("己庚辛壬癸甲乙丙丁戊", FIND(LEFT($BC22,1), "甲乙丙丁戊己庚辛壬癸"), 1))>0, CHOOSE(INT((FIND(LEFT($BC22,1), "甲己乙庚丙辛丁壬戊癸")+1)/2), "甲己干合", "乙庚干合", "丙辛干合", "丁壬干合", "戊癸干合"), ""), "")) | BJ22: =IF($BC22="","", IFERROR(IF(COUNTIF($G$6, MID("己庚辛壬癸甲乙丙丁戊", FIND(LEFT($BC22,1), "甲乙丙丁戊己庚辛壬癸"), 1))>0, CHOOSE(INT((FIND(LEFT($BC22,1), "甲己乙庚丙辛丁壬戊癸")+1)/2), "甲己干合", "乙庚干合", "丙辛干合", "丁壬干合", "戊癸干合"), ""), "")) | BK22: =IF($BC22="","", IFERROR(IF(COUNTIF($H$6, MID("己庚辛壬癸甲乙丙丁戊", FIND(LEFT($BC22,1), "甲乙丙丁戊己庚辛壬癸"), 1))>0, CHOOSE(INT((FIND(LEFT($BC22,1), "甲己乙庚丙辛丁壬戊癸")+1)/2), "甲己干合", "乙庚干合", "丙辛干合", "丁壬干合", "戊癸干合"), ""), "")) | BL22: =INDEX('12運シート'!C:C, MATCH(1, INDEX(('12運シート'!A:A=TRIM($T$42)) * ('12運シート'!B:B=TRIM(RIGHT(AZ22, 1))), 0), 0)) -> 財成 | BM22: =INDEX('12運シート'!$E:$E, MATCH(1, INDEX((TRIM('12運シート'!$A:$A)=TRIM($T$42)) * (TRIM('12運シート'!$B:$B)=TRIM(AZ22)), 0), 0)) -> 満天 | BN22: =VLOOKUP(BM22,$V$6:$W$18, 2, FALSE) -> 収穫の喜び。物質や人脈などあらゆる財を蓄積し、強固な基盤を作る。 | BQ22: 己 | BT22: =COUNTIF($F$6:$H$10, "*"&BQ22&"*") -> 0 | BU22: =IFERROR(__xludf.DUMMYFUNCTION("IFERROR(VLOOKUP(""*""&AQ22&""*"", {""甲"",7,10,11,12,8,4,2,5,1,3,6,9;""乙"",4,8,12,11,10,7,9,6,3,1,5,2;""丙"",3,6,9,7,10,11,12,8,4,2,5,1;""丁"",1,5,2,4,8,12,11,10,7,9,6,3;""戊"",3,6,9,7,10,11,12,8,4,2,5,1;""己"",1,5,2,4,8,12,11,10,7,9,6,3;""庚"",2,5,1,3,6,9,7,10"&",11,12,8,4;""辛"",9,6,3,1,5,2,4,8,12,11,10,7;""壬"",12,8,4,2,5,1,3,6,9,7,10,11;""癸"",11,10,7,9,6,3,1,5,2,4,8,12}, FIND(REGEXREPLACE($H$7,""[^子丑寅卯辰巳午未申酉戌亥]"",""""), ""子丑寅卯辰巳午未申酉戌亥"")+1, FALSE), 0)"),9) -> 9 | BV22: =IFERROR(__xludf.DUMMYFUNCTION("IFERROR(VLOOKUP(""*""&AQ22&""*"", {""甲"",7,10,11,12,8,4,2,5,1,3,6,9;""乙"",4,8,12,11,10,7,9,6,3,1,5,2;""丙"",3,6,9,7,10,11,12,8,4,2,5,1;""丁"",1,5,2,4,8,12,11,10,7,9,6,3;""戊"",3,6,9,7,10,11,12,8,4,2,5,1;""己"",1,5,2,4,8,12,11,10,7,9,6,3;""庚"",2,5,1,3,6,9,7,10"&",11,12,8,4;""辛"",9,6,3,1,5,2,4,8,12,11,10,7;""壬"",12,8,4,2,5,1,3,6,9,7,10,11;""癸"",11,10,7,9,6,3,1,5,2,4,8,12}, FIND(REGEXREPLACE($G$7,""[^子丑寅卯辰巳午未申酉戌亥]"",""""), ""子丑寅卯辰巳午未申酉戌亥"")+1, FALSE), 0)"),7) -> 7 | BW22: =IFERROR(__xludf.DUMMYFUNCTION("IFERROR(VLOOKUP(""*""&AQ22&""*"", {""甲"",7,10,11,12,8,4,2,5,1,3,6,9;""乙"",4,8,12,11,10,7,9,6,3,1,5,2;""丙"",3,6,9,7,10,11,12,8,4,2,5,1;""丁"",1,5,2,4,8,12,11,10,7,9,6,3;""戊"",3,6,9,7,10,11,12,8,4,2,5,1;""己"",1,5,2,4,8,12,11,10,7,9,6,3;""庚"",2,5,1,3,6,9,7,10"&",11,12,8,4;""辛"",9,6,3,1,5,2,4,8,12,11,10,7;""壬"",12,8,4,2,5,1,3,6,9,7,10,11;""癸"",11,10,7,9,6,3,1,5,2,4,8,12}, FIND(REGEXREPLACE($F$7,""[^子丑寅卯辰巳午未申酉戌亥]"",""""), ""子丑寅卯辰巳午未申酉戌亥"")+1, FALSE), 0)"),1) -> 1 | BX22: =BT22 * (BU22 + BV22 + BW22) -> 0 | BY22: 全体 | BZ22: =SUM(BZ17:BZ21) -> 161 | CA22: =BZ22/$BZ$22*100 -> 100 | CB22: =ROUND((BZ22 / MAX($BZ$17:$BZ$21)) * 10, 0) -> 18 | CF22: 12
F23: =[1]大運!F12 -> 大７ | G23: =[1]大運!G12 -> 己丑 | H23: =[1]大運!H12 -> 2051 | I23: =[1]大運!I12 -> 70 | J23: =[1]大運!J12 -> 石門星 | K23: =[1]大運!K12 -> 天印星 | L23: =[1]大運!L12 -> 支合 | M23: =[1]大運!M12 -> － | ... P23: =[1]大運!P12 | AE23: =RIGHT(AH23, 1) -> 辰 | AF23: =IF(OR($E$6=RIGHT(AM23,1),$E$7=RIGHT(AM23,1)),"殺",AG23-$I$3) -> 7 | AG23: =AG22+1 -> 1988 | AH23: =VLOOKUP(AM23,[1]大運!$B$31:$C$90,2,FALSE) -> 戊辰 | AI23: =VLOOKUP($F$5&"+"&AM23,[1]大運!$H$45:$K$3644,3,FALSE) -> 貫索星 | AK23: =VLOOKUP($F$5&"+"&AM23,[1]大運!$H$45:$K$3644,4,FALSE) -> 天南星 | AM23: =IF(MOD((AG23-1900+37),60)=0,60,MOD((AG23-1900+37),60)) -> 5 | AN23: =VLOOKUP($F$5&"+"&AM23,[1]大運!$H$45:$K$3644,2,FALSE) -> 大半会 | AO23: =VLOOKUP($G$5&"+"&AM23,[1]大運!$H$45:$K$3644,2,FALSE) -> 半会 | AP23: =VLOOKUP($H$5&"+"&AM23,[1]大運!$H$45:$K$3644,2,FALSE) -> 支合 | AQ23: =IF(OR(RIGHT(AH24,1)=$E$6,RIGHT(AH24,1)=$E$7),"殺","")&IF(ABS(RIGHT(AM24,1)-RIGHT($F$5,1))=5,"日","")&IF(ABS(RIGHT(AM24,1)-RIGHT($G$5,1))=5,"月","")&IF(ABS(RIGHT(AM24,1)-RIGHT($H$5,1))=5,"年","") | AR23: =IF($AH23="","", IFERROR(IF(COUNTIF($F$6, MID("己庚辛壬癸甲乙丙丁戊", FIND(LEFT($AH23,1), "甲乙丙丁戊己庚辛壬癸"), 1))>0, CHOOSE(INT((FIND(LEFT($AH23,1), "甲己乙庚丙辛丁壬戊癸")+1)/2), "甲己干合", "乙庚干合", "丙辛干合", "丁壬干合", "戊癸干合"), ""), "")) | AS23: =IF($AH23="","", IFERROR(IF(COUNTIF($G$6, MID("己庚辛壬癸甲乙丙丁戊", FIND(LEFT($AH23,1), "甲乙丙丁戊己庚辛壬癸"), 1))>0, CHOOSE(INT((FIND(LEFT($AH23,1), "甲己乙庚丙辛丁壬戊癸")+1)/2), "甲己干合", "乙庚干合", "丙辛干合", "丁壬干合", "戊癸干合"), ""), "")) | AT23: =IF($AH23="","", IFERROR(IF(COUNTIF($H$6, MID("己庚辛壬癸甲乙丙丁戊", FIND(LEFT($AH23,1), "甲乙丙丁戊己庚辛壬癸"), 1))>0, CHOOSE(INT((FIND(LEFT($AH23,1), "甲己乙庚丙辛丁壬戊癸")+1)/2), "甲己干合", "乙庚干合", "丙辛干合", "丁壬干合", "戊癸干合"), ""), "")) | AU23: =INDEX('12運シート'!C:C, MATCH(1, INDEX(('12運シート'!A:A=TRIM($T$42)) * ('12運シート'!B:B=TRIM(RIGHT(AE23, 1))), 0), 0)) -> 財成 | AV23: =INDEX('12運シート'!$E:$E, MATCH(1, INDEX((TRIM('12運シート'!$A:$A)=TRIM($T$42)) * (TRIM('12運シート'!$B:$B)=TRIM(AE23)), 0), 0)) -> 満天 | AW23: =VLOOKUP(AV23,$V$6:$W$18, 2, FALSE) -> 収穫の喜び。物質や人脈などあらゆる財を蓄積し、強固な基盤を作る。 | AZ23: =RIGHT(BC23, 1) -> 巳 | BA23: =BA22+1 -> 46149 | BB23: =MOD(BA23 - DATE(2024, 1, 1), 60) + 1 -> 18 | BC23: =VLOOKUP(BB23,[1]大運!$B$31:$C$90,2,FALSE) -> 辛巳 | BD23: =VLOOKUP($F$5 & "+" & (MOD(BA23 - DATE(2024, 1, 1), 60) + 1), [1]大運!$H$45:$K$3644, 3, FALSE) -> 調舒星 | BE23: =VLOOKUP($F$5 & "+" & (MOD(BA23 - DATE(2024, 1, 1), 60) + 1), [1]大運!$H$45:$K$3644, 4, FALSE) -> 天禄星 | BF23: =VLOOKUP($F$5 & "+" & (MOD(BA23 - DATE(2024, 1, 1), 60) + 1), [1]大運!$H$45:$K$3644, 2, FALSE) -> － | BG23: =VLOOKUP($G$5 & "+" & (MOD(BA23 - DATE(2024, 1, 1), 60) + 1), [1]大運!$H$45:$K$3644, 2, FALSE) -> 支合 | BH23: =VLOOKUP($H$5 & "+" & (MOD(BA23 - DATE(2024, 1, 1), 60) + 1), [1]大運!$H$45:$K$3644, 2, FALSE) -> 大半会 | BI23: =IF($BC23="","", IFERROR(IF(COUNTIF($F$6, MID("己庚辛壬癸甲乙丙丁戊", FIND(LEFT($BC23,1), "甲乙丙丁戊己庚辛壬癸"), 1))>0, CHOOSE(INT((FIND(LEFT($BC23,1), "甲己乙庚丙辛丁壬戊癸")+1)/2), "甲己干合", "乙庚干合", "丙辛干合", "丁壬干合", "戊癸干合"), ""), "")) | BJ23: =IF($BC23="","", IFERROR(IF(COUNTIF($G$6, MID("己庚辛壬癸甲乙丙丁戊", FIND(LEFT($BC23,1), "甲乙丙丁戊己庚辛壬癸"), 1))>0, CHOOSE(INT((FIND(LEFT($BC23,1), "甲己乙庚丙辛丁壬戊癸")+1)/2), "甲己干合", "乙庚干合", "丙辛干合", "丁壬干合", "戊癸干合"), ""), "")) -> 丙辛干合 | BK23: =IF($BC23="","", IFERROR(IF(COUNTIF($H$6, MID("己庚辛壬癸甲乙丙丁戊", FIND(LEFT($BC23,1), "甲乙丙丁戊己庚辛壬癸"), 1))>0, CHOOSE(INT((FIND(LEFT($BC23,1), "甲己乙庚丙辛丁壬戊癸")+1)/2), "甲己干合", "乙庚干合", "丙辛干合", "丁壬干合", "戊癸干合"), ""), "")) | BL23: =INDEX('12運シート'!C:C, MATCH(1, INDEX(('12運シート'!A:A=TRIM($T$42)) * ('12運シート'!B:B=TRIM(RIGHT(AZ23, 1))), 0), 0)) -> 充実 | BM23: =INDEX('12運シート'!$E:$E, MATCH(1, INDEX((TRIM('12運シート'!$A:$A)=TRIM($T$42)) * (TRIM('12運シート'!$B:$B)=TRIM(AZ23)), 0), 0)) -> 静天 | BN23: =VLOOKUP(BM23,$V$6:$W$18, 2, FALSE) -> 成果が出揃う。精神的な安定と充実の中で平和に人生を俯瞰する時期。 | BQ23: 庚 | BT23: =COUNTIF($F$6:$H$10, "*"&BQ23&"*") -> 1 | BU23: =IFERROR(__xludf.DUMMYFUNCTION("IFERROR(VLOOKUP(""*""&AQ23&""*"", {""甲"",7,10,11,12,8,4,2,5,1,3,6,9;""乙"",4,8,12,11,10,7,9,6,3,1,5,2;""丙"",3,6,9,7,10,11,12,8,4,2,5,1;""丁"",1,5,2,4,8,12,11,10,7,9,6,3;""戊"",3,6,9,7,10,11,12,8,4,2,5,1;""己"",1,5,2,4,8,12,11,10,7,9,6,3;""庚"",2,5,1,3,6,9,7,10"&",11,12,8,4;""辛"",9,6,3,1,5,2,4,8,12,11,10,7;""壬"",12,8,4,2,5,1,3,6,9,7,10,11;""癸"",11,10,7,9,6,3,1,5,2,4,8,12}, FIND(REGEXREPLACE($H$7,""[^子丑寅卯辰巳午未申酉戌亥]"",""""), ""子丑寅卯辰巳午未申酉戌亥"")+1, FALSE), 0)"),12) -> 12 | BV23: =IFERROR(__xludf.DUMMYFUNCTION("IFERROR(VLOOKUP(""*""&AQ23&""*"", {""甲"",7,10,11,12,8,4,2,5,1,3,6,9;""乙"",4,8,12,11,10,7,9,6,3,1,5,2;""丙"",3,6,9,7,10,11,12,8,4,2,5,1;""丁"",1,5,2,4,8,12,11,10,7,9,6,3;""戊"",3,6,9,7,10,11,12,8,4,2,5,1;""己"",1,5,2,4,8,12,11,10,7,9,6,3;""庚"",2,5,1,3,6,9,7,10"&",11,12,8,4;""辛"",9,6,3,1,5,2,4,8,12,11,10,7;""壬"",12,8,4,2,5,1,3,6,9,7,10,11;""癸"",11,10,7,9,6,3,1,5,2,4,8,12}, FIND(REGEXREPLACE($G$7,""[^子丑寅卯辰巳午未申酉戌亥]"",""""), ""子丑寅卯辰巳午未申酉戌亥"")+1, FALSE), 0)"),11) -> 11 | BW23: =IFERROR(__xludf.DUMMYFUNCTION("IFERROR(VLOOKUP(""*""&AQ23&""*"", {""甲"",7,10,11,12,8,4,2,5,1,3,6,9;""乙"",4,8,12,11,10,7,9,6,3,1,5,2;""丙"",3,6,9,7,10,11,12,8,4,2,5,1;""丁"",1,5,2,4,8,12,11,10,7,9,6,3;""戊"",3,6,9,7,10,11,12,8,4,2,5,1;""己"",1,5,2,4,8,12,11,10,7,9,6,3;""庚"",2,5,1,3,6,9,7,10"&",11,12,8,4;""辛"",9,6,3,1,5,2,4,8,12,11,10,7;""壬"",12,8,4,2,5,1,3,6,9,7,10,11;""癸"",11,10,7,9,6,3,1,5,2,4,8,12}, FIND(REGEXREPLACE($F$7,""[^子丑寅卯辰巳午未申酉戌亥]"",""""), ""子丑寅卯辰巳午未申酉戌亥"")+1, FALSE), 0)"),2) -> 2 | BX23: =BT23 * (BU23 + BV23 + BW23) -> 25 | CF23: 13
F24: =[1]大運!F13 -> 大８ | G24: =[1]大運!G13 -> 戊子 | H24: =[1]大運!H13 -> 2061 | I24: =[1]大運!I13 -> 80 | J24: =[1]大運!J13 -> 貫索星 | K24: =[1]大運!K13 -> 天報星 | L24: =[1]大運!L13 -> 律音 | M24: =[1]大運!M13 -> 半会 | ... P24: =[1]大運!P13 | AE24: =RIGHT(AH24, 1) -> 巳 | AF24: =IF(OR($E$6=RIGHT(AM24,1),$E$7=RIGHT(AM24,1)),"殺",AG24-$I$3) -> 8 | AG24: =AG23+1 -> 1989 | AH24: =VLOOKUP(AM24,[1]大運!$B$31:$C$90,2,FALSE) -> 己巳 | AI24: =VLOOKUP($F$5&"+"&AM24,[1]大運!$H$45:$K$3644,3,FALSE) -> 石門星 | AK24: =VLOOKUP($F$5&"+"&AM24,[1]大運!$H$45:$K$3644,4,FALSE) -> 天禄星 | AM24: =IF(MOD((AG24-1900+37),60)=0,60,MOD((AG24-1900+37),60)) -> 6 | AN24: =VLOOKUP($F$5&"+"&AM24,[1]大運!$H$45:$K$3644,2,FALSE) -> － | AO24: =VLOOKUP($G$5&"+"&AM24,[1]大運!$H$45:$K$3644,2,FALSE) -> 支合 | AP24: =VLOOKUP($H$5&"+"&AM24,[1]大運!$H$45:$K$3644,2,FALSE) -> 半会 | AQ24: =IF(OR(RIGHT(AH25,1)=$E$6,RIGHT(AH25,1)=$E$7),"殺","")&IF(ABS(RIGHT(AM25,1)-RIGHT($F$5,1))=5,"日","")&IF(ABS(RIGHT(AM25,1)-RIGHT($G$5,1))=5,"月","")&IF(ABS(RIGHT(AM25,1)-RIGHT($H$5,1))=5,"年","") -> 殺 | AR24: =IF($AH24="","", IFERROR(IF(COUNTIF($F$6, MID("己庚辛壬癸甲乙丙丁戊", FIND(LEFT($AH24,1), "甲乙丙丁戊己庚辛壬癸"), 1))>0, CHOOSE(INT((FIND(LEFT($AH24,1), "甲己乙庚丙辛丁壬戊癸")+1)/2), "甲己干合", "乙庚干合", "丙辛干合", "丁壬干合", "戊癸干合"), ""), "")) | AS24: =IF($AH24="","", IFERROR(IF(COUNTIF($G$6, MID("己庚辛壬癸甲乙丙丁戊", FIND(LEFT($AH24,1), "甲乙丙丁戊己庚辛壬癸"), 1))>0, CHOOSE(INT((FIND(LEFT($AH24,1), "甲己乙庚丙辛丁壬戊癸")+1)/2), "甲己干合", "乙庚干合", "丙辛干合", "丁壬干合", "戊癸干合"), ""), "")) | AT24: =IF($AH24="","", IFERROR(IF(COUNTIF($H$6, MID("己庚辛壬癸甲乙丙丁戊", FIND(LEFT($AH24,1), "甲乙丙丁戊己庚辛壬癸"), 1))>0, CHOOSE(INT((FIND(LEFT($AH24,1), "甲己乙庚丙辛丁壬戊癸")+1)/2), "甲己干合", "乙庚干合", "丙辛干合", "丁壬干合", "戊癸干合"), ""), "")) | AU24: =INDEX('12運シート'!C:C, MATCH(1, INDEX(('12運シート'!A:A=TRIM($T$42)) * ('12運シート'!B:B=TRIM(RIGHT(AE24, 1))), 0), 0)) -> 充実 | AV24: =INDEX('12運シート'!$E:$E, MATCH(1, INDEX((TRIM('12運シート'!$A:$A)=TRIM($T$42)) * (TRIM('12運シート'!$B:$B)=TRIM(AE24)), 0), 0)) -> 静天 | AW24: =VLOOKUP(AV24,$V$6:$W$18, 2, FALSE) -> 成果が出揃う。精神的な安定と充実の中で平和に人生を俯瞰する時期。 | AZ24: =RIGHT(BC24, 1) -> 午 | BA24: =BA23+1 -> 46150 | BB24: =MOD(BA24 - DATE(2024, 1, 1), 60) + 1 -> 19 | BC24: =VLOOKUP(BB24,[1]大運!$B$31:$C$90,2,FALSE) -> 壬午 | BD24: =VLOOKUP($F$5 & "+" & (MOD(BA24 - DATE(2024, 1, 1), 60) + 1), [1]大運!$H$45:$K$3644, 3, FALSE) -> 禄存星 | BE24: =VLOOKUP($F$5 & "+" & (MOD(BA24 - DATE(2024, 1, 1), 60) + 1), [1]大運!$H$45:$K$3644, 4, FALSE) -> 天将星 | BF24: =VLOOKUP($F$5 & "+" & (MOD(BA24 - DATE(2024, 1, 1), 60) + 1), [1]大運!$H$45:$K$3644, 2, FALSE) -> 天剋地冲 | BG24: =VLOOKUP($G$5 & "+" & (MOD(BA24 - DATE(2024, 1, 1), 60) + 1), [1]大運!$H$45:$K$3644, 2, FALSE) -> － | BH24: =VLOOKUP($H$5 & "+" & (MOD(BA24 - DATE(2024, 1, 1), 60) + 1), [1]大運!$H$45:$K$3644, 2, FALSE) -> － | BI24: =IF($BC24="","", IFERROR(IF(COUNTIF($F$6, MID("己庚辛壬癸甲乙丙丁戊", FIND(LEFT($BC24,1), "甲乙丙丁戊己庚辛壬癸"), 1))>0, CHOOSE(INT((FIND(LEFT($BC24,1), "甲己乙庚丙辛丁壬戊癸")+1)/2), "甲己干合", "乙庚干合", "丙辛干合", "丁壬干合", "戊癸干合"), ""), "")) | BJ24: =IF($BC24="","", IFERROR(IF(COUNTIF($G$6, MID("己庚辛壬癸甲乙丙丁戊", FIND(LEFT($BC24,1), "甲乙丙丁戊己庚辛壬癸"), 1))>0, CHOOSE(INT((FIND(LEFT($BC24,1), "甲己乙庚丙辛丁壬戊癸")+1)/2), "甲己干合", "乙庚干合", "丙辛干合", "丁壬干合", "戊癸干合"), ""), "")) | BK24: =IF($BC24="","", IFERROR(IF(COUNTIF($H$6, MID("己庚辛壬癸甲乙丙丁戊", FIND(LEFT($BC24,1), "甲乙丙丁戊己庚辛壬癸"), 1))>0, CHOOSE(INT((FIND(LEFT($BC24,1), "甲己乙庚丙辛丁壬戊癸")+1)/2), "甲己干合", "乙庚干合", "丙辛干合", "丁壬干合", "戊癸干合"), ""), "")) | BL24: =INDEX('12運シート'!C:C, MATCH(1, INDEX(('12運シート'!A:A=TRIM($T$42)) * ('12運シート'!B:B=TRIM(RIGHT(AZ24, 1))), 0), 0)) -> 陰影 | BM24: =INDEX('12運シート'!$E:$E, MATCH(1, INDEX((TRIM('12運シート'!$A:$A)=TRIM($T$42)) * (TRIM('12運シート'!$B:$B)=TRIM(AZ24)), 0), 0)) -> 暗天 | BN24: =VLOOKUP(BM24,$V$6:$W$18, 2, FALSE) -> 運気下降（運の冬入り）。孤独を感じやすいが水面下の自己鍛錬が必要。 | BQ24: 辛 | BT24: =COUNTIF($F$6:$H$10, "*"&BQ24&"*") -> 2 | BU24: =IFERROR(__xludf.DUMMYFUNCTION("IFERROR(VLOOKUP(""*""&AQ24&""*"", {""甲"",7,10,11,12,8,4,2,5,1,3,6,9;""乙"",4,8,12,11,10,7,9,6,3,1,5,2;""丙"",3,6,9,7,10,11,12,8,4,2,5,1;""丁"",1,5,2,4,8,12,11,10,7,9,6,3;""戊"",3,6,9,7,10,11,12,8,4,2,5,1;""己"",1,5,2,4,8,12,11,10,7,9,6,3;""庚"",2,5,1,3,6,9,7,10"&",11,12,8,4;""辛"",9,6,3,1,5,2,4,8,12,11,10,7;""壬"",12,8,4,2,5,1,3,6,9,7,10,11;""癸"",11,10,7,9,6,3,1,5,2,4,8,12}, FIND(REGEXREPLACE($H$7,""[^子丑寅卯辰巳午未申酉戌亥]"",""""), ""子丑寅卯辰巳午未申酉戌亥"")+1, FALSE), 0)"),11) -> 11 | BV24: =IFERROR(__xludf.DUMMYFUNCTION("IFERROR(VLOOKUP(""*""&AQ24&""*"", {""甲"",7,10,11,12,8,4,2,5,1,3,6,9;""乙"",4,8,12,11,10,7,9,6,3,1,5,2;""丙"",3,6,9,7,10,11,12,8,4,2,5,1;""丁"",1,5,2,4,8,12,11,10,7,9,6,3;""戊"",3,6,9,7,10,11,12,8,4,2,5,1;""己"",1,5,2,4,8,12,11,10,7,9,6,3;""庚"",2,5,1,3,6,9,7,10"&",11,12,8,4;""辛"",9,6,3,1,5,2,4,8,12,11,10,7;""壬"",12,8,4,2,5,1,3,6,9,7,10,11;""癸"",11,10,7,9,6,3,1,5,2,4,8,12}, FIND(REGEXREPLACE($G$7,""[^子丑寅卯辰巳午未申酉戌亥]"",""""), ""子丑寅卯辰巳午未申酉戌亥"")+1, FALSE), 0)"),12) -> 12 | BW24: =IFERROR(__xludf.DUMMYFUNCTION("IFERROR(VLOOKUP(""*""&AQ24&""*"", {""甲"",7,10,11,12,8,4,2,5,1,3,6,9;""乙"",4,8,12,11,10,7,9,6,3,1,5,2;""丙"",3,6,9,7,10,11,12,8,4,2,5,1;""丁"",1,5,2,4,8,12,11,10,7,9,6,3;""戊"",3,6,9,7,10,11,12,8,4,2,5,1;""己"",1,5,2,4,8,12,11,10,7,9,6,3;""庚"",2,5,1,3,6,9,7,10"&",11,12,8,4;""辛"",9,6,3,1,5,2,4,8,12,11,10,7;""壬"",12,8,4,2,5,1,3,6,9,7,10,11;""癸"",11,10,7,9,6,3,1,5,2,4,8,12}, FIND(REGEXREPLACE($F$7,""[^子丑寅卯辰巳午未申酉戌亥]"",""""), ""子丑寅卯辰巳午未申酉戌亥"")+1, FALSE), 0)"),9) -> 9 | BX24: =BT24 * (BU24 + BV24 + BW24) -> 64 | CF24: 14
F25: =[1]大運!F14 -> 大９ | G25: =[1]大運!G14 -> 丁亥 | H25: =[1]大運!H14 -> 2071 | I25: =[1]大運!I14 -> 90 | J25: =[1]大運!J14 -> 玉堂星 | K25: =[1]大運!K14 -> 天馳星 | L25: =[1]大運!L14 -> 準方位 | M25: =[1]大運!M14 -> 害 | ... P25: =[1]大運!P14 | AE25: =RIGHT(AH25, 1) -> 午 | AF25: =IF(OR($E$6=RIGHT(AM25,1),$E$7=RIGHT(AM25,1)),"殺",AG25-$I$3) -> 9 | AG25: =AG24+1 -> 1990 | AH25: =VLOOKUP(AM25,[1]大運!$B$31:$C$90,2,FALSE) -> 庚午 | AI25: =VLOOKUP($F$5&"+"&AM25,[1]大運!$H$45:$K$3644,3,FALSE) -> 鳳閣星 | AK25: =VLOOKUP($F$5&"+"&AM25,[1]大運!$H$45:$K$3644,4,FALSE) -> 天将星 | AM25: =IF(MOD((AG25-1900+37),60)=0,60,MOD((AG25-1900+37),60)) -> 7 | AN25: =VLOOKUP($F$5&"+"&AM25,[1]大運!$H$45:$K$3644,2,FALSE) -> 対冲 | AO25: =VLOOKUP($G$5&"+"&AM25,[1]大運!$H$45:$K$3644,2,FALSE) -> － | AP25: =VLOOKUP($H$5&"+"&AM25,[1]大運!$H$45:$K$3644,2,FALSE) -> － | AQ25: =IF(OR(RIGHT(AH26,1)=$E$6,RIGHT(AH26,1)=$E$7),"殺","")&IF(ABS(RIGHT(AM26,1)-RIGHT($F$5,1))=5,"日","")&IF(ABS(RIGHT(AM26,1)-RIGHT($G$5,1))=5,"月","")&IF(ABS(RIGHT(AM26,1)-RIGHT($H$5,1))=5,"年","") -> 殺月 | AR25: =IF($AH25="","", IFERROR(IF(COUNTIF($F$6, MID("己庚辛壬癸甲乙丙丁戊", FIND(LEFT($AH25,1), "甲乙丙丁戊己庚辛壬癸"), 1))>0, CHOOSE(INT((FIND(LEFT($AH25,1), "甲己乙庚丙辛丁壬戊癸")+1)/2), "甲己干合", "乙庚干合", "丙辛干合", "丁壬干合", "戊癸干合"), ""), "")) | AS25: =IF($AH25="","", IFERROR(IF(COUNTIF($G$6, MID("己庚辛壬癸甲乙丙丁戊", FIND(LEFT($AH25,1), "甲乙丙丁戊己庚辛壬癸"), 1))>0, CHOOSE(INT((FIND(LEFT($AH25,1), "甲己乙庚丙辛丁壬戊癸")+1)/2), "甲己干合", "乙庚干合", "丙辛干合", "丁壬干合", "戊癸干合"), ""), "")) | AT25: =IF($AH25="","", IFERROR(IF(COUNTIF($H$6, MID("己庚辛壬癸甲乙丙丁戊", FIND(LEFT($AH25,1), "甲乙丙丁戊己庚辛壬癸"), 1))>0, CHOOSE(INT((FIND(LEFT($AH25,1), "甲己乙庚丙辛丁壬戊癸")+1)/2), "甲己干合", "乙庚干合", "丙辛干合", "丁壬干合", "戊癸干合"), ""), "")) | AU25: =INDEX('12運シート'!C:C, MATCH(1, INDEX(('12運シート'!A:A=TRIM($T$42)) * ('12運シート'!B:B=TRIM(RIGHT(AE25, 1))), 0), 0)) -> 陰影 | AV25: =INDEX('12運シート'!$E:$E, MATCH(1, INDEX((TRIM('12運シート'!$A:$A)=TRIM($T$42)) * (TRIM('12運シート'!$B:$B)=TRIM(AE25)), 0), 0)) -> 暗天 | AW25: =VLOOKUP(AV25,$V$6:$W$18, 2, FALSE) -> 運気下降（運の冬入り）。孤独を感じやすいが水面下の自己鍛錬が必要。 | AZ25: =RIGHT(BC25, 1) -> 未 | BA25: =BA24+1 -> 46151 | BB25: =MOD(BA25 - DATE(2024, 1, 1), 60) + 1 -> 20 | BC25: =VLOOKUP(BB25,[1]大運!$B$31:$C$90,2,FALSE) -> 癸未 | BD25: =VLOOKUP($F$5 & "+" & (MOD(BA25 - DATE(2024, 1, 1), 60) + 1), [1]大運!$H$45:$K$3644, 3, FALSE) -> 司禄星 | BE25: =VLOOKUP($F$5 & "+" & (MOD(BA25 - DATE(2024, 1, 1), 60) + 1), [1]大運!$H$45:$K$3644, 4, FALSE) -> 天堂星 | BF25: =VLOOKUP($F$5 & "+" & (MOD(BA25 - DATE(2024, 1, 1), 60) + 1), [1]大運!$H$45:$K$3644, 2, FALSE) -> 害 | BG25: =VLOOKUP($G$5 & "+" & (MOD(BA25 - DATE(2024, 1, 1), 60) + 1), [1]大運!$H$45:$K$3644, 2, FALSE) -> － | BH25: =VLOOKUP($H$5 & "+" & (MOD(BA25 - DATE(2024, 1, 1), 60) + 1), [1]大運!$H$45:$K$3644, 2, FALSE) -> － | BI25: =IF($BC25="","", IFERROR(IF(COUNTIF($F$6, MID("己庚辛壬癸甲乙丙丁戊", FIND(LEFT($BC25,1), "甲乙丙丁戊己庚辛壬癸"), 1))>0, CHOOSE(INT((FIND(LEFT($BC25,1), "甲己乙庚丙辛丁壬戊癸")+1)/2), "甲己干合", "乙庚干合", "丙辛干合", "丁壬干合", "戊癸干合"), ""), "")) -> 戊癸干合 | BJ25: =IF($BC25="","", IFERROR(IF(COUNTIF($G$6, MID("己庚辛壬癸甲乙丙丁戊", FIND(LEFT($BC25,1), "甲乙丙丁戊己庚辛壬癸"), 1))>0, CHOOSE(INT((FIND(LEFT($BC25,1), "甲己乙庚丙辛丁壬戊癸")+1)/2), "甲己干合", "乙庚干合", "丙辛干合", "丁壬干合", "戊癸干合"), ""), "")) | BK25: =IF($BC25="","", IFERROR(IF(COUNTIF($H$6, MID("己庚辛壬癸甲乙丙丁戊", FIND(LEFT($BC25,1), "甲乙丙丁戊己庚辛壬癸"), 1))>0, CHOOSE(INT((FIND(LEFT($BC25,1), "甲己乙庚丙辛丁壬戊癸")+1)/2), "甲己干合", "乙庚干合", "丙辛干合", "丁壬干合", "戊癸干合"), ""), "")) | BL25: =INDEX('12運シート'!C:C, MATCH(1, INDEX(('12運シート'!A:A=TRIM($T$42)) * ('12運シート'!B:B=TRIM(RIGHT(AZ25, 1))), 0), 0)) -> 停止 | BM25: =INDEX('12運シート'!$E:$E, MATCH(1, INDEX((TRIM('12運シート'!$A:$A)=TRIM($T$42)) * (TRIM('12運シート'!$B:$B)=TRIM(AZ25)), 0), 0)) -> 大曇天 | BN25: =VLOOKUP(BM25,$V$6:$W$18, 2, FALSE) -> 運命の停止（運の真冬時期）。古い価値観を手放す究極の浄化期間。 | BQ25: 壬 | BT25: =COUNTIF($F$6:$H$10, "*"&BQ25&"*") -> 1 | BU25: =IFERROR(__xludf.DUMMYFUNCTION("IFERROR(VLOOKUP(""*""&AQ25&""*"", {""甲"",7,10,11,12,8,4,2,5,1,3,6,9;""乙"",4,8,12,11,10,7,9,6,3,1,5,2;""丙"",3,6,9,7,10,11,12,8,4,2,5,1;""丁"",1,5,2,4,8,12,11,10,7,9,6,3;""戊"",3,6,9,7,10,11,12,8,4,2,5,1;""己"",1,5,2,4,8,12,11,10,7,9,6,3;""庚"",2,5,1,3,6,9,7,10"&",11,12,8,4;""辛"",9,6,3,1,5,2,4,8,12,11,10,7;""壬"",12,8,4,2,5,1,3,6,9,7,10,11;""癸"",11,10,7,9,6,3,1,5,2,4,8,12}, FIND(REGEXREPLACE($H$7,""[^子丑寅卯辰巳午未申酉戌亥]"",""""), ""子丑寅卯辰巳午未申酉戌亥"")+1, FALSE), 0)"),7) -> 7 | BV25: =IFERROR(__xludf.DUMMYFUNCTION("IFERROR(VLOOKUP(""*""&AQ25&""*"", {""甲"",7,10,11,12,8,4,2,5,1,3,6,9;""乙"",4,8,12,11,10,7,9,6,3,1,5,2;""丙"",3,6,9,7,10,11,12,8,4,2,5,1;""丁"",1,5,2,4,8,12,11,10,7,9,6,3;""戊"",3,6,9,7,10,11,12,8,4,2,5,1;""己"",1,5,2,4,8,12,11,10,7,9,6,3;""庚"",2,5,1,3,6,9,7,10"&",11,12,8,4;""辛"",9,6,3,1,5,2,4,8,12,11,10,7;""壬"",12,8,4,2,5,1,3,6,9,7,10,11;""癸"",11,10,7,9,6,3,1,5,2,4,8,12}, FIND(REGEXREPLACE($G$7,""[^子丑寅卯辰巳午未申酉戌亥]"",""""), ""子丑寅卯辰巳午未申酉戌亥"")+1, FALSE), 0)"),9) -> 9 | BW25: =IFERROR(__xludf.DUMMYFUNCTION("IFERROR(VLOOKUP(""*""&AQ25&""*"", {""甲"",7,10,11,12,8,4,2,5,1,3,6,9;""乙"",4,8,12,11,10,7,9,6,3,1,5,2;""丙"",3,6,9,7,10,11,12,8,4,2,5,1;""丁"",1,5,2,4,8,12,11,10,7,9,6,3;""戊"",3,6,9,7,10,11,12,8,4,2,5,1;""己"",1,5,2,4,8,12,11,10,7,9,6,3;""庚"",2,5,1,3,6,9,7,10"&",11,12,8,4;""辛"",9,6,3,1,5,2,4,8,12,11,10,7;""壬"",12,8,4,2,5,1,3,6,9,7,10,11;""癸"",11,10,7,9,6,3,1,5,2,4,8,12}, FIND(REGEXREPLACE($F$7,""[^子丑寅卯辰巳午未申酉戌亥]"",""""), ""子丑寅卯辰巳午未申酉戌亥"")+1, FALSE), 0)"),12) -> 12 | BX25: =BT25 * (BU25 + BV25 + BW25) -> 28 | CF25: 15
AE26: =RIGHT(AH26, 1) -> 未 | AF26: =IF(OR($E$6=RIGHT(AM26,1),$E$7=RIGHT(AM26,1)),"殺",AG26-$I$3) -> 10 | AG26: =AG25+1 -> 1991 | AH26: =VLOOKUP(AM26,[1]大運!$B$31:$C$90,2,FALSE) -> 辛未 | AI26: =VLOOKUP($F$5&"+"&AM26,[1]大運!$H$45:$K$3644,3,FALSE) -> 調舒星 | AK26: =VLOOKUP($F$5&"+"&AM26,[1]大運!$H$45:$K$3644,4,FALSE) -> 天堂星 | AM26: =IF(MOD((AG26-1900+37),60)=0,60,MOD((AG26-1900+37),60)) -> 8 | AN26: =VLOOKUP($F$5&"+"&AM26,[1]大運!$H$45:$K$3644,2,FALSE) -> 害 | AO26: =VLOOKUP($G$5&"+"&AM26,[1]大運!$H$45:$K$3644,2,FALSE) -> － | AP26: =VLOOKUP($H$5&"+"&AM26,[1]大運!$H$45:$K$3644,2,FALSE) -> － | AQ26: =IF(OR(RIGHT(AH27,1)=$E$6,RIGHT(AH27,1)=$E$7),"殺","")&IF(ABS(RIGHT(AM27,1)-RIGHT($F$5,1))=5,"日","")&IF(ABS(RIGHT(AM27,1)-RIGHT($G$5,1))=5,"月","")&IF(ABS(RIGHT(AM27,1)-RIGHT($H$5,1))=5,"年","") | AR26: =IF($AH26="","", IFERROR(IF(COUNTIF($F$6, MID("己庚辛壬癸甲乙丙丁戊", FIND(LEFT($AH26,1), "甲乙丙丁戊己庚辛壬癸"), 1))>0, CHOOSE(INT((FIND(LEFT($AH26,1), "甲己乙庚丙辛丁壬戊癸")+1)/2), "甲己干合", "乙庚干合", "丙辛干合", "丁壬干合", "戊癸干合"), ""), "")) | AS26: =IF($AH26="","", IFERROR(IF(COUNTIF($G$6, MID("己庚辛壬癸甲乙丙丁戊", FIND(LEFT($AH26,1), "甲乙丙丁戊己庚辛壬癸"), 1))>0, CHOOSE(INT((FIND(LEFT($AH26,1), "甲己乙庚丙辛丁壬戊癸")+1)/2), "甲己干合", "乙庚干合", "丙辛干合", "丁壬干合", "戊癸干合"), ""), "")) -> 丙辛干合 | AT26: =IF($AH26="","", IFERROR(IF(COUNTIF($H$6, MID("己庚辛壬癸甲乙丙丁戊", FIND(LEFT($AH26,1), "甲乙丙丁戊己庚辛壬癸"), 1))>0, CHOOSE(INT((FIND(LEFT($AH26,1), "甲己乙庚丙辛丁壬戊癸")+1)/2), "甲己干合", "乙庚干合", "丙辛干合", "丁壬干合", "戊癸干合"), ""), "")) | AU26: =INDEX('12運シート'!C:C, MATCH(1, INDEX(('12運シート'!A:A=TRIM($T$42)) * ('12運シート'!B:B=TRIM(RIGHT(AE26, 1))), 0), 0)) -> 停止 | AV26: =INDEX('12運シート'!$E:$E, MATCH(1, INDEX((TRIM('12運シート'!$A:$A)=TRIM($T$42)) * (TRIM('12運シート'!$B:$B)=TRIM(AE26)), 0), 0)) -> 大曇天 | AW26: =VLOOKUP(AV26,$V$6:$W$18, 2, FALSE) -> 運命の停止（運の真冬時期）。古い価値観を手放す究極の浄化期間。 | AZ26: =RIGHT(BC26, 1) -> 申 | BA26: =BA25+1 -> 46152 | BB26: =MOD(BA26 - DATE(2024, 1, 1), 60) + 1 -> 21 | BC26: =VLOOKUP(BB26,[1]大運!$B$31:$C$90,2,FALSE) -> 甲申 | BD26: =VLOOKUP($F$5 & "+" & (MOD(BA26 - DATE(2024, 1, 1), 60) + 1), [1]大運!$H$45:$K$3644, 3, FALSE) -> 車騎星 | BE26: =VLOOKUP($F$5 & "+" & (MOD(BA26 - DATE(2024, 1, 1), 60) + 1), [1]大運!$H$45:$K$3644, 4, FALSE) -> 天胡星 | BF26: =VLOOKUP($F$5 & "+" & (MOD(BA26 - DATE(2024, 1, 1), 60) + 1), [1]大運!$H$45:$K$3644, 2, FALSE) -> 半会 | BG26: =VLOOKUP($G$5 & "+" & (MOD(BA26 - DATE(2024, 1, 1), 60) + 1), [1]大運!$H$45:$K$3644, 2, FALSE) -> 同 | BH26: =VLOOKUP($H$5 & "+" & (MOD(BA26 - DATE(2024, 1, 1), 60) + 1), [1]大運!$H$45:$K$3644, 2, FALSE) -> 準方位 | BI26: =IF($BC26="","", IFERROR(IF(COUNTIF($F$6, MID("己庚辛壬癸甲乙丙丁戊", FIND(LEFT($BC26,1), "甲乙丙丁戊己庚辛壬癸"), 1))>0, CHOOSE(INT((FIND(LEFT($BC26,1), "甲己乙庚丙辛丁壬戊癸")+1)/2), "甲己干合", "乙庚干合", "丙辛干合", "丁壬干合", "戊癸干合"), ""), "")) | BJ26: =IF($BC26="","", IFERROR(IF(COUNTIF($G$6, MID("己庚辛壬癸甲乙丙丁戊", FIND(LEFT($BC26,1), "甲乙丙丁戊己庚辛壬癸"), 1))>0, CHOOSE(INT((FIND(LEFT($BC26,1), "甲己乙庚丙辛丁壬戊癸")+1)/2), "甲己干合", "乙庚干合", "丙辛干合", "丁壬干合", "戊癸干合"), ""), "")) | BK26: =IF($BC26="","", IFERROR(IF(COUNTIF($H$6, MID("己庚辛壬癸甲乙丙丁戊", FIND(LEFT($BC26,1), "甲乙丙丁戊己庚辛壬癸"), 1))>0, CHOOSE(INT((FIND(LEFT($BC26,1), "甲己乙庚丙辛丁壬戊癸")+1)/2), "甲己干合", "乙庚干合", "丙辛干合", "丁壬干合", "戊癸干合"), ""), "")) | BL26: =INDEX('12運シート'!C:C, MATCH(1, INDEX(('12運シート'!A:A=TRIM($T$42)) * ('12運シート'!B:B=TRIM(RIGHT(AZ26, 1))), 0), 0)) -> 減退 | BM26: =INDEX('12運シート'!$E:$E, MATCH(1, INDEX((TRIM('12運シート'!$A:$A)=TRIM($T$42)) * (TRIM('12運シート'!$B:$B)=TRIM(AZ26)), 0), 0)) -> 雨天 | BN26: =VLOOKUP(BM26,$V$6:$W$18, 2, FALSE) -> カルマの精算。過去の執着をすべて洗い流し、次の春への準備を整える。 | BQ26: 癸 | BT26: =COUNTIF($F$6:$H$10, "*"&BQ26&"*") -> 1 | BU26: =IFERROR(__xludf.DUMMYFUNCTION("IFERROR(VLOOKUP(""*""&AQ26&""*"", {""甲"",7,10,11,12,8,4,2,5,1,3,6,9;""乙"",4,8,12,11,10,7,9,6,3,1,5,2;""丙"",3,6,9,7,10,11,12,8,4,2,5,1;""丁"",1,5,2,4,8,12,11,10,7,9,6,3;""戊"",3,6,9,7,10,11,12,8,4,2,5,1;""己"",1,5,2,4,8,12,11,10,7,9,6,3;""庚"",2,5,1,3,6,9,7,10"&",11,12,8,4;""辛"",9,6,3,1,5,2,4,8,12,11,10,7;""壬"",12,8,4,2,5,1,3,6,9,7,10,11;""癸"",11,10,7,9,6,3,1,5,2,4,8,12}, FIND(REGEXREPLACE($H$7,""[^子丑寅卯辰巳午未申酉戌亥]"",""""), ""子丑寅卯辰巳午未申酉戌亥"")+1, FALSE), 0)"),4) -> 4 | BV26: =IFERROR(__xludf.DUMMYFUNCTION("IFERROR(VLOOKUP(""*""&AQ26&""*"", {""甲"",7,10,11,12,8,4,2,5,1,3,6,9;""乙"",4,8,12,11,10,7,9,6,3,1,5,2;""丙"",3,6,9,7,10,11,12,8,4,2,5,1;""丁"",1,5,2,4,8,12,11,10,7,9,6,3;""戊"",3,6,9,7,10,11,12,8,4,2,5,1;""己"",1,5,2,4,8,12,11,10,7,9,6,3;""庚"",2,5,1,3,6,9,7,10"&",11,12,8,4;""辛"",9,6,3,1,5,2,4,8,12,11,10,7;""壬"",12,8,4,2,5,1,3,6,9,7,10,11;""癸"",11,10,7,9,6,3,1,5,2,4,8,12}, FIND(REGEXREPLACE($G$7,""[^子丑寅卯辰巳午未申酉戌亥]"",""""), ""子丑寅卯辰巳午未申酉戌亥"")+1, FALSE), 0)"),2) -> 2 | BW26: =IFERROR(__xludf.DUMMYFUNCTION("IFERROR(VLOOKUP(""*""&AQ26&""*"", {""甲"",7,10,11,12,8,4,2,5,1,3,6,9;""乙"",4,8,12,11,10,7,9,6,3,1,5,2;""丙"",3,6,9,7,10,11,12,8,4,2,5,1;""丁"",1,5,2,4,8,12,11,10,7,9,6,3;""戊"",3,6,9,7,10,11,12,8,4,2,5,1;""己"",1,5,2,4,8,12,11,10,7,9,6,3;""庚"",2,5,1,3,6,9,7,10"&",11,12,8,4;""辛"",9,6,3,1,5,2,4,8,12,11,10,7;""壬"",12,8,4,2,5,1,3,6,9,7,10,11;""癸"",11,10,7,9,6,3,1,5,2,4,8,12}, FIND(REGEXREPLACE($F$7,""[^子丑寅卯辰巳午未申酉戌亥]"",""""), ""子丑寅卯辰巳午未申酉戌亥"")+1, FALSE), 0)"),11) -> 11 | BX26: =BT26 * (BU26 + BV26 + BW26) -> 17 | CF26: 16
G27: 宿命星 | H27: 1旬 | I27: 2旬 | J27: 3旬 | K27: 4旬 | L27: 5旬 | M27: 6旬 | N27: 7旬 | O27: 8旬 | P27: 9旬 | AE27: =RIGHT(AH27, 1) -> 申 | AF27: =IF(OR($E$6=RIGHT(AM27,1),$E$7=RIGHT(AM27,1)),"殺",AG27-$I$3) -> 11 | AG27: =AG26+1 -> 1992 | AH27: =VLOOKUP(AM27,[1]大運!$B$31:$C$90,2,FALSE) -> 壬申 | AI27: =VLOOKUP($F$5&"+"&AM27,[1]大運!$H$45:$K$3644,3,FALSE) -> 禄存星 | AK27: =VLOOKUP($F$5&"+"&AM27,[1]大運!$H$45:$K$3644,4,FALSE) -> 天胡星 | AM27: =IF(MOD((AG27-1900+37),60)=0,60,MOD((AG27-1900+37),60)) -> 9 | AN27: =VLOOKUP($F$5&"+"&AM27,[1]大運!$H$45:$K$3644,2,FALSE) -> 半会 | AO27: =VLOOKUP($G$5&"+"&AM27,[1]大運!$H$45:$K$3644,2,FALSE) -> 同 | AP27: =VLOOKUP($H$5&"+"&AM27,[1]大運!$H$45:$K$3644,2,FALSE) -> 準方位 | AQ27: =IF(OR(RIGHT(AH28,1)=$E$6,RIGHT(AH28,1)=$E$7),"殺","")&IF(ABS(RIGHT(AM28,1)-RIGHT($F$5,1))=5,"日","")&IF(ABS(RIGHT(AM28,1)-RIGHT($G$5,1))=5,"月","")&IF(ABS(RIGHT(AM28,1)-RIGHT($H$5,1))=5,"年","") -> 日 | AR27: =IF($AH27="","", IFERROR(IF(COUNTIF($F$6, MID("己庚辛壬癸甲乙丙丁戊", FIND(LEFT($AH27,1), "甲乙丙丁戊己庚辛壬癸"), 1))>0, CHOOSE(INT((FIND(LEFT($AH27,1), "甲己乙庚丙辛丁壬戊癸")+1)/2), "甲己干合", "乙庚干合", "丙辛干合", "丁壬干合", "戊癸干合"), ""), "")) | AS27: =IF($AH27="","", IFERROR(IF(COUNTIF($G$6, MID("己庚辛壬癸甲乙丙丁戊", FIND(LEFT($AH27,1), "甲乙丙丁戊己庚辛壬癸"), 1))>0, CHOOSE(INT((FIND(LEFT($AH27,1), "甲己乙庚丙辛丁壬戊癸")+1)/2), "甲己干合", "乙庚干合", "丙辛干合", "丁壬干合", "戊癸干合"), ""), "")) | AT27: =IF($AH27="","", IFERROR(IF(COUNTIF($H$6, MID("己庚辛壬癸甲乙丙丁戊", FIND(LEFT($AH27,1), "甲乙丙丁戊己庚辛壬癸"), 1))>0, CHOOSE(INT((FIND(LEFT($AH27,1), "甲己乙庚丙辛丁壬戊癸")+1)/2), "甲己干合", "乙庚干合", "丙辛干合", "丁壬干合", "戊癸干合"), ""), "")) | AU27: =INDEX('12運シート'!C:C, MATCH(1, INDEX(('12運シート'!A:A=TRIM($T$42)) * ('12運シート'!B:B=TRIM(RIGHT(AE27, 1))), 0), 0)) -> 減退 | AV27: =INDEX('12運シート'!$E:$E, MATCH(1, INDEX((TRIM('12運シート'!$A:$A)=TRIM($T$42)) * (TRIM('12運シート'!$B:$B)=TRIM(AE27)), 0), 0)) -> 雨天 | AW27: =VLOOKUP(AV27,$V$6:$W$18, 2, FALSE) -> カルマの精算。過去の執着をすべて洗い流し、次の春への準備を整える。 | AZ27: =RIGHT(BC27, 1) -> 酉 | BA27: =BA26+1 -> 46153 | BB27: =MOD(BA27 - DATE(2024, 1, 1), 60) + 1 -> 22 | BC27: =VLOOKUP(BB27,[1]大運!$B$31:$C$90,2,FALSE) -> 乙酉 | BD27: =VLOOKUP($F$5 & "+" & (MOD(BA27 - DATE(2024, 1, 1), 60) + 1), [1]大運!$H$45:$K$3644, 3, FALSE) -> 牽牛星 | BE27: =VLOOKUP($F$5 & "+" & (MOD(BA27 - DATE(2024, 1, 1), 60) + 1), [1]大運!$H$45:$K$3644, 4, FALSE) -> 天極星 | BF27: =VLOOKUP($F$5 & "+" & (MOD(BA27 - DATE(2024, 1, 1), 60) + 1), [1]大運!$H$45:$K$3644, 2, FALSE) -> 破 | BG27: =VLOOKUP($G$5 & "+" & (MOD(BA27 - DATE(2024, 1, 1), 60) + 1), [1]大運!$H$45:$K$3644, 2, FALSE) -> 準方位 | BH27: =VLOOKUP($H$5 & "+" & (MOD(BA27 - DATE(2024, 1, 1), 60) + 1), [1]大運!$H$45:$K$3644, 2, FALSE) -> 自刑 | BI27: =IF($BC27="","", IFERROR(IF(COUNTIF($F$6, MID("己庚辛壬癸甲乙丙丁戊", FIND(LEFT($BC27,1), "甲乙丙丁戊己庚辛壬癸"), 1))>0, CHOOSE(INT((FIND(LEFT($BC27,1), "甲己乙庚丙辛丁壬戊癸")+1)/2), "甲己干合", "乙庚干合", "丙辛干合", "丁壬干合", "戊癸干合"), ""), "")) | BJ27: =IF($BC27="","", IFERROR(IF(COUNTIF($G$6, MID("己庚辛壬癸甲乙丙丁戊", FIND(LEFT($BC27,1), "甲乙丙丁戊己庚辛壬癸"), 1))>0, CHOOSE(INT((FIND(LEFT($BC27,1), "甲己乙庚丙辛丁壬戊癸")+1)/2), "甲己干合", "乙庚干合", "丙辛干合", "丁壬干合", "戊癸干合"), ""), "")) | BK27: =IF($BC27="","", IFERROR(IF(COUNTIF($H$6, MID("己庚辛壬癸甲乙丙丁戊", FIND(LEFT($BC27,1), "甲乙丙丁戊己庚辛壬癸"), 1))>0, CHOOSE(INT((FIND(LEFT($BC27,1), "甲己乙庚丙辛丁壬戊癸")+1)/2), "甲己干合", "乙庚干合", "丙辛干合", "丁壬干合", "戊癸干合"), ""), "")) | BL27: =INDEX('12運シート'!C:C, MATCH(1, INDEX(('12運シート'!A:A=TRIM($T$42)) * ('12運シート'!B:B=TRIM(RIGHT(AZ27, 1))), 0), 0)) -> 種子 | BM27: =INDEX('12運シート'!$E:$E, MATCH(1, INDEX((TRIM('12運シート'!$A:$A)=TRIM($T$42)) * (TRIM('12運シート'!$B:$B)=TRIM(AZ27)), 0), 0)) -> 起天 | BN27: =VLOOKUP(BM27,$V$6:$W$18, 2, FALSE) -> 運命の幕開け。過去を断ち切り新しい種をまく開拓期。 | BX27: =SUM(BX18:BX26) -> 161 | CF27: 17
F28: 西 | G28: =LEFT(J6,3) -> 司禄星 | H28: =[1]大運!H18 -> ○非 | I28: =[1]大運!I18 -> ○和 | J28: =[1]大運!J18 -> ⦿非 | K28: =[1]大運!K18 -> ○和 | L28: =[1]大運!L18 -> ◎非 | M28: =[1]大運!M18 -> ◎和 | N28: =[1]大運!N18 -> △非 | O28: =[1]大運!O18 -> △和 | P28: =[1]大運!P18 -> ×非 | AE28: =RIGHT(AH28, 1) -> 酉 | AF28: =IF(OR($E$6=RIGHT(AM28,1),$E$7=RIGHT(AM28,1)),"殺",AG28-$I$3) -> 12 | AG28: =AG27+1 -> 1993 | AH28: =VLOOKUP(AM28,[1]大運!$B$31:$C$90,2,FALSE) -> 癸酉 | AI28: =VLOOKUP($F$5&"+"&AM28,[1]大運!$H$45:$K$3644,3,FALSE) -> 司禄星 | AK28: =VLOOKUP($F$5&"+"&AM28,[1]大運!$H$45:$K$3644,4,FALSE) -> 天極星 | AM28: =IF(MOD((AG28-1900+37),60)=0,60,MOD((AG28-1900+37),60)) -> 10 | AN28: =VLOOKUP($F$5&"+"&AM28,[1]大運!$H$45:$K$3644,2,FALSE) -> 破 | AO28: =VLOOKUP($G$5&"+"&AM28,[1]大運!$H$45:$K$3644,2,FALSE) -> 準方位 | AP28: =VLOOKUP($H$5&"+"&AM28,[1]大運!$H$45:$K$3644,2,FALSE) -> 自刑 | AQ28: =IF(OR(RIGHT(AH29,1)=$E$6,RIGHT(AH29,1)=$E$7),"殺","")&IF(ABS(RIGHT(AM29,1)-RIGHT($F$5,1))=5,"日","")&IF(ABS(RIGHT(AM29,1)-RIGHT($G$5,1))=5,"月","")&IF(ABS(RIGHT(AM29,1)-RIGHT($H$5,1))=5,"年","") | AR28: =IF($AH28="","", IFERROR(IF(COUNTIF($F$6, MID("己庚辛壬癸甲乙丙丁戊", FIND(LEFT($AH28,1), "甲乙丙丁戊己庚辛壬癸"), 1))>0, CHOOSE(INT((FIND(LEFT($AH28,1), "甲己乙庚丙辛丁壬戊癸")+1)/2), "甲己干合", "乙庚干合", "丙辛干合", "丁壬干合", "戊癸干合"), ""), "")) -> 戊癸干合 | AS28: =IF($AH28="","", IFERROR(IF(COUNTIF($G$6, MID("己庚辛壬癸甲乙丙丁戊", FIND(LEFT($AH28,1), "甲乙丙丁戊己庚辛壬癸"), 1))>0, CHOOSE(INT((FIND(LEFT($AH28,1), "甲己乙庚丙辛丁壬戊癸")+1)/2), "甲己干合", "乙庚干合", "丙辛干合", "丁壬干合", "戊癸干合"), ""), "")) | AT28: =IF($AH28="","", IFERROR(IF(COUNTIF($H$6, MID("己庚辛壬癸甲乙丙丁戊", FIND(LEFT($AH28,1), "甲乙丙丁戊己庚辛壬癸"), 1))>0, CHOOSE(INT((FIND(LEFT($AH28,1), "甲己乙庚丙辛丁壬戊癸")+1)/2), "甲己干合", "乙庚干合", "丙辛干合", "丁壬干合", "戊癸干合"), ""), "")) | AU28: =INDEX('12運シート'!C:C, MATCH(1, INDEX(('12運シート'!A:A=TRIM($T$42)) * ('12運シート'!B:B=TRIM(RIGHT(AE28, 1))), 0), 0)) -> 種子 | AV28: =INDEX('12運シート'!$E:$E, MATCH(1, INDEX((TRIM('12運シート'!$A:$A)=TRIM($T$42)) * (TRIM('12運シート'!$B:$B)=TRIM(AE28)), 0), 0)) -> 起天 | AW28: =VLOOKUP(AV28,$V$6:$W$18, 2, FALSE) -> 運命の幕開け。過去を断ち切り新しい種をまく開拓期。 | AZ28: =RIGHT(BC28, 1) -> 戌 | BA28: =BA27+1 -> 46154 | BB28: =MOD(BA28 - DATE(2024, 1, 1), 60) + 1 -> 23 | BC28: =VLOOKUP(BB28,[1]大運!$B$31:$C$90,2,FALSE) -> 丙戌 | BD28: =VLOOKUP($F$5 & "+" & (MOD(BA28 - DATE(2024, 1, 1), 60) + 1), [1]大運!$H$45:$K$3644, 3, FALSE) -> 龍高星 | BE28: =VLOOKUP($F$5 & "+" & (MOD(BA28 - DATE(2024, 1, 1), 60) + 1), [1]大運!$H$45:$K$3644, 4, FALSE) -> 天庫星 | BF28: =VLOOKUP($F$5 & "+" & (MOD(BA28 - DATE(2024, 1, 1), 60) + 1), [1]大運!$H$45:$K$3644, 2, FALSE) -> － | BG28: =VLOOKUP($G$5 & "+" & (MOD(BA28 - DATE(2024, 1, 1), 60) + 1), [1]大運!$H$45:$K$3644, 2, FALSE) -> 準方位 | BH28: =VLOOKUP($H$5 & "+" & (MOD(BA28 - DATE(2024, 1, 1), 60) + 1), [1]大運!$H$45:$K$3644, 2, FALSE) -> 害 | BI28: =IF($BC28="","", IFERROR(IF(COUNTIF($F$6, MID("己庚辛壬癸甲乙丙丁戊", FIND(LEFT($BC28,1), "甲乙丙丁戊己庚辛壬癸"), 1))>0, CHOOSE(INT((FIND(LEFT($BC28,1), "甲己乙庚丙辛丁壬戊癸")+1)/2), "甲己干合", "乙庚干合", "丙辛干合", "丁壬干合", "戊癸干合"), ""), "")) | BJ28: =IF($BC28="","", IFERROR(IF(COUNTIF($G$6, MID("己庚辛壬癸甲乙丙丁戊", FIND(LEFT($BC28,1), "甲乙丙丁戊己庚辛壬癸"), 1))>0, CHOOSE(INT((FIND(LEFT($BC28,1), "甲己乙庚丙辛丁壬戊癸")+1)/2), "甲己干合", "乙庚干合", "丙辛干合", "丁壬干合", "戊癸干合"), ""), "")) | BK28: =IF($BC28="","", IFERROR(IF(COUNTIF($H$6, MID("己庚辛壬癸甲乙丙丁戊", FIND(LEFT($BC28,1), "甲乙丙丁戊己庚辛壬癸"), 1))>0, CHOOSE(INT((FIND(LEFT($BC28,1), "甲己乙庚丙辛丁壬戊癸")+1)/2), "甲己干合", "乙庚干合", "丙辛干合", "丁壬干合", "戊癸干合"), ""), "")) -> 丙辛干合 | BL28: =INDEX('12運シート'!C:C, MATCH(1, INDEX(('12運シート'!A:A=TRIM($T$42)) * ('12運シート'!B:B=TRIM(RIGHT(AZ28, 1))), 0), 0)) -> 緑生 | BM28: =INDEX('12運シート'!$E:$E, MATCH(1, INDEX((TRIM('12運シート'!$A:$A)=TRIM($T$42)) * (TRIM('12運シート'!$B:$B)=TRIM(AZ28)), 0), 0)) -> 吉祥天 | BN28: =VLOOKUP(BM28,$V$6:$W$18, 2, FALSE) -> まいた種が芽吹き、周囲の支援を受けて着実に育つ時期。 | CF28: 18
F29: 中央 | G29: =LEFT(L6,3) -> 鳳閣星 | H29: =[1]大運!H19 -> ×和 | I29: =[1]大運!I19 -> ×非 | J29: =[1]大運!J19 -> ○和 | K29: =[1]大運!K19 -> ○非 | L29: =[1]大運!L19 -> ◎和 | M29: =[1]大運!M19 -> ⦿非 | N29: =[1]大運!N19 -> ◎和 | O29: =[1]大運!O19 -> ◎非 | P29: =[1]大運!P19 -> △和 | Y29: 全体運 | Z29: 仕事運 | AA29: 恋愛結婚運 | AB29: 金運 | AC29: 健康運 | AE29: =RIGHT(AH29, 1) -> 戌 | AF29: =IF(OR($E$6=RIGHT(AM29,1),$E$7=RIGHT(AM29,1)),"殺",AG29-$I$3) -> 13 | AG29: =AG28+1 -> 1994 | AH29: =VLOOKUP(AM29,[1]大運!$B$31:$C$90,2,FALSE) -> 甲戌 | AI29: =VLOOKUP($F$5&"+"&AM29,[1]大運!$H$45:$K$3644,3,FALSE) -> 車騎星 | AK29: =VLOOKUP($F$5&"+"&AM29,[1]大運!$H$45:$K$3644,4,FALSE) -> 天庫星 | AM29: =IF(MOD((AG29-1900+37),60)=0,60,MOD((AG29-1900+37),60)) -> 11 | AN29: =VLOOKUP($F$5&"+"&AM29,[1]大運!$H$45:$K$3644,2,FALSE) -> － | AO29: =VLOOKUP($G$5&"+"&AM29,[1]大運!$H$45:$K$3644,2,FALSE) -> 準方位 | AP29: =VLOOKUP($H$5&"+"&AM29,[1]大運!$H$45:$K$3644,2,FALSE) -> 害 | AQ29: =IF(OR(RIGHT(AH30,1)=$E$6,RIGHT(AH30,1)=$E$7),"殺","")&IF(ABS(RIGHT(AM30,1)-RIGHT($F$5,1))=5,"日","")&IF(ABS(RIGHT(AM30,1)-RIGHT($G$5,1))=5,"月","")&IF(ABS(RIGHT(AM30,1)-RIGHT($H$5,1))=5,"年","") | AR29: =IF($AH29="","", IFERROR(IF(COUNTIF($F$6, MID("己庚辛壬癸甲乙丙丁戊", FIND(LEFT($AH29,1), "甲乙丙丁戊己庚辛壬癸"), 1))>0, CHOOSE(INT((FIND(LEFT($AH29,1), "甲己乙庚丙辛丁壬戊癸")+1)/2), "甲己干合", "乙庚干合", "丙辛干合", "丁壬干合", "戊癸干合"), ""), "")) | AS29: =IF($AH29="","", IFERROR(IF(COUNTIF($G$6, MID("己庚辛壬癸甲乙丙丁戊", FIND(LEFT($AH29,1), "甲乙丙丁戊己庚辛壬癸"), 1))>0, CHOOSE(INT((FIND(LEFT($AH29,1), "甲己乙庚丙辛丁壬戊癸")+1)/2), "甲己干合", "乙庚干合", "丙辛干合", "丁壬干合", "戊癸干合"), ""), "")) | AT29: =IF($AH29="","", IFERROR(IF(COUNTIF($H$6, MID("己庚辛壬癸甲乙丙丁戊", FIND(LEFT($AH29,1), "甲乙丙丁戊己庚辛壬癸"), 1))>0, CHOOSE(INT((FIND(LEFT($AH29,1), "甲己乙庚丙辛丁壬戊癸")+1)/2), "甲己干合", "乙庚干合", "丙辛干合", "丁壬干合", "戊癸干合"), ""), "")) | AU29: =INDEX('12運シート'!C:C, MATCH(1, INDEX(('12運シート'!A:A=TRIM($T$42)) * ('12運シート'!B:B=TRIM(RIGHT(AE29, 1))), 0), 0)) -> 緑生 | AV29: =INDEX('12運シート'!$E:$E, MATCH(1, INDEX((TRIM('12運シート'!$A:$A)=TRIM($T$42)) * (TRIM('12運シート'!$B:$B)=TRIM(AE29)), 0), 0)) -> 吉祥天 | AW29: =VLOOKUP(AV29,$V$6:$W$18, 2, FALSE) -> まいた種が芽吹き、周囲の支援を受けて着実に育つ時期。 | AZ29: =RIGHT(BC29, 1) -> 亥 | BA29: =BA28+1 -> 46155 | BB29: =MOD(BA29 - DATE(2024, 1, 1), 60) + 1 -> 24 | BC29: =VLOOKUP(BB29,[1]大運!$B$31:$C$90,2,FALSE) -> 丁亥 | BD29: =VLOOKUP($F$5 & "+" & (MOD(BA29 - DATE(2024, 1, 1), 60) + 1), [1]大運!$H$45:$K$3644, 3, FALSE) -> 玉堂星 | BE29: =VLOOKUP($F$5 & "+" & (MOD(BA29 - DATE(2024, 1, 1), 60) + 1), [1]大運!$H$45:$K$3644, 4, FALSE) -> 天馳星 | BF29: =VLOOKUP($F$5 & "+" & (MOD(BA29 - DATE(2024, 1, 1), 60) + 1), [1]大運!$H$45:$K$3644, 2, FALSE) -> 準方位 | BG29: =VLOOKUP($G$5 & "+" & (MOD(BA29 - DATE(2024, 1, 1), 60) + 1), [1]大運!$H$45:$K$3644, 2, FALSE) -> 害 | BH29: =VLOOKUP($H$5 & "+" & (MOD(BA29 - DATE(2024, 1, 1), 60) + 1), [1]大運!$H$45:$K$3644, 2, FALSE) -> － | BI29: =IF($BC29="","", IFERROR(IF(COUNTIF($F$6, MID("己庚辛壬癸甲乙丙丁戊", FIND(LEFT($BC29,1), "甲乙丙丁戊己庚辛壬癸"), 1))>0, CHOOSE(INT((FIND(LEFT($BC29,1), "甲己乙庚丙辛丁壬戊癸")+1)/2), "甲己干合", "乙庚干合", "丙辛干合", "丁壬干合", "戊癸干合"), ""), "")) | BJ29: =IF($BC29="","", IFERROR(IF(COUNTIF($G$6, MID("己庚辛壬癸甲乙丙丁戊", FIND(LEFT($BC29,1), "甲乙丙丁戊己庚辛壬癸"), 1))>0, CHOOSE(INT((FIND(LEFT($BC29,1), "甲己乙庚丙辛丁壬戊癸")+1)/2), "甲己干合", "乙庚干合", "丙辛干合", "丁壬干合", "戊癸干合"), ""), "")) | BK29: =IF($BC29="","", IFERROR(IF(COUNTIF($H$6, MID("己庚辛壬癸甲乙丙丁戊", FIND(LEFT($BC29,1), "甲乙丙丁戊己庚辛壬癸"), 1))>0, CHOOSE(INT((FIND(LEFT($BC29,1), "甲己乙庚丙辛丁壬戊癸")+1)/2), "甲己干合", "乙庚干合", "丙辛干合", "丁壬干合", "戊癸干合"), ""), "")) | BL29: =INDEX('12運シート'!C:C, MATCH(1, INDEX(('12運シート'!A:A=TRIM($T$42)) * ('12運シート'!B:B=TRIM(RIGHT(AZ29, 1))), 0), 0)) -> 立花 | BM29: =INDEX('12運シート'!$E:$E, MATCH(1, INDEX((TRIM('12運シート'!$A:$A)=TRIM($T$42)) * (TRIM('12運シート'!$B:$B)=TRIM(AZ29)), 0), 0)) -> 弁財天 | BN29: =VLOOKUP(BM29,$V$6:$W$18, 2, FALSE) -> 才能がパッと花開き、今後の人生を左右する重要な決定を下す発展期。 | CF29: 19
F30: 東 | G30: =LEFT(N6,3) -> 調舒星 | H30: =[1]大運!H20 -> ×非 | I30: =[1]大運!I20 -> ×和 | J30: =[1]大運!J20 -> ○非 | K30: =[1]大運!K20 -> ○和 | L30: =[1]大運!L20 -> ⦿非 | M30: =[1]大運!M20 -> ○和 | N30: =[1]大運!N20 -> ◎非 | O30: =[1]大運!O20 -> ◎和 | P30: =[1]大運!P20 -> △非 | V30: 土星人（＋） | W30: 戌亥＋ | X30: 裏おひつじ座 | Y30: 群れることを好まない孤高の完璧主義者としての特性が、人生の基盤となります。他人の意見や世間の常識に流されることなく、内なるルールに絶対の自信を持って独自の道を切り開く強さを持っています。集団行動では息苦しさを感じることもありますが、妥協を許さないその生き様は、最終的に多くの人から一目置かれる存在へとあなたを押し上げます。信念を貫くことで運気が開ける大器です。 | Z30: 裁量権のある単独ポジションや専門職において、誰も真似できないような圧倒的な成果を上げて大成します。組織の歯車として細かな指示を受ける環境では能力が半減してしまうため、自らの判断で動けるフリーランスやリーダー職が最適です。与えられた任務に対しては完璧を目指すため、その圧倒的なクオリティが周囲からの絶大な評価と信頼に直結していくでしょう。 | AA30: 恋愛や結婚においては、依存し合う関係を好まず、自立と尊敬をベースにした精神的な繋がりを何よりも重視します。ベタベタした交際よりも、お互いがひとりの人間として目標に向かって努力し、高め合えるようなパートナーシップが理想です。相手の領域に踏み込みすぎず、自分の聖域も守りながら、深く静かな愛情を育んでいく大人の恋愛関係を築き上げます。 | AB30: 完璧主義に基づく徹底したリサーチ能力と自己管理能力が、手堅く確実な財産形成に直結します。ギャンブルや不確実な投資には手を出さず、自らの実力と専門スキルでお金を稼ぎ出す力が非常に強いです。自分の納得のいく「質の高いもの」には惜しみなくお金を使いますが、無駄遣いは一切しないため、生涯を通じて安定した力強い金運を維持することができるでしょう。 | AC30: 精神的な緊張状態が続きやすいため、意識的に一人になって心身をリラックスさせる「完全なオフの時間」を設けることが健康運アップの鍵です。他人に気を遣わず、自分のペースで楽しめる単独の趣味やスポーツ、または自然の中で静かに過ごす時間が、すり減ったエネルギーを強力にチャージしてくれます。質の高い睡眠環境を整えることも重要です。 | AE30: =RIGHT(AH30, 1) -> 亥 | AF30: =IF(OR($E$6=RIGHT(AM30,1),$E$7=RIGHT(AM30,1)),"殺",AG30-$I$3) -> 14 | AG30: =AG29+1 -> 1995 | AH30: =VLOOKUP(AM30,[1]大運!$B$31:$C$90,2,FALSE) -> 乙亥 | AI30: =VLOOKUP($F$5&"+"&AM30,[1]大運!$H$45:$K$3644,3,FALSE) -> 牽牛星 | AK30: =VLOOKUP($F$5&"+"&AM30,[1]大運!$H$45:$K$3644,4,FALSE) -> 天馳星 | AM30: =IF(MOD((AG30-1900+37),60)=0,60,MOD((AG30-1900+37),60)) -> 12 | AN30: =VLOOKUP($F$5&"+"&AM30,[1]大運!$H$45:$K$3644,2,FALSE) -> 準方位 | AO30: =VLOOKUP($G$5&"+"&AM30,[1]大運!$H$45:$K$3644,2,FALSE) -> 害 | AP30: =VLOOKUP($H$5&"+"&AM30,[1]大運!$H$45:$K$3644,2,FALSE) -> － | AQ30: =IF(OR(RIGHT(AH30,1)=$E$6,RIGHT(AH30,1)=$E$7),"殺","")&IF(ABS(RIGHT(AM30,1)-RIGHT($F$5,1))=5,"日","")&IF(ABS(RIGHT(AM30,1)-RIGHT($G$5,1))=5,"月","")&IF(ABS(RIGHT(AM30,1)-RIGHT($H$5,1))=5,"年","") | AR30: =IF($AH30="","", IFERROR(IF(COUNTIF($F$6, MID("己庚辛壬癸甲乙丙丁戊", FIND(LEFT($AH30,1), "甲乙丙丁戊己庚辛壬癸"), 1))>0, CHOOSE(INT((FIND(LEFT($AH30,1), "甲己乙庚丙辛丁壬戊癸")+1)/2), "甲己干合", "乙庚干合", "丙辛干合", "丁壬干合", "戊癸干合"), ""), "")) | AS30: =IF($AH30="","", IFERROR(IF(COUNTIF($G$6, MID("己庚辛壬癸甲乙丙丁戊", FIND(LEFT($AH30,1), "甲乙丙丁戊己庚辛壬癸"), 1))>0, CHOOSE(INT((FIND(LEFT($AH30,1), "甲己乙庚丙辛丁壬戊癸")+1)/2), "甲己干合", "乙庚干合", "丙辛干合", "丁壬干合", "戊癸干合"), ""), "")) | AT30: =IF($AH30="","", IFERROR(IF(COUNTIF($H$6, MID("己庚辛壬癸甲乙丙丁戊", FIND(LEFT($AH30,1), "甲乙丙丁戊己庚辛壬癸"), 1))>0, CHOOSE(INT((FIND(LEFT($AH30,1), "甲己乙庚丙辛丁壬戊癸")+1)/2), "甲己干合", "乙庚干合", "丙辛干合", "丁壬干合", "戊癸干合"), ""), "")) | AU30: =INDEX('12運シート'!C:C, MATCH(1, INDEX(('12運シート'!A:A=TRIM($T$42)) * ('12運シート'!B:B=TRIM(RIGHT(AE30, 1))), 0), 0)) -> 立花 | AV30: =INDEX('12運シート'!$E:$E, MATCH(1, INDEX((TRIM('12運シート'!$A:$A)=TRIM($T$42)) * (TRIM('12運シート'!$B:$B)=TRIM(AE30)), 0), 0)) -> 弁財天 | AW30: =VLOOKUP(AV30,$V$6:$W$18, 2, FALSE) -> 才能がパッと花開き、今後の人生を左右する重要な決定を下す発展期。 | AZ30: =RIGHT(BC30, 1) -> 子 | BA30: =BA29+1 -> 46156 | BB30: =MOD(BA30 - DATE(2024, 1, 1), 60) + 1 -> 25 | BC30: =VLOOKUP(BB30,[1]大運!$B$31:$C$90,2,FALSE) -> 戊子 | BD30: =VLOOKUP($F$5 & "+" & (MOD(BA30 - DATE(2024, 1, 1), 60) + 1), [1]大運!$H$45:$K$3644, 3, FALSE) -> 貫索星 | BE30: =VLOOKUP($F$5 & "+" & (MOD(BA30 - DATE(2024, 1, 1), 60) + 1), [1]大運!$H$45:$K$3644, 4, FALSE) -> 天報星 | BF30: =VLOOKUP($F$5 & "+" & (MOD(BA30 - DATE(2024, 1, 1), 60) + 1), [1]大運!$H$45:$K$3644, 2, FALSE) -> 律音 | BG30: =VLOOKUP($G$5 & "+" & (MOD(BA30 - DATE(2024, 1, 1), 60) + 1), [1]大運!$H$45:$K$3644, 2, FALSE) -> 半会 | BH30: =VLOOKUP($H$5 & "+" & (MOD(BA30 - DATE(2024, 1, 1), 60) + 1), [1]大運!$H$45:$K$3644, 2, FALSE) -> 破 | BI30: =IF($BC30="","", IFERROR(IF(COUNTIF($F$6, MID("己庚辛壬癸甲乙丙丁戊", FIND(LEFT($BC30,1), "甲乙丙丁戊己庚辛壬癸"), 1))>0, CHOOSE(INT((FIND(LEFT($BC30,1), "甲己乙庚丙辛丁壬戊癸")+1)/2), "甲己干合", "乙庚干合", "丙辛干合", "丁壬干合", "戊癸干合"), ""), "")) | BJ30: =IF($BC30="","", IFERROR(IF(COUNTIF($G$6, MID("己庚辛壬癸甲乙丙丁戊", FIND(LEFT($BC30,1), "甲乙丙丁戊己庚辛壬癸"), 1))>0, CHOOSE(INT((FIND(LEFT($BC30,1), "甲己乙庚丙辛丁壬戊癸")+1)/2), "甲己干合", "乙庚干合", "丙辛干合", "丁壬干合", "戊癸干合"), ""), "")) | BK30: =IF($BC30="","", IFERROR(IF(COUNTIF($H$6, MID("己庚辛壬癸甲乙丙丁戊", FIND(LEFT($BC30,1), "甲乙丙丁戊己庚辛壬癸"), 1))>0, CHOOSE(INT((FIND(LEFT($BC30,1), "甲己乙庚丙辛丁壬戊癸")+1)/2), "甲己干合", "乙庚干合", "丙辛干合", "丁壬干合", "戊癸干合"), ""), "")) | BL30: =INDEX('12運シート'!C:C, MATCH(1, INDEX(('12運シート'!A:A=TRIM($T$42)) * ('12運シート'!B:B=TRIM(RIGHT(AZ30, 1))), 0), 0)) -> 健弱 | BM30: =INDEX('12運シート'!$E:$E, MATCH(1, INDEX((TRIM('12運シート'!$A:$A)=TRIM($T$42)) * (TRIM('12運シート'!$B:$B)=TRIM(AZ30)), 0), 0)) -> 曇天 | BN30: =VLOOKUP(BM30,$V$6:$W$18, 2, FALSE) -> 運気の勢いに心身が追いつかない小休止。自己治癒の時期。 | CF30: 20
F31: 南 | G31: =LEFT(L7,3) -> 龍高星 | H31: =[1]大運!H21 -> ◎和 | I31: =[1]大運!I21 -> ◎非 | J31: =[1]大運!J21 -> △和 | K31: =[1]大運!K21 -> △非 | L31: =[1]大運!L21 -> ×和 | M31: =[1]大運!M21 -> ×非 | N31: =[1]大運!N21 -> ○和 | O31: =[1]大運!O21 -> ○非 | P31: =[1]大運!P21 -> ◎和 | V31: 土星人（－） | W31: 戌亥－ | X31: 裏うお座 | Y31: 妥協を許さない極めて厳格で気高い理想主義者としての魂を持ち、独自の美学を追求する運命にあります。優しさの中に決して折れない鋭い剣を隠し持ち、自らの信じる正義や理想を現実世界で体現しようと闘い続けます。世俗的なものに迎合しないため孤立感を覚えることもありますが、その高い精神性は周囲に深い感動を与え、精神的な指導者やカリスマとしてのポジションを確立していくことになります。 | Z31: 独自の精神世界を表現できる芸術分野や、高度な技術が求められるプロフェッショナルな仕事において、孤高の地位を築き上げます。ルーチンワークや妥協を強いられる職場では魂が枯渇してしまうため、自らの世界観を存分に発揮できるクリエイティブな環境が天職です。ストイックに技術を磨き上げる姿勢は、やがて業界内で唯一無二の評価を獲得することに繋がります。 | AA31: 表面的な条件やルックスではなく、魂レベルで共鳴できるような深く運命的な愛を探し求めるロマンチストです。一度この人だと決めた相手に対しては、すべてを包み込むような究極の優しさと深い愛情を注ぎ込みます。精神的な絆を何よりも大切にするため、言葉にしなくてもお互いの感情を理解し合えるような、スピリチュアルな繋がりを感じる結婚生活に強い憧れを抱きます。 | AB31: 物質的な豊かさよりも「精神的な満足」を重視する傾向があるため、お金そのものへの執着は薄いタイプです。しかし、追求を重ねた専門的なスキルや芸術的な才能が、結果として莫大な富を引き寄せるという不思議な金運を持っています。自らの直感や美意識を信じて自己投資を続けることで、後から自然とお金がついてくるという理想的な金銭サイクルを作り出すことができます。 | AC31: 高い理想と現実のギャップに悩みやすく、メンタル面からの不調が体調に表れやすいデリケートな体質です。気高い精神を休ませるために、音楽やアート、アロマテラピーなど、五感を癒す美しいものに触れる時間を日常に取り入れてください。また、水辺の近くを散歩したり、質の高い入浴時間を確保することで、体内に溜まったマイナスエネルギーを効果的に浄化できます。 | AE31: =RIGHT(AH31, 1) -> 子 | AF31: =IF(OR($E$6=RIGHT(AM31,1),$E$7=RIGHT(AM31,1)),"殺",AG31-$I$3) -> 15 | AG31: =AG30+1 -> 1996 | AH31: =VLOOKUP(AM31,[1]大運!$B$31:$C$90,2,FALSE) -> 丙子 | AI31: =VLOOKUP($F$5&"+"&AM31,[1]大運!$H$45:$K$3644,3,FALSE) -> 龍高星 | AK31: =VLOOKUP($F$5&"+"&AM31,[1]大運!$H$45:$K$3644,4,FALSE) -> 天報星 | AM31: =IF(MOD((AG31-1900+37),60)=0,60,MOD((AG31-1900+37),60)) -> 13 | AN31: =VLOOKUP($F$5&"+"&AM31,[1]大運!$H$45:$K$3644,2,FALSE) -> 同 | AO31: =VLOOKUP($G$5&"+"&AM31,[1]大運!$H$45:$K$3644,2,FALSE) -> 大半会 | AP31: =VLOOKUP($H$5&"+"&AM31,[1]大運!$H$45:$K$3644,2,FALSE) -> 破 | AQ31: =IF(OR(RIGHT(AH31,1)=$E$6,RIGHT(AH31,1)=$E$7),"殺","")&IF(ABS(RIGHT(AM31,1)-RIGHT($F$5,1))=5,"日","")&IF(ABS(RIGHT(AM31,1)-RIGHT($G$5,1))=5,"月","")&IF(ABS(RIGHT(AM31,1)-RIGHT($H$5,1))=5,"年","") -> 年 | AR31: =IF($AH31="","", IFERROR(IF(COUNTIF($F$6, MID("己庚辛壬癸甲乙丙丁戊", FIND(LEFT($AH31,1), "甲乙丙丁戊己庚辛壬癸"), 1))>0, CHOOSE(INT((FIND(LEFT($AH31,1), "甲己乙庚丙辛丁壬戊癸")+1)/2), "甲己干合", "乙庚干合", "丙辛干合", "丁壬干合", "戊癸干合"), ""), "")) | AS31: =IF($AH31="","", IFERROR(IF(COUNTIF($G$6, MID("己庚辛壬癸甲乙丙丁戊", FIND(LEFT($AH31,1), "甲乙丙丁戊己庚辛壬癸"), 1))>0, CHOOSE(INT((FIND(LEFT($AH31,1), "甲己乙庚丙辛丁壬戊癸")+1)/2), "甲己干合", "乙庚干合", "丙辛干合", "丁壬干合", "戊癸干合"), ""), "")) | AT31: =IF($AH31="","", IFERROR(IF(COUNTIF($H$6, MID("己庚辛壬癸甲乙丙丁戊", FIND(LEFT($AH31,1), "甲乙丙丁戊己庚辛壬癸"), 1))>0, CHOOSE(INT((FIND(LEFT($AH31,1), "甲己乙庚丙辛丁壬戊癸")+1)/2), "甲己干合", "乙庚干合", "丙辛干合", "丁壬干合", "戊癸干合"), ""), "")) -> 丙辛干合 | AU31: =INDEX('12運シート'!C:C, MATCH(1, INDEX(('12運シート'!A:A=TRIM($T$42)) * ('12運シート'!B:B=TRIM(RIGHT(AE31, 1))), 0), 0)) -> 健弱 | AV31: =INDEX('12運シート'!$E:$E, MATCH(1, INDEX((TRIM('12運シート'!$A:$A)=TRIM($T$42)) * (TRIM('12運シート'!$B:$B)=TRIM(AE31)), 0), 0)) -> 曇天 | AW31: =VLOOKUP(AV31,$V$6:$W$18, 2, FALSE) -> 運気の勢いに心身が追いつかない小休止。自己治癒の時期。 | AZ31: =RIGHT(BC31, 1) -> 丑 | BA31: =BA30+1 -> 46157 | BB31: =MOD(BA31 - DATE(2024, 1, 1), 60) + 1 -> 26 | BC31: =VLOOKUP(BB31,[1]大運!$B$31:$C$90,2,FALSE) -> 己丑 | BD31: =VLOOKUP($F$5 & "+" & (MOD(BA31 - DATE(2024, 1, 1), 60) + 1), [1]大運!$H$45:$K$3644, 3, FALSE) -> 石門星 | BE31: =VLOOKUP($F$5 & "+" & (MOD(BA31 - DATE(2024, 1, 1), 60) + 1), [1]大運!$H$45:$K$3644, 4, FALSE) -> 天印星 | BF31: =VLOOKUP($F$5 & "+" & (MOD(BA31 - DATE(2024, 1, 1), 60) + 1), [1]大運!$H$45:$K$3644, 2, FALSE) -> 支合 | BG31: =VLOOKUP($G$5 & "+" & (MOD(BA31 - DATE(2024, 1, 1), 60) + 1), [1]大運!$H$45:$K$3644, 2, FALSE) -> － | BH31: =VLOOKUP($H$5 & "+" & (MOD(BA31 - DATE(2024, 1, 1), 60) + 1), [1]大運!$H$45:$K$3644, 2, FALSE) -> 半会 | BI31: =IF($BC31="","", IFERROR(IF(COUNTIF($F$6, MID("己庚辛壬癸甲乙丙丁戊", FIND(LEFT($BC31,1), "甲乙丙丁戊己庚辛壬癸"), 1))>0, CHOOSE(INT((FIND(LEFT($BC31,1), "甲己乙庚丙辛丁壬戊癸")+1)/2), "甲己干合", "乙庚干合", "丙辛干合", "丁壬干合", "戊癸干合"), ""), "")) | BJ31: =IF($BC31="","", IFERROR(IF(COUNTIF($G$6, MID("己庚辛壬癸甲乙丙丁戊", FIND(LEFT($BC31,1), "甲乙丙丁戊己庚辛壬癸"), 1))>0, CHOOSE(INT((FIND(LEFT($BC31,1), "甲己乙庚丙辛丁壬戊癸")+1)/2), "甲己干合", "乙庚干合", "丙辛干合", "丁壬干合", "戊癸干合"), ""), "")) | BK31: =IF($BC31="","", IFERROR(IF(COUNTIF($H$6, MID("己庚辛壬癸甲乙丙丁戊", FIND(LEFT($BC31,1), "甲乙丙丁戊己庚辛壬癸"), 1))>0, CHOOSE(INT((FIND(LEFT($BC31,1), "甲己乙庚丙辛丁壬戊癸")+1)/2), "甲己干合", "乙庚干合", "丙辛干合", "丁壬干合", "戊癸干合"), ""), "")) | BL31: =INDEX('12運シート'!C:C, MATCH(1, INDEX(('12運シート'!A:A=TRIM($T$42)) * ('12運シート'!B:B=TRIM(RIGHT(AZ31, 1))), 0), 0)) -> 達成 | BM31: =INDEX('12運シート'!$E:$E, MATCH(1, INDEX((TRIM('12運シート'!$A:$A)=TRIM($T$42)) * (TRIM('12運シート'!$B:$B)=TRIM(AZ31)), 0), 0)) -> 韋駄天 | BN31: =VLOOKUP(BM31,$V$6:$W$18, 2, FALSE) -> 運気絶頂。これまでの努力が実を結び、最高のスポットライトを浴びる。 | CF31: 21
F32: 北 | G32: =LEFT(L5,3) -> 調舒星 | H32: =[1]大運!H22 -> ×非 | I32: =[1]大運!I22 -> ×和 | J32: =[1]大運!J22 -> ○非 | K32: =[1]大運!K22 -> ○和 | L32: =[1]大運!L22 -> ⦿非 | M32: =[1]大運!M22 -> ○和 | N32: =[1]大運!N22 -> ◎非 | O32: =[1]大運!O22 -> ◎和 | P32: =[1]大運!P22 -> △非 | V32: 金星人（＋） | W32: 申酉＋ | X32: 裏ふたご座 | Y32: 人と関わることで魂が最も輝く、超・社交型としてのバイオリズムを持っています。直感で即座に行動を起こす抜群の機動力で、常に時代の最先端やトレンドを創り出していくエネルギッシュな運命です。好奇心旺盛でフットワークが軽く、新しい情報や人脈を次々と引き寄せるため、あなたの周囲には常に活気と笑顔が溢れます。停滞を嫌い、変化を楽しみながら人生をハイスピードで駆け抜けていくでしょう。 | Z32: ルーチンワークを嫌い、営業や企画など、常に変化と刺激のある職場環境に身を置くことで最高のパフォーマンスを発揮する最適性があります。持ち前のコミュニケーション能力と頭の回転の速さを活かし、人と人とを繋ぐハブのような役割を担うと大成功を収めます。マルチタスクが得意なため、複数のプロジェクトを同時に回しながら次々と結果を出していくことができます。 | AA32: 恋愛においても「楽しさ」と「新鮮さ」を最重視し、まるで親友同士のように軽やかで明るい交際を求めます。束縛されたり重苦しい関係になったりすると途端に熱が冷めてしまうため、お互いの自由を尊重し合いながら、様々な場所へ出かけて新しい体験を共有できるパートナーがベストです。結婚後も所帯染みることなく、いつまでも若々しく刺激的な関係を築きます。 | AB32: 情報収集能力の高さがそのまま金運に直結するタイプです。最新のトレンドや有利な投資情報を誰よりも早くキャッチし、機動力を活かしてサクッと利益を上げる才能があります。交際費や自己投資への出費は多くなりがちですが、それが「生ききたお金」となって人脈や新しいチャンスとして何倍にもなって返ってくるため、ケチケチせずに経済を回していくスタイルが金運をさらに引き上げます。 | AC32: 常に動き回り、頭もフル回転しているため、本人が気づかないうちに神経が疲労困憊していることがあります。オンとオフの切り替えを意識し、情報を完全にシャットアウトする「デジタルデトックス」の時間を意識的に作ることが健康維持の秘訣です。睡眠不足は運気低下に直結するため、良質な睡眠を確保し、疲労を翌日に持ち越さないようケアを怠らないようにしましょう。 | AE32: =RIGHT(AH32, 1) -> 丑 | AF32: =IF(OR($E$6=RIGHT(AM32,1),$E$7=RIGHT(AM32,1)),"殺",AG32-$I$3) -> 16 | AG32: =AG31+1 -> 1997 | AH32: =VLOOKUP(AM32,[1]大運!$B$31:$C$90,2,FALSE) -> 丁丑 | AI32: =VLOOKUP($F$5&"+"&AM32,[1]大運!$H$45:$K$3644,3,FALSE) -> 玉堂星 | AK32: =VLOOKUP($F$5&"+"&AM32,[1]大運!$H$45:$K$3644,4,FALSE) -> 天印星 | AM32: =IF(MOD((AG32-1900+37),60)=0,60,MOD((AG32-1900+37),60)) -> 14 | AN32: =VLOOKUP($F$5&"+"&AM32,[1]大運!$H$45:$K$3644,2,FALSE) -> 支合 | AO32: =VLOOKUP($G$5&"+"&AM32,[1]大運!$H$45:$K$3644,2,FALSE) -> － | AP32: =VLOOKUP($H$5&"+"&AM32,[1]大運!$H$45:$K$3644,2,FALSE) -> 半会 | AQ32: =IF(OR(RIGHT(AH32,1)=$E$6,RIGHT(AH32,1)=$E$7),"殺","")&IF(ABS(RIGHT(AM32,1)-RIGHT($F$5,1))=5,"日","")&IF(ABS(RIGHT(AM32,1)-RIGHT($G$5,1))=5,"月","")&IF(ABS(RIGHT(AM32,1)-RIGHT($H$5,1))=5,"年","") | AR32: =IF($AH32="","", IFERROR(IF(COUNTIF($F$6, MID("己庚辛壬癸甲乙丙丁戊", FIND(LEFT($AH32,1), "甲乙丙丁戊己庚辛壬癸"), 1))>0, CHOOSE(INT((FIND(LEFT($AH32,1), "甲己乙庚丙辛丁壬戊癸")+1)/2), "甲己干合", "乙庚干合", "丙辛干合", "丁壬干合", "戊癸干合"), ""), "")) | AS32: =IF($AH32="","", IFERROR(IF(COUNTIF($G$6, MID("己庚辛壬癸甲乙丙丁戊", FIND(LEFT($AH32,1), "甲乙丙丁戊己庚辛壬癸"), 1))>0, CHOOSE(INT((FIND(LEFT($AH32,1), "甲己乙庚丙辛丁壬戊癸")+1)/2), "甲己干合", "乙庚干合", "丙辛干合", "丁壬干合", "戊癸干合"), ""), "")) | AT32: =IF($AH32="","", IFERROR(IF(COUNTIF($H$6, MID("己庚辛壬癸甲乙丙丁戊", FIND(LEFT($AH32,1), "甲乙丙丁戊己庚辛壬癸"), 1))>0, CHOOSE(INT((FIND(LEFT($AH32,1), "甲己乙庚丙辛丁壬戊癸")+1)/2), "甲己干合", "乙庚干合", "丙辛干合", "丁壬干合", "戊癸干合"), ""), "")) | AU32: =INDEX('12運シート'!C:C, MATCH(1, INDEX(('12運シート'!A:A=TRIM($T$42)) * ('12運シート'!B:B=TRIM(RIGHT(AE32, 1))), 0), 0)) -> 達成 | AV32: =INDEX('12運シート'!$E:$E, MATCH(1, INDEX((TRIM('12運シート'!$A:$A)=TRIM($T$42)) * (TRIM('12運シート'!$B:$B)=TRIM(AE32)), 0), 0)) -> 韋駄天 | AW32: =VLOOKUP(AV32,$V$6:$W$18, 2, FALSE) -> 運気絶頂。これまでの努力が実を結び、最高のスポットライトを浴びる。 | AZ32: =RIGHT(BC32, 1) -> 寅 | BA32: =BA31+1 -> 46158 | BB32: =MOD(BA32 - DATE(2024, 1, 1), 60) + 1 -> 27 | BC32: =VLOOKUP(BB32,[1]大運!$B$31:$C$90,2,FALSE) -> 庚寅 | BD32: =VLOOKUP($F$5 & "+" & (MOD(BA32 - DATE(2024, 1, 1), 60) + 1), [1]大運!$H$45:$K$3644, 3, FALSE) -> 鳳閣星 | BE32: =VLOOKUP($F$5 & "+" & (MOD(BA32 - DATE(2024, 1, 1), 60) + 1), [1]大運!$H$45:$K$3644, 4, FALSE) -> 天貴星 | BF32: =VLOOKUP($F$5 & "+" & (MOD(BA32 - DATE(2024, 1, 1), 60) + 1), [1]大運!$H$45:$K$3644, 2, FALSE) -> － | BG32: =VLOOKUP($G$5 & "+" & (MOD(BA32 - DATE(2024, 1, 1), 60) + 1), [1]大運!$H$45:$K$3644, 2, FALSE) -> 天剋地冲 | BH32: =VLOOKUP($H$5 & "+" & (MOD(BA32 - DATE(2024, 1, 1), 60) + 1), [1]大運!$H$45:$K$3644, 2, FALSE) -> － | BI32: =IF($BC32="","", IFERROR(IF(COUNTIF($F$6, MID("己庚辛壬癸甲乙丙丁戊", FIND(LEFT($BC32,1), "甲乙丙丁戊己庚辛壬癸"), 1))>0, CHOOSE(INT((FIND(LEFT($BC32,1), "甲己乙庚丙辛丁壬戊癸")+1)/2), "甲己干合", "乙庚干合", "丙辛干合", "丁壬干合", "戊癸干合"), ""), "")) | BJ32: =IF($BC32="","", IFERROR(IF(COUNTIF($G$6, MID("己庚辛壬癸甲乙丙丁戊", FIND(LEFT($BC32,1), "甲乙丙丁戊己庚辛壬癸"), 1))>0, CHOOSE(INT((FIND(LEFT($BC32,1), "甲己乙庚丙辛丁壬戊癸")+1)/2), "甲己干合", "乙庚干合", "丙辛干合", "丁壬干合", "戊癸干合"), ""), "")) | BK32: =IF($BC32="","", IFERROR(IF(COUNTIF($H$6, MID("己庚辛壬癸甲乙丙丁戊", FIND(LEFT($BC32,1), "甲乙丙丁戊己庚辛壬癸"), 1))>0, CHOOSE(INT((FIND(LEFT($BC32,1), "甲己乙庚丙辛丁壬戊癸")+1)/2), "甲己干合", "乙庚干合", "丙辛干合", "丁壬干合", "戊癸干合"), ""), "")) | BL32: =INDEX('12運シート'!C:C, MATCH(1, INDEX(('12運シート'!A:A=TRIM($T$42)) * ('12運シート'!B:B=TRIM(RIGHT(AZ32, 1))), 0), 0)) -> 乱気 | BM32: =INDEX('12運シート'!$E:$E, MATCH(1, INDEX((TRIM('12運シート'!$A:$A)=TRIM($T$42)) * (TRIM('12運シート'!$B:$B)=TRIM(AZ32)), 0), 0)) -> 伏魔天 | BN32: =VLOOKUP(BM32,$V$6:$W$18, 2, FALSE) -> 強すぎる運気の反動で迷いや摩擦が生じる。理性と現状維持が必要な嵐。 | CF32: 22
H33: =H17 -> 1991 | I33: =H18 -> 2001 | J33: =H19 -> 2011 | K33: =H20 -> 2021 | L33: =H21 -> 2031 | M33: =H22 -> 2041 | N33: =H23 -> 2051 | O33: =H24 -> 2061 | P33: =H25 -> 2071 | V33: 金星人（－） | W33: 申酉－ | X33: 裏おうし座 | Y33: 常に新しい刺激を求めるアグレッシブな自由人としての顔を持ちながら、独自の視点を着実に形にしていく堅実さを併せ持つ、非常にバランスの取れた運命です。自由奔放に見えても、内面には絶対にブレない芯があり、自分が「これだ」と思った目標に対しては驚くべき持久力を発揮します。古い価値観に縛られることなく、自分自身の五感と直感を信じて人生を開拓していく開拓者と言えます。 | Z33: ひとつの仕事に縛られることなく、情報収集力を存分に活かして複数の仕事を同時進行させるようなパラレルワークの環境こそが天職です。型にハマった業務ではストレスを抱えますが、自身のペースで多様な案件を裁ける自由な環境を与えられれば、持ち前の堅実さで圧倒的な成果を上げます。独自のセンスが光るため、クリエイティブな分野とビジネスを見事に融合させる才能があります。 | AA33: ベタベタした束縛を極端に嫌い、お互いが自立した「友達感覚の楽しい交際」を好む傾向があります。趣味や美味しい食事を共有し、共に笑顔でいられる時間を大切にします。結婚後もパートナーとは対等な関係を望み、お互いのライフスタイルを尊重し合える風通しの良い家庭を築きます。重い感情の押し付け合いを避けるため、サバサバとした爽やかな愛情表現が特徴です。 | AB33: 五感に優れ、「本当に価値のあるもの」を見極める審美眼を持っているため、生涯を通じて安定した豊かな金運に恵まれます。美味しい食事や美しい芸術、居心地の良い空間作りなど、自分のライフスタイルを向上させる出費にはお金を惜しみません。それがさらなるモチベーションとなり、結果的に収入アップへと繋がります。着実な蓄財能力も併せ持っているため、財産形成も非常に上手です。 | AC33: アクティブに活動するエネルギーと、徹底してリラックスしたいという欲求が交互に訪れます。疲労を感じた時は、マッサージや温泉、美味しい食事など「五感を満たすケア」を取り入れることで、驚くほど速やかに体力が回復します。喉や首回り、胃腸などが弱りやすいため、暴飲暴食には注意し、日頃から良質な食材を使ったバランスの良い食事を心がけることが大切です。 | AE33: =RIGHT(AH33, 1) -> 寅 | AF33: =IF(OR($E$6=RIGHT(AM33,1),$E$7=RIGHT(AM33,1)),"殺",AG33-$I$3) -> 17 | AG33: =AG32+1 -> 1998 | AH33: =VLOOKUP(AM33,[1]大運!$B$31:$C$90,2,FALSE) -> 戊寅 | AI33: =VLOOKUP($F$5&"+"&AM33,[1]大運!$H$45:$K$3644,3,FALSE) -> 貫索星 | AK33: =VLOOKUP($F$5&"+"&AM33,[1]大運!$H$45:$K$3644,4,FALSE) -> 天貴星 | AM33: =IF(MOD((AG33-1900+37),60)=0,60,MOD((AG33-1900+37),60)) -> 15 | AN33: =VLOOKUP($F$5&"+"&AM33,[1]大運!$H$45:$K$3644,2,FALSE) -> － | AO33: =VLOOKUP($G$5&"+"&AM33,[1]大運!$H$45:$K$3644,2,FALSE) -> 対冲 | AP33: =VLOOKUP($H$5&"+"&AM33,[1]大運!$H$45:$K$3644,2,FALSE) -> － | AQ33: =IF(OR(RIGHT(AH33,1)=$E$6,RIGHT(AH33,1)=$E$7),"殺","")&IF(ABS(RIGHT(AM33,1)-RIGHT($F$5,1))=5,"日","")&IF(ABS(RIGHT(AM33,1)-RIGHT($G$5,1))=5,"月","")&IF(ABS(RIGHT(AM33,1)-RIGHT($H$5,1))=5,"年","") | AR33: =IF($AH33="","", IFERROR(IF(COUNTIF($F$6, MID("己庚辛壬癸甲乙丙丁戊", FIND(LEFT($AH33,1), "甲乙丙丁戊己庚辛壬癸"), 1))>0, CHOOSE(INT((FIND(LEFT($AH33,1), "甲己乙庚丙辛丁壬戊癸")+1)/2), "甲己干合", "乙庚干合", "丙辛干合", "丁壬干合", "戊癸干合"), ""), "")) | AS33: =IF($AH33="","", IFERROR(IF(COUNTIF($G$6, MID("己庚辛壬癸甲乙丙丁戊", FIND(LEFT($AH33,1), "甲乙丙丁戊己庚辛壬癸"), 1))>0, CHOOSE(INT((FIND(LEFT($AH33,1), "甲己乙庚丙辛丁壬戊癸")+1)/2), "甲己干合", "乙庚干合", "丙辛干合", "丁壬干合", "戊癸干合"), ""), "")) | AT33: =IF($AH33="","", IFERROR(IF(COUNTIF($H$6, MID("己庚辛壬癸甲乙丙丁戊", FIND(LEFT($AH33,1), "甲乙丙丁戊己庚辛壬癸"), 1))>0, CHOOSE(INT((FIND(LEFT($AH33,1), "甲己乙庚丙辛丁壬戊癸")+1)/2), "甲己干合", "乙庚干合", "丙辛干合", "丁壬干合", "戊癸干合"), ""), "")) | AU33: =INDEX('12運シート'!C:C, MATCH(1, INDEX(('12運シート'!A:A=TRIM($T$42)) * ('12運シート'!B:B=TRIM(RIGHT(AE33, 1))), 0), 0)) -> 乱気 | AV33: =INDEX('12運シート'!$E:$E, MATCH(1, INDEX((TRIM('12運シート'!$A:$A)=TRIM($T$42)) * (TRIM('12運シート'!$B:$B)=TRIM(AE33)), 0), 0)) -> 伏魔天 | AW33: =VLOOKUP(AV33,$V$6:$W$18, 2, FALSE) -> 強すぎる運気の反動で迷いや摩擦が生じる。理性と現状維持が必要な嵐。 | AZ33: =RIGHT(BC33, 1) -> 卯 | BA33: =BA32+1 -> 46159 | BB33: =MOD(BA33 - DATE(2024, 1, 1), 60) + 1 -> 28 | BC33: =VLOOKUP(BB33,[1]大運!$B$31:$C$90,2,FALSE) -> 辛卯 | BD33: =VLOOKUP($F$5 & "+" & (MOD(BA33 - DATE(2024, 1, 1), 60) + 1), [1]大運!$H$45:$K$3644, 3, FALSE) -> 調舒星 | BE33: =VLOOKUP($F$5 & "+" & (MOD(BA33 - DATE(2024, 1, 1), 60) + 1), [1]大運!$H$45:$K$3644, 4, FALSE) -> 天恍星 | BF33: =VLOOKUP($F$5 & "+" & (MOD(BA33 - DATE(2024, 1, 1), 60) + 1), [1]大運!$H$45:$K$3644, 2, FALSE) -> 刑 | BG33: =VLOOKUP($G$5 & "+" & (MOD(BA33 - DATE(2024, 1, 1), 60) + 1), [1]大運!$H$45:$K$3644, 2, FALSE) -> － | BH33: =VLOOKUP($H$5 & "+" & (MOD(BA33 - DATE(2024, 1, 1), 60) + 1), [1]大運!$H$45:$K$3644, 2, FALSE) -> 納音 | BI33: =IF($BC33="","", IFERROR(IF(COUNTIF($F$6, MID("己庚辛壬癸甲乙丙丁戊", FIND(LEFT($BC33,1), "甲乙丙丁戊己庚辛壬癸"), 1))>0, CHOOSE(INT((FIND(LEFT($BC33,1), "甲己乙庚丙辛丁壬戊癸")+1)/2), "甲己干合", "乙庚干合", "丙辛干合", "丁壬干合", "戊癸干合"), ""), "")) | BJ33: =IF($BC33="","", IFERROR(IF(COUNTIF($G$6, MID("己庚辛壬癸甲乙丙丁戊", FIND(LEFT($BC33,1), "甲乙丙丁戊己庚辛壬癸"), 1))>0, CHOOSE(INT((FIND(LEFT($BC33,1), "甲己乙庚丙辛丁壬戊癸")+1)/2), "甲己干合", "乙庚干合", "丙辛干合", "丁壬干合", "戊癸干合"), ""), "")) -> 丙辛干合 | BK33: =IF($BC33="","", IFERROR(IF(COUNTIF($H$6, MID("己庚辛壬癸甲乙丙丁戊", FIND(LEFT($BC33,1), "甲乙丙丁戊己庚辛壬癸"), 1))>0, CHOOSE(INT((FIND(LEFT($BC33,1), "甲己乙庚丙辛丁壬戊癸")+1)/2), "甲己干合", "乙庚干合", "丙辛干合", "丁壬干合", "戊癸干合"), ""), "")) | BL33: =INDEX('12運シート'!C:C, MATCH(1, INDEX(('12運シート'!A:A=TRIM($T$42)) * ('12運シート'!B:B=TRIM(RIGHT(AZ33, 1))), 0), 0)) -> 再会 | BM33: =INDEX('12運シート'!$E:$E, MATCH(1, INDEX((TRIM('12運シート'!$A:$A)=TRIM($T$42)) * (TRIM('12運シート'!$B:$B)=TRIM(AZ33)), 0), 0)) -> 有頂天 | BN33: =VLOOKUP(BM33,$V$6:$W$18, 2, FALSE) -> 第2の絶頂期。過去の縁が繋がり、周囲を巻き込み大きな成果を出す。 | CF33: 23
H34: =I17 -> 10 | I34: =I18 -> 20 | J34: =I19 -> 30 | K34: =I20 -> 40 | L34: =I21 -> 50 | M34: =I22 -> 60 | N34: =I23 -> 70 | O34: =I24 -> 80 | P34: =I25 -> 90 | V34: 火星人（＋） | W34: 午未＋ | X34: 裏しし座 | Y34: 燃えたぎる強烈な情熱と、芸術家のように繊細な感性が同居する、非常にドラマチックな運命の持ち主です。他人の評価よりも「自分が心から納得できるか」を人生の最優先事項とし、周囲の反対を押し切ってでも我が道を力強く切り開いていく圧倒的なカリスマ性を秘めています。その生き様は多くの人を惹きつけますが、内面のデリケートさゆえに孤独を感じることも少なくありません。 | Z34: 組織のルールに縛られることを嫌い、自らの采配で動けるフリーランスやクリエイターなど、己の美学を貫ける仕事が最適です。自分が情熱を注げるプロジェクトに出会った時の爆発力は凄まじく、誰も到達できないような高いクオリティの作品や成果を生み出します。妥協を許さないプロ意識が評価され、いつしか業界内でトップクラスの地位を確立することになるでしょう。 | AA34: 恋愛においては、映画のようなドラマチックな展開を好む情熱的なロマンチストです。一度火がつくと周りが見えなくなるほど情熱的に愛を貫き、相手に対してストレートな愛情表現を欠かしません。プライドが高いため、自分を特別扱いして心から称賛してくれるパートナーを求めます。結婚後も生活感を出さず、いつまでも華やかで恋人同士のようなロマンチックな関係を維持しようと努力します。 | AB34: 「自分の美学」や「見栄え」にこだわりがあるため、ファッションやステータスシンボルなど、華やかなものにお金を使う傾向があります。しかし、それが単なる浪費ではなく、自らのセルフプロデュース力やオーラを高めるための「必要経費」として機能し、結果的にさらに大きな仕事や富を引き寄せるという派手な金運を持っています。大胆な決断で大きな財を動かす才能があります。 | AC34: 情熱の赴くままに限界を超えて活動してしまうため、突然のガス欠（バーンアウト）に陥りやすい傾向があります。心臓や血流、背中などに負担がかかりやすいため、日頃から適度な運動で血行を促進することが重要です。また、繊細な内面がストレスを感じやすいため、誰にも邪魔されない空間で一人静かに好きなことに没頭し、心のエネルギーを満たす時間を意識的に作ってください。 | AE34: =RIGHT(AH34, 1) -> 卯 | AF34: =IF(OR($E$6=RIGHT(AM34,1),$E$7=RIGHT(AM34,1)),"殺",AG34-$I$3) -> 18 | AG34: =AG33+1 -> 1999 | AH34: =VLOOKUP(AM34,[1]大運!$B$31:$C$90,2,FALSE) -> 己卯 | AI34: =VLOOKUP($F$5&"+"&AM34,[1]大運!$H$45:$K$3644,3,FALSE) -> 石門星 | AK34: =VLOOKUP($F$5&"+"&AM34,[1]大運!$H$45:$K$3644,4,FALSE) -> 天恍星 | AM34: =IF(MOD((AG34-1900+37),60)=0,60,MOD((AG34-1900+37),60)) -> 16 | AQ34: =IF(OR(RIGHT(AH34,1)=$E$6,RIGHT(AH34,1)=$E$7),"殺","")&IF(ABS(RIGHT(AM34,1)-RIGHT($F$5,1))=5,"日","")&IF(ABS(RIGHT(AM34,1)-RIGHT($G$5,1))=5,"月","")&IF(ABS(RIGHT(AM34,1)-RIGHT($H$5,1))=5,"年","") | AR34: =IF($AH34="","", IFERROR(IF(COUNTIF($F$6, MID("己庚辛壬癸甲乙丙丁戊", FIND(LEFT($AH34,1), "甲乙丙丁戊己庚辛壬癸"), 1))>0, CHOOSE(INT((FIND(LEFT($AH34,1), "甲己乙庚丙辛丁壬戊癸")+1)/2), "甲己干合", "乙庚干合", "丙辛干合", "丁壬干合", "戊癸干合"), ""), "")) | AS34: =IF($AH34="","", IFERROR(IF(COUNTIF($G$6, MID("己庚辛壬癸甲乙丙丁戊", FIND(LEFT($AH34,1), "甲乙丙丁戊己庚辛壬癸"), 1))>0, CHOOSE(INT((FIND(LEFT($AH34,1), "甲己乙庚丙辛丁壬戊癸")+1)/2), "甲己干合", "乙庚干合", "丙辛干合", "丁壬干合", "戊癸干合"), ""), "")) | AT34: =IF($AH34="","", IFERROR(IF(COUNTIF($H$6, MID("己庚辛壬癸甲乙丙丁戊", FIND(LEFT($AH34,1), "甲乙丙丁戊己庚辛壬癸"), 1))>0, CHOOSE(INT((FIND(LEFT($AH34,1), "甲己乙庚丙辛丁壬戊癸")+1)/2), "甲己干合", "乙庚干合", "丙辛干合", "丁壬干合", "戊癸干合"), ""), "")) | AU34: =INDEX('12運シート'!C:C, MATCH(1, INDEX(('12運シート'!A:A=TRIM($T$42)) * ('12運シート'!B:B=TRIM(RIGHT(AE34, 1))), 0), 0)) -> 再会 | AV34: =INDEX('12運シート'!$E:$E, MATCH(1, INDEX((TRIM('12運シート'!$A:$A)=TRIM($T$42)) * (TRIM('12運シート'!$B:$B)=TRIM(AE34)), 0), 0)) -> 有頂天 | AW34: =VLOOKUP(AV34,$V$6:$W$18, 2, FALSE) -> 第2の絶頂期。過去の縁が繋がり、周囲を巻き込み大きな成果を出す。 | AZ34: =RIGHT(BC34, 1) -> 辰 | BA34: =BA33+1 -> 46160 | BB34: =MOD(BA34 - DATE(2024, 1, 1), 60) + 1 -> 29 | BC34: =VLOOKUP(BB34,[1]大運!$B$31:$C$90,2,FALSE) -> 壬辰 | BD34: =VLOOKUP($F$5 & "+" & (MOD(BA34 - DATE(2024, 1, 1), 60) + 1), [1]大運!$H$45:$K$3644, 3, FALSE) -> 禄存星 | BE34: =VLOOKUP($F$5 & "+" & (MOD(BA34 - DATE(2024, 1, 1), 60) + 1), [1]大運!$H$45:$K$3644, 4, FALSE) -> 天南星 | BF34: =VLOOKUP($F$5 & "+" & (MOD(BA34 - DATE(2024, 1, 1), 60) + 1), [1]大運!$H$45:$K$3644, 2, FALSE) -> 半会 | BG34: =VLOOKUP($G$5 & "+" & (MOD(BA34 - DATE(2024, 1, 1), 60) + 1), [1]大運!$H$45:$K$3644, 2, FALSE) -> 半会 | BH34: =VLOOKUP($H$5 & "+" & (MOD(BA34 - DATE(2024, 1, 1), 60) + 1), [1]大運!$H$45:$K$3644, 2, FALSE) -> 支合 | BI34: =IF($BC34="","", IFERROR(IF(COUNTIF($F$6, MID("己庚辛壬癸甲乙丙丁戊", FIND(LEFT($BC34,1), "甲乙丙丁戊己庚辛壬癸"), 1))>0, CHOOSE(INT((FIND(LEFT($BC34,1), "甲己乙庚丙辛丁壬戊癸")+1)/2), "甲己干合", "乙庚干合", "丙辛干合", "丁壬干合", "戊癸干合"), ""), "")) | BJ34: =IF($BC34="","", IFERROR(IF(COUNTIF($G$6, MID("己庚辛壬癸甲乙丙丁戊", FIND(LEFT($BC34,1), "甲乙丙丁戊己庚辛壬癸"), 1))>0, CHOOSE(INT((FIND(LEFT($BC34,1), "甲己乙庚丙辛丁壬戊癸")+1)/2), "甲己干合", "乙庚干合", "丙辛干合", "丁壬干合", "戊癸干合"), ""), "")) | BK34: =IF($BC34="","", IFERROR(IF(COUNTIF($H$6, MID("己庚辛壬癸甲乙丙丁戊", FIND(LEFT($BC34,1), "甲乙丙丁戊己庚辛壬癸"), 1))>0, CHOOSE(INT((FIND(LEFT($BC34,1), "甲己乙庚丙辛丁壬戊癸")+1)/2), "甲己干合", "乙庚干合", "丙辛干合", "丁壬干合", "戊癸干合"), ""), "")) | BL34: =INDEX('12運シート'!C:C, MATCH(1, INDEX(('12運シート'!A:A=TRIM($T$42)) * ('12運シート'!B:B=TRIM(RIGHT(AZ34, 1))), 0), 0)) -> 財成 | BM34: =INDEX('12運シート'!$E:$E, MATCH(1, INDEX((TRIM('12運シート'!$A:$A)=TRIM($T$42)) * (TRIM('12運シート'!$B:$B)=TRIM(AZ34)), 0), 0)) -> 満天 | BN34: =VLOOKUP(BM34,$V$6:$W$18, 2, FALSE) -> 収穫の喜び。物質や人脈などあらゆる財を蓄積し、強固な基盤を作る。 | CF34: 24
H35: =[1]大運!Q6 -> 幸山運 | I35: =[1]大運!Q7 -> 他山運 | J35: =[1]大運!Q8 -> 幸山運 | K35: =[1]大運!Q9 -> 幸山運 | L35: =[1]大運!Q10 -> 幸山運 | M35: =[1]大運!Q11 -> 幸山運 | N35: =[1]大運!Q12 -> 空転運 | O35: =[1]大運!Q13 -> 幸山運 | P35: =[1]大運!Q14 -> 幸山運 | V35: 火星人（－） | W35: 午未－ | X35: 裏かに座 | Y35: 他人に決して踏み込まれない絶対的な「聖域」を持つ、孤高の存在としての運気を背負っています。一見穏やかに見えても、内面には底知れぬ忍耐力と強烈な反骨精神を秘めており、どんな困難な状況に陥っても決して諦めない不屈の魂を持っています。警戒心が強いため人間関係の構築には時間をかけますが、一度心を開いた相手には絶対的な味方となる、非常に義理堅く情に深い性質です。 | Z35: 他人のペースに巻き込まれず、自分のペースで深く没頭できる専門分野や職人肌の仕事において、絶大な信頼と評価を得ます。表立ってリーダーシップを取るよりも、裏方や専門職として「この人にしかできない」と言われるような替えのきかないポジションを確立することが成功の鍵です。並外れた集中力と忍耐力で、誰も成し遂げられないような困難なミッションを見事にクリアしていきます。 | AA35: 警戒心が強いため、相手に心を開くまでに非常に長い時間を必要とします。しかし、一度相手を深く愛し信頼すると決めたら、見返りを求めない底知れぬ愛情と献身を注ぎ込みます。家族や恋人を「自分のテリトリー内の大切な存在」として徹底的に守り抜く強さを持っています。結婚後は非常に家庭的になり、強固な絆で結ばれた温かく安心できる家庭を何よりも大切に築き上げます。 | AB35: 貯蓄能力が非常に高く、お金に対しては保守的で堅実な価値観を持っています。無駄遣いや見栄のための出費を嫌い、将来の安心のためにコツコツと着実に財産を形成していくことができる手堅い金運です。ギャンブルや投資話には簡単には乗りませんが、家族のためや「いざという時の備え」に対する出費は惜しみません。晩年になるほど豊かさが増していく大器晩成型の財運です。 | AC35: 我慢強く忍耐力がある反面、ストレスや疲労を限界まで溜め込んでしまう傾向があるため注意が必要です。胃腸や消化器系が感情と直結しており、不安や怒りを感じると胃が痛くなるなどの症状が出やすい体質です。心を開ける少数の親しい友人と語り合ったり、家の中でリラックスできるお気に入りの空間を整えたりすることで、精神的なデトックスをこまめに行うことが健康長寿の秘訣です。 | AE35: =RIGHT(AH35, 1) -> 辰 | AF35: =IF(OR($E$6=RIGHT(AM35,1),$E$7=RIGHT(AM35,1)),"殺",AG35-$I$3) -> 19 | AG35: =AG34+1 -> 2000 | AH35: =VLOOKUP(AM35,[1]大運!$B$31:$C$90,2,FALSE) -> 庚辰 | AI35: =VLOOKUP($F$5&"+"&AM35,[1]大運!$H$45:$K$3644,3,FALSE) -> 鳳閣星 | AK35: =VLOOKUP($F$5&"+"&AM35,[1]大運!$H$45:$K$3644,4,FALSE) -> 天南星 | AM35: =IF(MOD((AG35-1900+37),60)=0,60,MOD((AG35-1900+37),60)) -> 17 | AN35: =VLOOKUP($F$5&"+"&AM35,[1]大運!$H$45:$K$3644,2,FALSE) -> 半会 | AO35: =VLOOKUP($G$5&"+"&AM35,[1]大運!$H$45:$K$3644,2,FALSE) -> 半会 | AP35: =VLOOKUP($H$5&"+"&AM35,[1]大運!$H$45:$K$3644,2,FALSE) -> 支合 | AQ35: =IF(OR(RIGHT(AH35,1)=$E$6,RIGHT(AH35,1)=$E$7),"殺","")&IF(ABS(RIGHT(AM35,1)-RIGHT($F$5,1))=5,"日","")&IF(ABS(RIGHT(AM35,1)-RIGHT($G$5,1))=5,"月","")&IF(ABS(RIGHT(AM35,1)-RIGHT($H$5,1))=5,"年","") | AR35: =IF($AH35="","", IFERROR(IF(COUNTIF($F$6, MID("己庚辛壬癸甲乙丙丁戊", FIND(LEFT($AH35,1), "甲乙丙丁戊己庚辛壬癸"), 1))>0, CHOOSE(INT((FIND(LEFT($AH35,1), "甲己乙庚丙辛丁壬戊癸")+1)/2), "甲己干合", "乙庚干合", "丙辛干合", "丁壬干合", "戊癸干合"), ""), "")) | AS35: =IF($AH35="","", IFERROR(IF(COUNTIF($G$6, MID("己庚辛壬癸甲乙丙丁戊", FIND(LEFT($AH35,1), "甲乙丙丁戊己庚辛壬癸"), 1))>0, CHOOSE(INT((FIND(LEFT($AH35,1), "甲己乙庚丙辛丁壬戊癸")+1)/2), "甲己干合", "乙庚干合", "丙辛干合", "丁壬干合", "戊癸干合"), ""), "")) | AT35: =IF($AH35="","", IFERROR(IF(COUNTIF($H$6, MID("己庚辛壬癸甲乙丙丁戊", FIND(LEFT($AH35,1), "甲乙丙丁戊己庚辛壬癸"), 1))>0, CHOOSE(INT((FIND(LEFT($AH35,1), "甲己乙庚丙辛丁壬戊癸")+1)/2), "甲己干合", "乙庚干合", "丙辛干合", "丁壬干合", "戊癸干合"), ""), "")) | AU35: =INDEX('12運シート'!C:C, MATCH(1, INDEX(('12運シート'!A:A=TRIM($T$42)) * ('12運シート'!B:B=TRIM(RIGHT(AE35, 1))), 0), 0)) -> 財成 | AV35: =INDEX('12運シート'!$E:$E, MATCH(1, INDEX((TRIM('12運シート'!$A:$A)=TRIM($T$42)) * (TRIM('12運シート'!$B:$B)=TRIM(AE35)), 0), 0)) -> 満天 | AW35: =VLOOKUP(AV35,$V$6:$W$18, 2, FALSE) -> 収穫の喜び。物質や人脈などあらゆる財を蓄積し、強固な基盤を作る。 | AZ35: =RIGHT(BC35, 1) -> 巳 | BA35: =BA34+1 -> 46161 | BB35: =MOD(BA35 - DATE(2024, 1, 1), 60) + 1 -> 30 | BC35: =VLOOKUP(BB35,[1]大運!$B$31:$C$90,2,FALSE) -> 癸巳 | BD35: =VLOOKUP($F$5 & "+" & (MOD(BA35 - DATE(2024, 1, 1), 60) + 1), [1]大運!$H$45:$K$3644, 3, FALSE) -> 司禄星 | BE35: =VLOOKUP($F$5 & "+" & (MOD(BA35 - DATE(2024, 1, 1), 60) + 1), [1]大運!$H$45:$K$3644, 4, FALSE) -> 天禄星 | BF35: =VLOOKUP($F$5 & "+" & (MOD(BA35 - DATE(2024, 1, 1), 60) + 1), [1]大運!$H$45:$K$3644, 2, FALSE) -> － | BG35: =VLOOKUP($G$5 & "+" & (MOD(BA35 - DATE(2024, 1, 1), 60) + 1), [1]大運!$H$45:$K$3644, 2, FALSE) -> 支合 | BH35: =VLOOKUP($H$5 & "+" & (MOD(BA35 - DATE(2024, 1, 1), 60) + 1), [1]大運!$H$45:$K$3644, 2, FALSE) -> 半会 | BI35: =IF($BC35="","", IFERROR(IF(COUNTIF($F$6, MID("己庚辛壬癸甲乙丙丁戊", FIND(LEFT($BC35,1), "甲乙丙丁戊己庚辛壬癸"), 1))>0, CHOOSE(INT((FIND(LEFT($BC35,1), "甲己乙庚丙辛丁壬戊癸")+1)/2), "甲己干合", "乙庚干合", "丙辛干合", "丁壬干合", "戊癸干合"), ""), "")) -> 戊癸干合 | BJ35: =IF($BC35="","", IFERROR(IF(COUNTIF($G$6, MID("己庚辛壬癸甲乙丙丁戊", FIND(LEFT($BC35,1), "甲乙丙丁戊己庚辛壬癸"), 1))>0, CHOOSE(INT((FIND(LEFT($BC35,1), "甲己乙庚丙辛丁壬戊癸")+1)/2), "甲己干合", "乙庚干合", "丙辛干合", "丁壬干合", "戊癸干合"), ""), "")) | BK35: =IF($BC35="","", IFERROR(IF(COUNTIF($H$6, MID("己庚辛壬癸甲乙丙丁戊", FIND(LEFT($BC35,1), "甲乙丙丁戊己庚辛壬癸"), 1))>0, CHOOSE(INT((FIND(LEFT($BC35,1), "甲己乙庚丙辛丁壬戊癸")+1)/2), "甲己干合", "乙庚干合", "丙辛干合", "丁壬干合", "戊癸干合"), ""), "")) | BL35: =INDEX('12運シート'!C:C, MATCH(1, INDEX(('12運シート'!A:A=TRIM($T$42)) * ('12運シート'!B:B=TRIM(RIGHT(AZ35, 1))), 0), 0)) -> 充実 | BM35: =INDEX('12運シート'!$E:$E, MATCH(1, INDEX((TRIM('12運シート'!$A:$A)=TRIM($T$42)) * (TRIM('12運シート'!$B:$B)=TRIM(AZ35)), 0), 0)) -> 静天 | BN35: =VLOOKUP(BM35,$V$6:$W$18, 2, FALSE) -> 成果が出揃う。精神的な安定と充実の中で平和に人生を俯瞰する時期。 | CF35: 25
T36: 戌亥 | U36: 土星人 | V36: 天王星人（＋） | W36: 辰巳＋ | X36: 裏てんびん座 | Y36: 独自の優れた論理的思考と、人情味あふれる温かなリーダーシップを併せ持つ、非常にスケールの大きな運命の持ち主です。多様な価値観を受け入れる広い視野を持ち、周囲の人々を巧みに巻き込みながら、一人では到達できないような大きな目標を次々と達成していきます。平和主義でありながらも、理想の実現のためには毅然とした態度で物事を推し進める、頼りになるカリスマ性を発揮します。 | Z36: 人を動かす卓越した手腕を持っているため、プロデュース業やマネジメント業、ディレクターなどのポジションで圧倒的な才能を発揮します。それぞれのメンバーの適性を見抜き、適材適所に配置して最高のチームを作り上げる天才です。論理的な戦略と、相手の感情に寄り添う人情味のバランスが絶妙なため、上司からも部下からも熱烈な支持を受け、組織のトップへと上り詰める暗示があります。 | AA36: 争いごとを極端に嫌い、常に平和で穏やかな関係を好みます。相手の気持ちを察する気配りに長け、洗練された会話術とスマートな振る舞いができるため、異性からは非常にモテる運命にあります。恋愛経験は豊富になりがちですが、結婚後は持ち前のバランス感覚を発揮し、喧嘩の少ない落ち着いた温かい家庭を築きます。パートナーを陰ながらプロデュースし、成功へと導く力も持っています。 | AB36: 人脈がそのまま金脈へと繋がる強力な引き寄せの金運を持っています。周囲の人々との調和を大切にし、他者に利益をもたらすことで、巡り巡って自分自身に大きな富が還元されるというサイクルを生まれ持っています。交際費への投資は惜しむべきではありません。公平な視点を持っているため、ビジネスパートナーとの共同事業や投資などでも、双方が納得する形で大きな利益を生み出します。 | AC36: 人当たりが良く常に他者に気を配っているため、対人関係の疲労が蓄積しやすい傾向があります。腰や腎臓などにストレスのサインが出やすいため、定期的な休息が必要です。美しいものや芸術に触れることで精神的なバランスを取り戻すことができるため、休日は美術館巡りやクラシック音楽の鑑賞、または洗練された空間での優雅なティータイムなどで、心のチューニングを行うと良いでしょう。 | AE36: =RIGHT(AH36, 1) -> 巳 | AF36: =IF(OR($E$6=RIGHT(AM36,1),$E$7=RIGHT(AM36,1)),"殺",AG36-$I$3) -> 20 | AG36: =AG35+1 -> 2001 | AH36: =VLOOKUP(AM36,[1]大運!$B$31:$C$90,2,FALSE) -> 辛巳 | AI36: =VLOOKUP($F$5&"+"&AM36,[1]大運!$H$45:$K$3644,3,FALSE) -> 調舒星 | AK36: =VLOOKUP($F$5&"+"&AM36,[1]大運!$H$45:$K$3644,4,FALSE) -> 天禄星 | AM36: =IF(MOD((AG36-1900+37),60)=0,60,MOD((AG36-1900+37),60)) -> 18 | AN36: =VLOOKUP($F$5&"+"&AM36,[1]大運!$H$45:$K$3644,2,FALSE) -> － | AO36: =VLOOKUP($G$5&"+"&AM36,[1]大運!$H$45:$K$3644,2,FALSE) -> 支合 | AP36: =VLOOKUP($H$5&"+"&AM36,[1]大運!$H$45:$K$3644,2,FALSE) -> 大半会 | AQ36: =IF(OR(RIGHT(AH36,1)=$E$6,RIGHT(AH36,1)=$E$7),"殺","")&IF(ABS(RIGHT(AM36,1)-RIGHT($F$5,1))=5,"日","")&IF(ABS(RIGHT(AM36,1)-RIGHT($G$5,1))=5,"月","")&IF(ABS(RIGHT(AM36,1)-RIGHT($H$5,1))=5,"年","") -> 月 | AR36: =IF($AH36="","", IFERROR(IF(COUNTIF($F$6, MID("己庚辛壬癸甲乙丙丁戊", FIND(LEFT($AH36,1), "甲乙丙丁戊己庚辛壬癸"), 1))>0, CHOOSE(INT((FIND(LEFT($AH36,1), "甲己乙庚丙辛丁壬戊癸")+1)/2), "甲己干合", "乙庚干合", "丙辛干合", "丁壬干合", "戊癸干合"), ""), "")) | AS36: =IF($AH36="","", IFERROR(IF(COUNTIF($G$6, MID("己庚辛壬癸甲乙丙丁戊", FIND(LEFT($AH36,1), "甲乙丙丁戊己庚辛壬癸"), 1))>0, CHOOSE(INT((FIND(LEFT($AH36,1), "甲己乙庚丙辛丁壬戊癸")+1)/2), "甲己干合", "乙庚干合", "丙辛干合", "丁壬干合", "戊癸干合"), ""), "")) -> 丙辛干合 | AT36: =IF($AH36="","", IFERROR(IF(COUNTIF($H$6, MID("己庚辛壬癸甲乙丙丁戊", FIND(LEFT($AH36,1), "甲乙丙丁戊己庚辛壬癸"), 1))>0, CHOOSE(INT((FIND(LEFT($AH36,1), "甲己乙庚丙辛丁壬戊癸")+1)/2), "甲己干合", "乙庚干合", "丙辛干合", "丁壬干合", "戊癸干合"), ""), "")) | AU36: =INDEX('12運シート'!C:C, MATCH(1, INDEX(('12運シート'!A:A=TRIM($T$42)) * ('12運シート'!B:B=TRIM(RIGHT(AE36, 1))), 0), 0)) -> 充実 | AV36: =INDEX('12運シート'!$E:$E, MATCH(1, INDEX((TRIM('12運シート'!$A:$A)=TRIM($T$42)) * (TRIM('12運シート'!$B:$B)=TRIM(AE36)), 0), 0)) -> 静天 | AW36: =VLOOKUP(AV36,$V$6:$W$18, 2, FALSE) -> 成果が出揃う。精神的な安定と充実の中で平和に人生を俯瞰する時期。 | AZ36: =RIGHT(BC36, 1) -> 午 | BA36: =BA35+1 -> 46162 | BB36: =MOD(BA36 - DATE(2024, 1, 1), 60) + 1 -> 31 | BC36: =VLOOKUP(BB36,[1]大運!$B$31:$C$90,2,FALSE) -> 甲午 | BD36: =VLOOKUP($F$5 & "+" & (MOD(BA36 - DATE(2024, 1, 1), 60) + 1), [1]大運!$H$45:$K$3644, 3, FALSE) -> 車騎星 | BE36: =VLOOKUP($F$5 & "+" & (MOD(BA36 - DATE(2024, 1, 1), 60) + 1), [1]大運!$H$45:$K$3644, 4, FALSE) -> 天将星 | BF36: =VLOOKUP($F$5 & "+" & (MOD(BA36 - DATE(2024, 1, 1), 60) + 1), [1]大運!$H$45:$K$3644, 2, FALSE) -> 天剋地冲 | BG36: =VLOOKUP($G$5 & "+" & (MOD(BA36 - DATE(2024, 1, 1), 60) + 1), [1]大運!$H$45:$K$3644, 2, FALSE) -> － | BH36: =VLOOKUP($H$5 & "+" & (MOD(BA36 - DATE(2024, 1, 1), 60) + 1), [1]大運!$H$45:$K$3644, 2, FALSE) -> － | BI36: =IF($BC36="","", IFERROR(IF(COUNTIF($F$6, MID("己庚辛壬癸甲乙丙丁戊", FIND(LEFT($BC36,1), "甲乙丙丁戊己庚辛壬癸"), 1))>0, CHOOSE(INT((FIND(LEFT($BC36,1), "甲己乙庚丙辛丁壬戊癸")+1)/2), "甲己干合", "乙庚干合", "丙辛干合", "丁壬干合", "戊癸干合"), ""), "")) | BJ36: =IF($BC36="","", IFERROR(IF(COUNTIF($G$6, MID("己庚辛壬癸甲乙丙丁戊", FIND(LEFT($BC36,1), "甲乙丙丁戊己庚辛壬癸"), 1))>0, CHOOSE(INT((FIND(LEFT($BC36,1), "甲己乙庚丙辛丁壬戊癸")+1)/2), "甲己干合", "乙庚干合", "丙辛干合", "丁壬干合", "戊癸干合"), ""), "")) | BK36: =IF($BC36="","", IFERROR(IF(COUNTIF($H$6, MID("己庚辛壬癸甲乙丙丁戊", FIND(LEFT($BC36,1), "甲乙丙丁戊己庚辛壬癸"), 1))>0, CHOOSE(INT((FIND(LEFT($BC36,1), "甲己乙庚丙辛丁壬戊癸")+1)/2), "甲己干合", "乙庚干合", "丙辛干合", "丁壬干合", "戊癸干合"), ""), "")) | BL36: =INDEX('12運シート'!C:C, MATCH(1, INDEX(('12運シート'!A:A=TRIM($T$42)) * ('12運シート'!B:B=TRIM(RIGHT(AZ36, 1))), 0), 0)) -> 陰影 | BM36: =INDEX('12運シート'!$E:$E, MATCH(1, INDEX((TRIM('12運シート'!$A:$A)=TRIM($T$42)) * (TRIM('12運シート'!$B:$B)=TRIM(AZ36)), 0), 0)) -> 暗天 | BN36: =VLOOKUP(BM36,$V$6:$W$18, 2, FALSE) -> 運気下降（運の冬入り）。孤独を感じやすいが水面下の自己鍛錬が必要。 | CF36: 26
F37: =VLOOKUP(M143&N143,J143:K167,2,FALSE) -> 月支が身弱の場合・・これは「混迷の中で救われる」という意味を持ちます。なかなかまとまりのある形を作りにくいパターンです。職業変化や生活環境の変化が起こりやすく、混迷している感じになります。ただ、人に好かれやすい性質を持つようになり、窮地においても助けられることが多くなります。追い込まれたら、だれでもいいから人にすがれば、周りが助けてくれます。 月支が身強の場合・・運勢の波も人間性も大きくなります。人生のスケールが大きくなって、プラス面もマイナス面も大きいという、激しいものになります。「天国か地獄か」というパターンです。最上を極めたかと思えば、最下へと急降下することもあれば、地獄から天国へと舞い上がることもあります。 | T37: 申酉 | U37: 金星人 | V37: 天王星人（－） | W37: 辰巳－ | X37: 裏おとめ座 | Y37: 常識や既存のルールに一切囚われない、非常に柔軟で博愛主義的な魂を持っています。水のようにどんな環境や状況にも見事に適応し、困っている人や弱者に寄り添うことを心から喜びとする、深い慈愛の精神に満ちた人生を送ります。損得勘定抜きで他者に尽くすその姿勢は、巡り巡ってあなた自身を強固に守る見えないバリアとなり、多くの人から愛され、助けられる温かい運命を引き寄せます。 | Z37: 表舞台で目立つよりも、医療や福祉、教育、人事など、人を直接サポートし、チーム全体を円滑に回す調整役・裏方としてのポジションが天職です。相手が何を求めているかを瞬時に察知し、先回りして行動する能力は天才的です。あなたが職場にいるだけで雰囲気が和らぎ、トラブルが激減するため、組織にとって決して手放せない「扇の要」のような重要人物として重宝されることになります。 | AA37: 相手の喜ぶ顔を見ること、相手に尽くすことに至上の喜びを感じる、究極の奉仕型恋愛を好みます。パートナーの欠点すらも受け入れて包み込むほどの深い愛情を持っていますが、尽くしすぎて自分が疲弊してしまったり、依存心の強い相手を引き寄せてしまうことには注意が必要です。あなたの献身的な愛に心から感謝し、対等に思いやりのキャッチボールができる相手を選ぶことで、最高の幸せを掴めます。 | AB37: 他人のためにお金を使うことを惜しまないため、手元にお金が残りにくい傾向があります。しかし、あなたのその無私の精神に感動した人々から、思いがけない援助や引き立てを受け、結果的にお金に困ることはないという特殊で恵まれた金運を持っています。福祉やボランティア、後進の育成など、社会の役に立つことへお金を循環させることで、さらに大きくて清らかな財運の波を引き寄せることができます。 | AC37: 他人の悩みや痛みを自分のことのように受け取ってしまう共感能力の高さゆえに、精神的な疲労やネガティブなエネルギーをもらいやすい体質です。腸内環境や神経系にストレスが出やすいため、日々の食事を整えることが基本となります。定期的に自然の豊かな場所へ出かけたり、海や山で深呼吸をして、他者の感情と自分の感情の境界線をリセットする「浄化」の習慣を持つことが健康維持の要です。 | AE37: =RIGHT(AH37, 1) -> 午 | AF37: =IF(OR($E$6=RIGHT(AM37,1),$E$7=RIGHT(AM37,1)),"殺",AG37-$I$3) -> 21 | AG37: =AG36+1 -> 2002 | AH37: =VLOOKUP(AM37,[1]大運!$B$31:$C$90,2,FALSE) -> 壬午 | AI37: =VLOOKUP($F$5&"+"&AM37,[1]大運!$H$45:$K$3644,3,FALSE) -> 禄存星 | AK37: =VLOOKUP($F$5&"+"&AM37,[1]大運!$H$45:$K$3644,4,FALSE) -> 天将星 | AM37: =IF(MOD((AG37-1900+37),60)=0,60,MOD((AG37-1900+37),60)) -> 19 | AN37: =VLOOKUP($F$5&"+"&AM37,[1]大運!$H$45:$K$3644,2,FALSE) -> 天剋地冲 | AO37: =VLOOKUP($G$5&"+"&AM37,[1]大運!$H$45:$K$3644,2,FALSE) -> － | AP37: =VLOOKUP($H$5&"+"&AM37,[1]大運!$H$45:$K$3644,2,FALSE) -> － | AQ37: =IF(OR(RIGHT(AH37,1)=$E$6,RIGHT(AH37,1)=$E$7),"殺","")&IF(ABS(RIGHT(AM37,1)-RIGHT($F$5,1))=5,"日","")&IF(ABS(RIGHT(AM37,1)-RIGHT($G$5,1))=5,"月","")&IF(ABS(RIGHT(AM37,1)-RIGHT($H$5,1))=5,"年","") -> 殺 | AR37: =IF($AH37="","", IFERROR(IF(COUNTIF($F$6, MID("己庚辛壬癸甲乙丙丁戊", FIND(LEFT($AH37,1), "甲乙丙丁戊己庚辛壬癸"), 1))>0, CHOOSE(INT((FIND(LEFT($AH37,1), "甲己乙庚丙辛丁壬戊癸")+1)/2), "甲己干合", "乙庚干合", "丙辛干合", "丁壬干合", "戊癸干合"), ""), "")) | AS37: =IF($AH37="","", IFERROR(IF(COUNTIF($G$6, MID("己庚辛壬癸甲乙丙丁戊", FIND(LEFT($AH37,1), "甲乙丙丁戊己庚辛壬癸"), 1))>0, CHOOSE(INT((FIND(LEFT($AH37,1), "甲己乙庚丙辛丁壬戊癸")+1)/2), "甲己干合", "乙庚干合", "丙辛干合", "丁壬干合", "戊癸干合"), ""), "")) | AT37: =IF($AH37="","", IFERROR(IF(COUNTIF($H$6, MID("己庚辛壬癸甲乙丙丁戊", FIND(LEFT($AH37,1), "甲乙丙丁戊己庚辛壬癸"), 1))>0, CHOOSE(INT((FIND(LEFT($AH37,1), "甲己乙庚丙辛丁壬戊癸")+1)/2), "甲己干合", "乙庚干合", "丙辛干合", "丁壬干合", "戊癸干合"), ""), "")) | AU37: =INDEX('12運シート'!C:C, MATCH(1, INDEX(('12運シート'!A:A=TRIM($T$42)) * ('12運シート'!B:B=TRIM(RIGHT(AE37, 1))), 0), 0)) -> 陰影 | AV37: =INDEX('12運シート'!$E:$E, MATCH(1, INDEX((TRIM('12運シート'!$A:$A)=TRIM($T$42)) * (TRIM('12運シート'!$B:$B)=TRIM(AE37)), 0), 0)) -> 暗天 | AW37: =VLOOKUP(AV37,$V$6:$W$18, 2, FALSE) -> 運気下降（運の冬入り）。孤独を感じやすいが水面下の自己鍛錬が必要。 | AZ37: =RIGHT(BC37, 1) -> 未 | BA37: =BA36+1 -> 46163 | BB37: =MOD(BA37 - DATE(2024, 1, 1), 60) + 1 -> 32 | BC37: =VLOOKUP(BB37,[1]大運!$B$31:$C$90,2,FALSE) -> 乙未 | BD37: =VLOOKUP($F$5 & "+" & (MOD(BA37 - DATE(2024, 1, 1), 60) + 1), [1]大運!$H$45:$K$3644, 3, FALSE) -> 牽牛星 | BE37: =VLOOKUP($F$5 & "+" & (MOD(BA37 - DATE(2024, 1, 1), 60) + 1), [1]大運!$H$45:$K$3644, 4, FALSE) -> 天堂星 | BF37: =VLOOKUP($F$5 & "+" & (MOD(BA37 - DATE(2024, 1, 1), 60) + 1), [1]大運!$H$45:$K$3644, 2, FALSE) -> 害 | BG37: =VLOOKUP($G$5 & "+" & (MOD(BA37 - DATE(2024, 1, 1), 60) + 1), [1]大運!$H$45:$K$3644, 2, FALSE) -> － | BH37: =VLOOKUP($H$5 & "+" & (MOD(BA37 - DATE(2024, 1, 1), 60) + 1), [1]大運!$H$45:$K$3644, 2, FALSE) -> － | BI37: =IF($BC37="","", IFERROR(IF(COUNTIF($F$6, MID("己庚辛壬癸甲乙丙丁戊", FIND(LEFT($BC37,1), "甲乙丙丁戊己庚辛壬癸"), 1))>0, CHOOSE(INT((FIND(LEFT($BC37,1), "甲己乙庚丙辛丁壬戊癸")+1)/2), "甲己干合", "乙庚干合", "丙辛干合", "丁壬干合", "戊癸干合"), ""), "")) | BJ37: =IF($BC37="","", IFERROR(IF(COUNTIF($G$6, MID("己庚辛壬癸甲乙丙丁戊", FIND(LEFT($BC37,1), "甲乙丙丁戊己庚辛壬癸"), 1))>0, CHOOSE(INT((FIND(LEFT($BC37,1), "甲己乙庚丙辛丁壬戊癸")+1)/2), "甲己干合", "乙庚干合", "丙辛干合", "丁壬干合", "戊癸干合"), ""), "")) | BK37: =IF($BC37="","", IFERROR(IF(COUNTIF($H$6, MID("己庚辛壬癸甲乙丙丁戊", FIND(LEFT($BC37,1), "甲乙丙丁戊己庚辛壬癸"), 1))>0, CHOOSE(INT((FIND(LEFT($BC37,1), "甲己乙庚丙辛丁壬戊癸")+1)/2), "甲己干合", "乙庚干合", "丙辛干合", "丁壬干合", "戊癸干合"), ""), "")) | BL37: =INDEX('12運シート'!C:C, MATCH(1, INDEX(('12運シート'!A:A=TRIM($T$42)) * ('12運シート'!B:B=TRIM(RIGHT(AZ37, 1))), 0), 0)) -> 停止 | BM37: =INDEX('12運シート'!$E:$E, MATCH(1, INDEX((TRIM('12運シート'!$A:$A)=TRIM($T$42)) * (TRIM('12運シート'!$B:$B)=TRIM(AZ37)), 0), 0)) -> 大曇天 | BN37: =VLOOKUP(BM37,$V$6:$W$18, 2, FALSE) -> 運命の停止（運の真冬時期）。古い価値観を手放す究極の浄化期間。 | CF37: 27
T38: 午未 | U38: 火星人 | V38: 木星人（＋） | W38: 寅卯＋ | X38: 裏いて座 | Y38: 伝統や歴史、先人たちの知恵を深く重んじる、非常に真面目で学習意欲旺盛な優等生としての魂を持っています。高い論理的思考力と、どんな状況でも冷静に分析して最適解を導き出す優れた適応力を武器に、人生の壁を着実に乗り越えていきます。軽はずみな行動は取らず、常に長期的な視点で物事を捉えるため、年齢を重ねるごとに知識と経験が重厚なオーラとなり、大器晩成型の成功を収めます。 | Z38: 高い知性と探求心を活かせる、研究職、教育分野、データ分析、企業の戦略立案などのポジションで才能が最高に輝きます。物事の本質を深く掘り下げ、体系化して人に教えることが非常に得意です。コンプライアンスやルールを厳守し、正確でミスのない完璧な仕事ぶりは上司からの信頼も厚く、最終的には組織の中枢を担う知恵袋や顧問のような立場へと昇り詰める暗示があります。 | AA38: 感情の赴くままの情熱的な恋愛よりも、お互いの知識や世界観を深く共有し合える、尊敬を伴う知的な恋愛関係を強く望みます。議論を交わしたり、一緒に勉強や読書を楽しんだりできる、精神的なレベルの高いパートナーとのご縁に恵まれます。結婚に対しても非常に慎重で責任感が強いため、一度結んだ絆は決して裏切ることなく、安定的で倫理観の高い、模範的な家庭を築き上げます。 | AB38: 一攫千金を狙うようなハイリスクな行動は取らず、緻密な計画に基づいた非常に手堅く安定した金運の持ち主です。若い頃からコツコツと貯蓄や堅実な投資（インデックス投資や不動産など）を行い、老後には磐石の財産を築き上げているタイプです。また、知識や資格取得への自己投資は最強のリターンを生むため、学ぶことに対してはお金を出し惜しみしないことが、さらなる富の拡大に繋がります。 | AC38: 真面目で責任感が強すぎるあまり、無意識のうちにストレスを溜め込み、肩こりや頭痛、肝臓などの不調を引き起こしやすい傾向があります。「〜しなければならない」という思考の枠をたまには外し、意図的に「何もしないだらけの時間」を作ることが究極の健康法です。読書などで脳を使いすぎた後は、軽いジョギングやストレッチで身体を動かし、頭に上った血を全身に巡らせることを意識してください。 | AE38: =RIGHT(AH38, 1) -> 未 | AF38: =IF(OR($E$6=RIGHT(AM38,1),$E$7=RIGHT(AM38,1)),"殺",AG38-$I$3) -> 22 | AG38: =AG37+1 -> 2003 | AH38: =VLOOKUP(AM38,[1]大運!$B$31:$C$90,2,FALSE) -> 癸未 | AI38: =VLOOKUP($F$5&"+"&AM38,[1]大運!$H$45:$K$3644,3,FALSE) -> 司禄星 | AK38: =VLOOKUP($F$5&"+"&AM38,[1]大運!$H$45:$K$3644,4,FALSE) -> 天堂星 | AM38: =IF(MOD((AG38-1900+37),60)=0,60,MOD((AG38-1900+37),60)) -> 20 | AQ38: =IF(OR(RIGHT(AH38,1)=$E$6,RIGHT(AH38,1)=$E$7),"殺","")&IF(ABS(RIGHT(AM38,1)-RIGHT($F$5,1))=5,"日","")&IF(ABS(RIGHT(AM38,1)-RIGHT($G$5,1))=5,"月","")&IF(ABS(RIGHT(AM38,1)-RIGHT($H$5,1))=5,"年","") -> 殺日 | AR38: =IF($AH38="","", IFERROR(IF(COUNTIF($F$6, MID("己庚辛壬癸甲乙丙丁戊", FIND(LEFT($AH38,1), "甲乙丙丁戊己庚辛壬癸"), 1))>0, CHOOSE(INT((FIND(LEFT($AH38,1), "甲己乙庚丙辛丁壬戊癸")+1)/2), "甲己干合", "乙庚干合", "丙辛干合", "丁壬干合", "戊癸干合"), ""), "")) -> 戊癸干合 | AS38: =IF($AH38="","", IFERROR(IF(COUNTIF($G$6, MID("己庚辛壬癸甲乙丙丁戊", FIND(LEFT($AH38,1), "甲乙丙丁戊己庚辛壬癸"), 1))>0, CHOOSE(INT((FIND(LEFT($AH38,1), "甲己乙庚丙辛丁壬戊癸")+1)/2), "甲己干合", "乙庚干合", "丙辛干合", "丁壬干合", "戊癸干合"), ""), "")) | AT38: =IF($AH38="","", IFERROR(IF(COUNTIF($H$6, MID("己庚辛壬癸甲乙丙丁戊", FIND(LEFT($AH38,1), "甲乙丙丁戊己庚辛壬癸"), 1))>0, CHOOSE(INT((FIND(LEFT($AH38,1), "甲己乙庚丙辛丁壬戊癸")+1)/2), "甲己干合", "乙庚干合", "丙辛干合", "丁壬干合", "戊癸干合"), ""), "")) | AU38: =INDEX('12運シート'!C:C, MATCH(1, INDEX(('12運シート'!A:A=TRIM($T$42)) * ('12運シート'!B:B=TRIM(RIGHT(AE38, 1))), 0), 0)) -> 停止 | AV38: =INDEX('12運シート'!$E:$E, MATCH(1, INDEX((TRIM('12運シート'!$A:$A)=TRIM($T$42)) * (TRIM('12運シート'!$B:$B)=TRIM(AE38)), 0), 0)) -> 大曇天 | AW38: =VLOOKUP(AV38,$V$6:$W$18, 2, FALSE) -> 運命の停止（運の真冬時期）。古い価値観を手放す究極の浄化期間。 | AZ38: =RIGHT(BC38, 1) -> 申 | BA38: =BA37+1 -> 46164 | BB38: =MOD(BA38 - DATE(2024, 1, 1), 60) + 1 -> 33 | BC38: =VLOOKUP(BB38,[1]大運!$B$31:$C$90,2,FALSE) -> 丙申 | BD38: =VLOOKUP($F$5 & "+" & (MOD(BA38 - DATE(2024, 1, 1), 60) + 1), [1]大運!$H$45:$K$3644, 3, FALSE) -> 龍高星 | BE38: =VLOOKUP($F$5 & "+" & (MOD(BA38 - DATE(2024, 1, 1), 60) + 1), [1]大運!$H$45:$K$3644, 4, FALSE) -> 天胡星 | BF38: =VLOOKUP($F$5 & "+" & (MOD(BA38 - DATE(2024, 1, 1), 60) + 1), [1]大運!$H$45:$K$3644, 2, FALSE) -> 半会 | BG38: =VLOOKUP($G$5 & "+" & (MOD(BA38 - DATE(2024, 1, 1), 60) + 1), [1]大運!$H$45:$K$3644, 2, FALSE) -> 律音 | BH38: =VLOOKUP($H$5 & "+" & (MOD(BA38 - DATE(2024, 1, 1), 60) + 1), [1]大運!$H$45:$K$3644, 2, FALSE) -> 準方位 | BI38: =IF($BC38="","", IFERROR(IF(COUNTIF($F$6, MID("己庚辛壬癸甲乙丙丁戊", FIND(LEFT($BC38,1), "甲乙丙丁戊己庚辛壬癸"), 1))>0, CHOOSE(INT((FIND(LEFT($BC38,1), "甲己乙庚丙辛丁壬戊癸")+1)/2), "甲己干合", "乙庚干合", "丙辛干合", "丁壬干合", "戊癸干合"), ""), "")) | BJ38: =IF($BC38="","", IFERROR(IF(COUNTIF($G$6, MID("己庚辛壬癸甲乙丙丁戊", FIND(LEFT($BC38,1), "甲乙丙丁戊己庚辛壬癸"), 1))>0, CHOOSE(INT((FIND(LEFT($BC38,1), "甲己乙庚丙辛丁壬戊癸")+1)/2), "甲己干合", "乙庚干合", "丙辛干合", "丁壬干合", "戊癸干合"), ""), "")) | BK38: =IF($BC38="","", IFERROR(IF(COUNTIF($H$6, MID("己庚辛壬癸甲乙丙丁戊", FIND(LEFT($BC38,1), "甲乙丙丁戊己庚辛壬癸"), 1))>0, CHOOSE(INT((FIND(LEFT($BC38,1), "甲己乙庚丙辛丁壬戊癸")+1)/2), "甲己干合", "乙庚干合", "丙辛干合", "丁壬干合", "戊癸干合"), ""), "")) -> 丙辛干合 | BL38: =INDEX('12運シート'!C:C, MATCH(1, INDEX(('12運シート'!A:A=TRIM($T$42)) * ('12運シート'!B:B=TRIM(RIGHT(AZ38, 1))), 0), 0)) -> 減退 | BM38: =INDEX('12運シート'!$E:$E, MATCH(1, INDEX((TRIM('12運シート'!$A:$A)=TRIM($T$42)) * (TRIM('12運シート'!$B:$B)=TRIM(AZ38)), 0), 0)) -> 雨天 | BN38: =VLOOKUP(BM38,$V$6:$W$18, 2, FALSE) -> カルマの精算。過去の執着をすべて洗い流し、次の春への準備を整える。 | CF38: 28
T39: 辰巳 | U39: 天王星人 | V39: 木星人（－） | W39: 寅卯－ | X39: 裏さそり座 | Y39: その場の空気を敏感に読み取り、周囲の環境や状況に合わせて自らをカメレオンのように変化させる、驚異的な模倣能力と適応力を持った運命です。決して派手に目立つことは好まず、裏で緻密な計算と準備を重ね、一歩ずつ確実に実績を積み上げていく筋金入りの大器晩成型です。内面に秘めた野心は誰よりも強く、最終的にはしたたかに大きな成功と権力を手中に収める実力者となります。 | Z39: 優れたロールモデルやメンターを見つけ、その技術や思考法を完全に吸収して自分のものにしてしまう天才的な学習能力を持っています。目立つポジションよりも、実務を取り仕切る参謀役や、地道な作業の積み重ねが結果を生む職人肌の仕事で確固たる地位を築きます。困難な状況でも決して弱音を吐かず、泥臭く結果にコミットし続ける姿勢が、後年になって莫大な評価となって返ってきます。 | AA39: 一時の感情に流されることなく、相手の人間性や将来性をじっくりと見極めた上で、誠実で安定した恋愛関係を好みます。交際がスタートすれば、よそ見をすることなく一途に相手を愛し抜く深い情念を持っています。結婚に対しても「生活の安定」や「家族を守ること」を最優先に考えるため、非常に堅実で頼りがいのあるパートナーとなります。浮気や不倫といったリスクの高い行動は絶対に避けるタイプです。 | AB39: 生殖器系や泌尿器系に疲れが出やすく、ストレスが溜まると極端に無口になったり、内に籠もったりする傾向があります。溜め込んだ感情を安全に発散させるために、日記を書いたり、親しい人にだけは本音を打ち明けたりする習慣を持つことが大切です。また、デトックス効果のあるサウナや岩盤浴、発酵食品の摂取などを通じて、体内に溜まった老廃物やマイナス感情を定期的に排出することが健康の鍵です。 | AC39: 「沈黙は金」を地で行くような、非常に強力で隠密性の高い蓄財能力を持っています。人知れずコツコツと貯えを増やし、気づけば周囲が驚くような財産を築いているという「隠れ富豪」になりやすい運命です。ギャンブルには向いていませんが、長期的な複利効果を狙う投資や、不動産など手堅い資産運用で才能を発揮します。お金の貸し借りはトラブルの元になるため、どれほど親しい相手でも避けた方が無難です。 | AE39: =RIGHT(AH39, 1) -> 申 | AF39: =IF(OR($E$6=RIGHT(AM39,1),$E$7=RIGHT(AM39,1)),"殺",AG39-$I$3) -> 23 | AG39: =AG38+1 -> 2004 | AH39: =VLOOKUP(AM39,[1]大運!$B$31:$C$90,2,FALSE) -> 甲申 | AI39: =VLOOKUP($F$5&"+"&AM39,[1]大運!$H$45:$K$3644,3,FALSE) -> 車騎星 | AK39: =VLOOKUP($F$5&"+"&AM39,[1]大運!$H$45:$K$3644,4,FALSE) -> 天胡星 | AM39: =IF(MOD((AG39-1900+37),60)=0,60,MOD((AG39-1900+37),60)) -> 21 | AN39: =VLOOKUP($F$5&"+"&AM39,[1]大運!$H$45:$K$3644,2,FALSE) -> 半会 | AO39: =VLOOKUP($G$5&"+"&AM39,[1]大運!$H$45:$K$3644,2,FALSE) -> 同 | AP39: =VLOOKUP($H$5&"+"&AM39,[1]大運!$H$45:$K$3644,2,FALSE) -> 準方位 | AQ39: =IF(OR(RIGHT(AH39,1)=$E$6,RIGHT(AH39,1)=$E$7),"殺","")&IF(ABS(RIGHT(AM39,1)-RIGHT($F$5,1))=5,"日","")&IF(ABS(RIGHT(AM39,1)-RIGHT($G$5,1))=5,"月","")&IF(ABS(RIGHT(AM39,1)-RIGHT($H$5,1))=5,"年","") | AR39: =IF($AH39="","", IFERROR(IF(COUNTIF($F$6, MID("己庚辛壬癸甲乙丙丁戊", FIND(LEFT($AH39,1), "甲乙丙丁戊己庚辛壬癸"), 1))>0, CHOOSE(INT((FIND(LEFT($AH39,1), "甲己乙庚丙辛丁壬戊癸")+1)/2), "甲己干合", "乙庚干合", "丙辛干合", "丁壬干合", "戊癸干合"), ""), "")) | AS39: =IF($AH39="","", IFERROR(IF(COUNTIF($G$6, MID("己庚辛壬癸甲乙丙丁戊", FIND(LEFT($AH39,1), "甲乙丙丁戊己庚辛壬癸"), 1))>0, CHOOSE(INT((FIND(LEFT($AH39,1), "甲己乙庚丙辛丁壬戊癸")+1)/2), "甲己干合", "乙庚干合", "丙辛干合", "丁壬干合", "戊癸干合"), ""), "")) | AT39: =IF($AH39="","", IFERROR(IF(COUNTIF($H$6, MID("己庚辛壬癸甲乙丙丁戊", FIND(LEFT($AH39,1), "甲乙丙丁戊己庚辛壬癸"), 1))>0, CHOOSE(INT((FIND(LEFT($AH39,1), "甲己乙庚丙辛丁壬戊癸")+1)/2), "甲己干合", "乙庚干合", "丙辛干合", "丁壬干合", "戊癸干合"), ""), "")) | AU39: =INDEX('12運シート'!C:C, MATCH(1, INDEX(('12運シート'!A:A=TRIM($T$42)) * ('12運シート'!B:B=TRIM(RIGHT(AE39, 1))), 0), 0)) -> 減退 | AV39: =INDEX('12運シート'!$E:$E, MATCH(1, INDEX((TRIM('12運シート'!$A:$A)=TRIM($T$42)) * (TRIM('12運シート'!$B:$B)=TRIM(AE39)), 0), 0)) -> 雨天 | AW39: =VLOOKUP(AV39,$V$6:$W$18, 2, FALSE) -> カルマの精算。過去の執着をすべて洗い流し、次の春への準備を整える。 | AZ39: =RIGHT(BC39, 1) -> 酉 | BA39: =BA38+1 -> 46165 | BB39: =MOD(BA39 - DATE(2024, 1, 1), 60) + 1 -> 34 | BC39: =VLOOKUP(BB39,[1]大運!$B$31:$C$90,2,FALSE) -> 丁酉 | BD39: =VLOOKUP($F$5 & "+" & (MOD(BA39 - DATE(2024, 1, 1), 60) + 1), [1]大運!$H$45:$K$3644, 3, FALSE) -> 玉堂星 | BE39: =VLOOKUP($F$5 & "+" & (MOD(BA39 - DATE(2024, 1, 1), 60) + 1), [1]大運!$H$45:$K$3644, 4, FALSE) -> 天極星 | BF39: =VLOOKUP($F$5 & "+" & (MOD(BA39 - DATE(2024, 1, 1), 60) + 1), [1]大運!$H$45:$K$3644, 2, FALSE) -> 破 | BG39: =VLOOKUP($G$5 & "+" & (MOD(BA39 - DATE(2024, 1, 1), 60) + 1), [1]大運!$H$45:$K$3644, 2, FALSE) -> 準方位 | BH39: =VLOOKUP($H$5 & "+" & (MOD(BA39 - DATE(2024, 1, 1), 60) + 1), [1]大運!$H$45:$K$3644, 2, FALSE) -> 自刑 | BI39: =IF($BC39="","", IFERROR(IF(COUNTIF($F$6, MID("己庚辛壬癸甲乙丙丁戊", FIND(LEFT($BC39,1), "甲乙丙丁戊己庚辛壬癸"), 1))>0, CHOOSE(INT((FIND(LEFT($BC39,1), "甲己乙庚丙辛丁壬戊癸")+1)/2), "甲己干合", "乙庚干合", "丙辛干合", "丁壬干合", "戊癸干合"), ""), "")) | BJ39: =IF($BC39="","", IFERROR(IF(COUNTIF($G$6, MID("己庚辛壬癸甲乙丙丁戊", FIND(LEFT($BC39,1), "甲乙丙丁戊己庚辛壬癸"), 1))>0, CHOOSE(INT((FIND(LEFT($BC39,1), "甲己乙庚丙辛丁壬戊癸")+1)/2), "甲己干合", "乙庚干合", "丙辛干合", "丁壬干合", "戊癸干合"), ""), "")) | BK39: =IF($BC39="","", IFERROR(IF(COUNTIF($H$6, MID("己庚辛壬癸甲乙丙丁戊", FIND(LEFT($BC39,1), "甲乙丙丁戊己庚辛壬癸"), 1))>0, CHOOSE(INT((FIND(LEFT($BC39,1), "甲己乙庚丙辛丁壬戊癸")+1)/2), "甲己干合", "乙庚干合", "丙辛干合", "丁壬干合", "戊癸干合"), ""), "")) | BL39: =INDEX('12運シート'!C:C, MATCH(1, INDEX(('12運シート'!A:A=TRIM($T$42)) * ('12運シート'!B:B=TRIM(RIGHT(AZ39, 1))), 0), 0)) -> 種子 | BM39: =INDEX('12運シート'!$E:$E, MATCH(1, INDEX((TRIM('12運シート'!$A:$A)=TRIM($T$42)) * (TRIM('12運シート'!$B:$B)=TRIM(AZ39)), 0), 0)) -> 起天 | BN39: =VLOOKUP(BM39,$V$6:$W$18, 2, FALSE) -> 運命の幕開け。過去を断ち切り新しい種をまく開拓期。 | CF39: 29
T40: 寅卯 | U40: 木星人 | V40: 水星人（＋） | W40: 子丑＋ | X40: 裏みずがめ座 | Y40: 周囲の人を楽しませ、笑顔にすることに自分の全エネルギーを注ぎ込む、カリスマ的なエンターテイナーとしての魂を持っています。ユーモアのセンスに溢れ、明るく知的に人生を謳歌するその姿は、性別や年齢を問わず多くの人を惹きつける強烈な磁力を持っています。常識や古い慣習にとらわれない自由な発想力で、周囲に驚きと感動を与えながら、自分自身の人生をも壮大なエンターテインメントとして昇華させます。 | Z40: サービス業やエンタメ業、マスコミ、企画PRなど、あなたの個性とセンスが直接評価される目立つポジションにおいて、圧倒的な輝きを放ちます。退屈な単純作業や厳しい上下関係のある職場では才能が完全に枯れてしまいます。常に新しいアイデアを発信し、周囲をワクワクさせるようなムードメーカーとして活躍することで、大抜擢を受け、若くして業界のスターダムにのし上がる可能性を秘めています。 | AA40: 恋愛においても「驚き」と「喜び」を提供することを愛し、サプライズを企画してパートナーを喜ばせることに幸せを感じます。甘くベタベタしたロマンスよりも、共通の趣味を楽しんだり、冗談を言い合って一緒に大笑いできるような、親友や仲間のような風通しの良い恋愛関係が理想です。束縛を極端に嫌うため、お互いの自由を尊重し合える自立した相手との結婚が最も上手くいきます。 | AB40: お金を「人生を楽しむためのチケット」と捉えているため、旅行やイベント、友人との交際費などにパッと使ってしまう傾向があります。蓄財はあまり得意ではありませんが、その天性の明るさと人脈の広さが強力な金脈となり、ピンチの時には必ずどこかからスポンサーや援助者が現れるという「お金に愛される」不思議な運を持っています。楽しいことにお金を使うほど、金運の波がさらに大きくなって還ってきます。 | AC40: 常に周囲を楽しませようと気を張っているため、本人が気づかないうちに神経が極度に疲弊していることがあります。足首やふくらはぎ、神経系にトラブルが出やすいため、一日の終わりには入浴やマッサージで心身のテンションをしっかりと鎮めることが重要です。休日はあえて誰とも会わず、時間を気にせずにたっぷりと眠る「何もしない日」を作ることで、枯渇したエンターテイナーとしてのエネルギーが復活します。 | AE40: =RIGHT(AH40, 1) -> 酉 | AF40: =IF(OR($E$6=RIGHT(AM40,1),$E$7=RIGHT(AM40,1)),"殺",AG40-$I$3) -> 24 | AG40: =AG39+1 -> 2005 | AH40: =VLOOKUP(AM40,[1]大運!$B$31:$C$90,2,FALSE) -> 乙酉 | AI40: =VLOOKUP($F$5&"+"&AM40,[1]大運!$H$45:$K$3644,3,FALSE) -> 牽牛星 | AK40: =VLOOKUP($F$5&"+"&AM40,[1]大運!$H$45:$K$3644,4,FALSE) -> 天極星 | AM40: =IF(MOD((AG40-1900+37),60)=0,60,MOD((AG40-1900+37),60)) -> 22 | AN40: =VLOOKUP($F$5&"+"&AM40,[1]大運!$H$45:$K$3644,2,FALSE) -> 破 | AO40: =VLOOKUP($G$5&"+"&AM40,[1]大運!$H$45:$K$3644,2,FALSE) -> 準方位 | AP40: =VLOOKUP($H$5&"+"&AM40,[1]大運!$H$45:$K$3644,2,FALSE) -> 自刑 | AQ40: =IF(OR(RIGHT(AH40,1)=$E$6,RIGHT(AH40,1)=$E$7),"殺","")&IF(ABS(RIGHT(AM40,1)-RIGHT($F$5,1))=5,"日","")&IF(ABS(RIGHT(AM40,1)-RIGHT($G$5,1))=5,"月","")&IF(ABS(RIGHT(AM40,1)-RIGHT($H$5,1))=5,"年","") | AR40: =IF($AH40="","", IFERROR(IF(COUNTIF($F$6, MID("己庚辛壬癸甲乙丙丁戊", FIND(LEFT($AH40,1), "甲乙丙丁戊己庚辛壬癸"), 1))>0, CHOOSE(INT((FIND(LEFT($AH40,1), "甲己乙庚丙辛丁壬戊癸")+1)/2), "甲己干合", "乙庚干合", "丙辛干合", "丁壬干合", "戊癸干合"), ""), "")) | AS40: =IF($AH40="","", IFERROR(IF(COUNTIF($G$6, MID("己庚辛壬癸甲乙丙丁戊", FIND(LEFT($AH40,1), "甲乙丙丁戊己庚辛壬癸"), 1))>0, CHOOSE(INT((FIND(LEFT($AH40,1), "甲己乙庚丙辛丁壬戊癸")+1)/2), "甲己干合", "乙庚干合", "丙辛干合", "丁壬干合", "戊癸干合"), ""), "")) | AT40: =IF($AH40="","", IFERROR(IF(COUNTIF($H$6, MID("己庚辛壬癸甲乙丙丁戊", FIND(LEFT($AH40,1), "甲乙丙丁戊己庚辛壬癸"), 1))>0, CHOOSE(INT((FIND(LEFT($AH40,1), "甲己乙庚丙辛丁壬戊癸")+1)/2), "甲己干合", "乙庚干合", "丙辛干合", "丁壬干合", "戊癸干合"), ""), "")) | AU40: =INDEX('12運シート'!C:C, MATCH(1, INDEX(('12運シート'!A:A=TRIM($T$42)) * ('12運シート'!B:B=TRIM(RIGHT(AE40, 1))), 0), 0)) -> 種子 | AV40: =INDEX('12運シート'!$E:$E, MATCH(1, INDEX((TRIM('12運シート'!$A:$A)=TRIM($T$42)) * (TRIM('12運シート'!$B:$B)=TRIM(AE40)), 0), 0)) -> 起天 | AW40: =VLOOKUP(AV40,$V$6:$W$18, 2, FALSE) -> 運命の幕開け。過去を断ち切り新しい種をまく開拓期。 | AZ40: =RIGHT(BC40, 1) -> 戌 | BA40: =BA39+1 -> 46166 | BB40: =MOD(BA40 - DATE(2024, 1, 1), 60) + 1 -> 35 | BC40: =VLOOKUP(BB40,[1]大運!$B$31:$C$90,2,FALSE) -> 戊戌 | BD40: =VLOOKUP($F$5 & "+" & (MOD(BA40 - DATE(2024, 1, 1), 60) + 1), [1]大運!$H$45:$K$3644, 3, FALSE) -> 貫索星 | BE40: =VLOOKUP($F$5 & "+" & (MOD(BA40 - DATE(2024, 1, 1), 60) + 1), [1]大運!$H$45:$K$3644, 4, FALSE) -> 天庫星 | BF40: =VLOOKUP($F$5 & "+" & (MOD(BA40 - DATE(2024, 1, 1), 60) + 1), [1]大運!$H$45:$K$3644, 2, FALSE) -> － | BG40: =VLOOKUP($G$5 & "+" & (MOD(BA40 - DATE(2024, 1, 1), 60) + 1), [1]大運!$H$45:$K$3644, 2, FALSE) -> 準方位 | BH40: =VLOOKUP($H$5 & "+" & (MOD(BA40 - DATE(2024, 1, 1), 60) + 1), [1]大運!$H$45:$K$3644, 2, FALSE) -> 害 | BI40: =IF($BC40="","", IFERROR(IF(COUNTIF($F$6, MID("己庚辛壬癸甲乙丙丁戊", FIND(LEFT($BC40,1), "甲乙丙丁戊己庚辛壬癸"), 1))>0, CHOOSE(INT((FIND(LEFT($BC40,1), "甲己乙庚丙辛丁壬戊癸")+1)/2), "甲己干合", "乙庚干合", "丙辛干合", "丁壬干合", "戊癸干合"), ""), "")) | BJ40: =IF($BC40="","", IFERROR(IF(COUNTIF($G$6, MID("己庚辛壬癸甲乙丙丁戊", FIND(LEFT($BC40,1), "甲乙丙丁戊己庚辛壬癸"), 1))>0, CHOOSE(INT((FIND(LEFT($BC40,1), "甲己乙庚丙辛丁壬戊癸")+1)/2), "甲己干合", "乙庚干合", "丙辛干合", "丁壬干合", "戊癸干合"), ""), "")) | BK40: =IF($BC40="","", IFERROR(IF(COUNTIF($H$6, MID("己庚辛壬癸甲乙丙丁戊", FIND(LEFT($BC40,1), "甲乙丙丁戊己庚辛壬癸"), 1))>0, CHOOSE(INT((FIND(LEFT($BC40,1), "甲己乙庚丙辛丁壬戊癸")+1)/2), "甲己干合", "乙庚干合", "丙辛干合", "丁壬干合", "戊癸干合"), ""), "")) | BL40: =INDEX('12運シート'!C:C, MATCH(1, INDEX(('12運シート'!A:A=TRIM($T$42)) * ('12運シート'!B:B=TRIM(RIGHT(AZ40, 1))), 0), 0)) -> 緑生 | BM40: =INDEX('12運シート'!$E:$E, MATCH(1, INDEX((TRIM('12運シート'!$A:$A)=TRIM($T$42)) * (TRIM('12運シート'!$B:$B)=TRIM(AZ40)), 0), 0)) -> 吉祥天 | BN40: =VLOOKUP(BM40,$V$6:$W$18, 2, FALSE) -> まいた種が芽吹き、周囲の支援を受けて着実に育つ時期。 | CF40: 30
T41: 子丑 | U41: 水星人 | V41: 水星人（－） | W41: 子丑－ | X41: 裏やぎ座 | Y41: 冷静な判断力と遊び心を絶妙なバランスで兼ね備えた、非常にクレバーな創設者（ファウンダー）としての運命を持っています。独立心が極めて強く、他人の下で使われることを良しとせず、自らの知略と行動力で一代にして巨大な城を築き上げる知的な勝負師です。冷徹な計算高さだけでなく、周囲を惹きつける独特のユーモアを持つため、敵を作らずにしたたかに頂点へと登り詰めるカリスマ性を誇ります。 | Z41: 「ゼロからイチを生み出す初代運」を強力に持っているため、起業や新規プロジェクトの立ち上げ、独立開業において大成功を収める暗示があります。既存の枠組みを壊し、誰も思いつかなかったような斬新なビジネスモデルを構築する天才です。リスクを恐れずに勝負に出る度胸と、最悪の事態を想定して打つ緻密な戦略を併せ持つため、どんな厳しいビジネス環境でも必ず生き残り、莫大な利益を叩き出します。 | AA41: 恋愛においては非常に理想が高く、自分と同等かそれ以上の知性や野心を持つ相手に強く惹かれます。お互いの仕事や生き方を心からリスペクトし合える、洗練された大人の恋愛関係を好みます。恋愛に依存することはなく、あくまで自分の人生を豊かにするためのエッセンスと捉えています。結婚後もベタベタとした関係ではなく、最強のビジネスパートナーのような、同志としての強い結束力を持った家庭を築きます。 | AB41: 非常に強力な「財を成す運気」を持っています。投資やビジネスで大きなお金を動かす胆力があり、ピンチをチャンスに変えて莫大な利益を生み出す天性の勝負強さがあります。お金を単なる紙幣ではなく「自分の理想を実現するためのツール」として効果的に使う術を熟知しているため、生涯を通じて巨万の富を築き上げる可能性が高いです。晩年はその財力を活かし、後進の育成や社会貢献に投資することでさらに名誉を得ます。 | AC41: 仕事や目標達成のために睡眠や食事を犠牲にして限界まで働き続けてしまう、ワーカーホリックに陥りやすい傾向があります。骨や関節、皮膚などにストレスのサインが出やすいため、カルシウムの摂取や適度な日光浴を心がけてください。常に頭脳を酷使しているため、デジタルデバイスから離れて自然の中で過ごしたり、瞑想を取り入れるなどして、脳を強制的にシャットダウンする時間を設けることが健康の秘訣です。 | AE41: =RIGHT(AH41, 1) -> 戌 | AF41: =IF(OR($E$6=RIGHT(AM41,1),$E$7=RIGHT(AM41,1)),"殺",AG41-$I$3) -> 25 | AG41: =AG40+1 -> 2006 | AH41: =VLOOKUP(AM41,[1]大運!$B$31:$C$90,2,FALSE) -> 丙戌 | AI41: =VLOOKUP($F$5&"+"&AM41,[1]大運!$H$45:$K$3644,3,FALSE) -> 龍高星 | AK41: =VLOOKUP($F$5&"+"&AM41,[1]大運!$H$45:$K$3644,4,FALSE) -> 天庫星 | AM41: =IF(MOD((AG41-1900+37),60)=0,60,MOD((AG41-1900+37),60)) -> 23 | AN41: =VLOOKUP($F$5&"+"&AM41,[1]大運!$H$45:$K$3644,2,FALSE) -> － | AO41: =VLOOKUP($G$5&"+"&AM41,[1]大運!$H$45:$K$3644,2,FALSE) -> 準方位 | AP41: =VLOOKUP($H$5&"+"&AM41,[1]大運!$H$45:$K$3644,2,FALSE) -> 害 | AQ41: =IF(OR(RIGHT(AH41,1)=$E$6,RIGHT(AH41,1)=$E$7),"殺","")&IF(ABS(RIGHT(AM41,1)-RIGHT($F$5,1))=5,"日","")&IF(ABS(RIGHT(AM41,1)-RIGHT($G$5,1))=5,"月","")&IF(ABS(RIGHT(AM41,1)-RIGHT($H$5,1))=5,"年","") -> 年 | AR41: =IF($AH41="","", IFERROR(IF(COUNTIF($F$6, MID("己庚辛壬癸甲乙丙丁戊", FIND(LEFT($AH41,1), "甲乙丙丁戊己庚辛壬癸"), 1))>0, CHOOSE(INT((FIND(LEFT($AH41,1), "甲己乙庚丙辛丁壬戊癸")+1)/2), "甲己干合", "乙庚干合", "丙辛干合", "丁壬干合", "戊癸干合"), ""), "")) | AS41: =IF($AH41="","", IFERROR(IF(COUNTIF($G$6, MID("己庚辛壬癸甲乙丙丁戊", FIND(LEFT($AH41,1), "甲乙丙丁戊己庚辛壬癸"), 1))>0, CHOOSE(INT((FIND(LEFT($AH41,1), "甲己乙庚丙辛丁壬戊癸")+1)/2), "甲己干合", "乙庚干合", "丙辛干合", "丁壬干合", "戊癸干合"), ""), "")) | AT41: =IF($AH41="","", IFERROR(IF(COUNTIF($H$6, MID("己庚辛壬癸甲乙丙丁戊", FIND(LEFT($AH41,1), "甲乙丙丁戊己庚辛壬癸"), 1))>0, CHOOSE(INT((FIND(LEFT($AH41,1), "甲己乙庚丙辛丁壬戊癸")+1)/2), "甲己干合", "乙庚干合", "丙辛干合", "丁壬干合", "戊癸干合"), ""), "")) -> 丙辛干合 | AU41: =INDEX('12運シート'!C:C, MATCH(1, INDEX(('12運シート'!A:A=TRIM($T$42)) * ('12運シート'!B:B=TRIM(RIGHT(AE41, 1))), 0), 0)) -> 緑生 | AV41: =INDEX('12運シート'!$E:$E, MATCH(1, INDEX((TRIM('12運シート'!$A:$A)=TRIM($T$42)) * (TRIM('12運シート'!$B:$B)=TRIM(AE41)), 0), 0)) -> 吉祥天 | AW41: =VLOOKUP(AV41,$V$6:$W$18, 2, FALSE) -> まいた種が芽吹き、周囲の支援を受けて着実に育つ時期。 | AZ41: =RIGHT(BC41, 1) -> 亥 | BA41: =BA40+1 -> 46167 | BB41: =MOD(BA41 - DATE(2024, 1, 1), 60) + 1 -> 36 | BC41: =VLOOKUP(BB41,[1]大運!$B$31:$C$90,2,FALSE) -> 己亥 | BD41: =VLOOKUP($F$5 & "+" & (MOD(BA41 - DATE(2024, 1, 1), 60) + 1), [1]大運!$H$45:$K$3644, 3, FALSE) -> 石門星 | BE41: =VLOOKUP($F$5 & "+" & (MOD(BA41 - DATE(2024, 1, 1), 60) + 1), [1]大運!$H$45:$K$3644, 4, FALSE) -> 天馳星 | BF41: =VLOOKUP($F$5 & "+" & (MOD(BA41 - DATE(2024, 1, 1), 60) + 1), [1]大運!$H$45:$K$3644, 2, FALSE) -> 準方位 | BG41: =VLOOKUP($G$5 & "+" & (MOD(BA41 - DATE(2024, 1, 1), 60) + 1), [1]大運!$H$45:$K$3644, 2, FALSE) -> 害 | BH41: =VLOOKUP($H$5 & "+" & (MOD(BA41 - DATE(2024, 1, 1), 60) + 1), [1]大運!$H$45:$K$3644, 2, FALSE) -> － | BI41: =IF($BC41="","", IFERROR(IF(COUNTIF($F$6, MID("己庚辛壬癸甲乙丙丁戊", FIND(LEFT($BC41,1), "甲乙丙丁戊己庚辛壬癸"), 1))>0, CHOOSE(INT((FIND(LEFT($BC41,1), "甲己乙庚丙辛丁壬戊癸")+1)/2), "甲己干合", "乙庚干合", "丙辛干合", "丁壬干合", "戊癸干合"), ""), "")) | BJ41: =IF($BC41="","", IFERROR(IF(COUNTIF($G$6, MID("己庚辛壬癸甲乙丙丁戊", FIND(LEFT($BC41,1), "甲乙丙丁戊己庚辛壬癸"), 1))>0, CHOOSE(INT((FIND(LEFT($BC41,1), "甲己乙庚丙辛丁壬戊癸")+1)/2), "甲己干合", "乙庚干合", "丙辛干合", "丁壬干合", "戊癸干合"), ""), "")) | BK41: =IF($BC41="","", IFERROR(IF(COUNTIF($H$6, MID("己庚辛壬癸甲乙丙丁戊", FIND(LEFT($BC41,1), "甲乙丙丁戊己庚辛壬癸"), 1))>0, CHOOSE(INT((FIND(LEFT($BC41,1), "甲己乙庚丙辛丁壬戊癸")+1)/2), "甲己干合", "乙庚干合", "丙辛干合", "丁壬干合", "戊癸干合"), ""), "")) | BL41: =INDEX('12運シート'!C:C, MATCH(1, INDEX(('12運シート'!A:A=TRIM($T$42)) * ('12運シート'!B:B=TRIM(RIGHT(AZ41, 1))), 0), 0)) -> 立花 | BM41: =INDEX('12運シート'!$E:$E, MATCH(1, INDEX((TRIM('12運シート'!$A:$A)=TRIM($T$42)) * (TRIM('12運シート'!$B:$B)=TRIM(AZ41)), 0), 0)) -> 弁財天 | BN41: =VLOOKUP(BM41,$V$6:$W$18, 2, FALSE) -> 才能がパッと花開き、今後の人生を左右する重要な決定を下す発展期。 | CF41: 31
T42: =VLOOKUP(E8, $T$36:$U$41, 2, FALSE) & "（" & T44 & "）" -> 火星人（－） | U42: =VLOOKUP(TRIM($T$42),V:X, 2, FALSE) -> 午未－ | V42: =VLOOKUP(TRIM($T$42),V:X, 3, FALSE) -> 裏かに座 | W42: アスペクト | AE42: =RIGHT(AH42, 1) -> 亥 | AF42: =IF(OR($E$6=RIGHT(AM42,1),$E$7=RIGHT(AM42,1)),"殺",AG42-$I$3) -> 26 | AG42: =AG41+1 -> 2007 | AH42: =VLOOKUP(AM42,[1]大運!$B$31:$C$90,2,FALSE) -> 丁亥 | AI42: =VLOOKUP($F$5&"+"&AM42,[1]大運!$H$45:$K$3644,3,FALSE) -> 玉堂星 | AK42: =VLOOKUP($F$5&"+"&AM42,[1]大運!$H$45:$K$3644,4,FALSE) -> 天馳星 | AM42: =IF(MOD((AG42-1900+37),60)=0,60,MOD((AG42-1900+37),60)) -> 24 | AN42: =VLOOKUP($F$5&"+"&AM42,[1]大運!$H$45:$K$3644,2,FALSE) -> 準方位 | AO42: =VLOOKUP($G$5&"+"&AM42,[1]大運!$H$45:$K$3644,2,FALSE) -> 害 | AP42: =VLOOKUP($H$5&"+"&AM42,[1]大運!$H$45:$K$3644,2,FALSE) -> － | AQ42: =IF(OR(RIGHT(AH42,1)=$E$6,RIGHT(AH42,1)=$E$7),"殺","")&IF(ABS(RIGHT(AM42,1)-RIGHT($F$5,1))=5,"日","")&IF(ABS(RIGHT(AM42,1)-RIGHT($G$5,1))=5,"月","")&IF(ABS(RIGHT(AM42,1)-RIGHT($H$5,1))=5,"年","") | AR42: =IF($AH42="","", IFERROR(IF(COUNTIF($F$6, MID("己庚辛壬癸甲乙丙丁戊", FIND(LEFT($AH42,1), "甲乙丙丁戊己庚辛壬癸"), 1))>0, CHOOSE(INT((FIND(LEFT($AH42,1), "甲己乙庚丙辛丁壬戊癸")+1)/2), "甲己干合", "乙庚干合", "丙辛干合", "丁壬干合", "戊癸干合"), ""), "")) | AS42: =IF($AH42="","", IFERROR(IF(COUNTIF($G$6, MID("己庚辛壬癸甲乙丙丁戊", FIND(LEFT($AH42,1), "甲乙丙丁戊己庚辛壬癸"), 1))>0, CHOOSE(INT((FIND(LEFT($AH42,1), "甲己乙庚丙辛丁壬戊癸")+1)/2), "甲己干合", "乙庚干合", "丙辛干合", "丁壬干合", "戊癸干合"), ""), "")) | AT42: =IF($AH42="","", IFERROR(IF(COUNTIF($H$6, MID("己庚辛壬癸甲乙丙丁戊", FIND(LEFT($AH42,1), "甲乙丙丁戊己庚辛壬癸"), 1))>0, CHOOSE(INT((FIND(LEFT($AH42,1), "甲己乙庚丙辛丁壬戊癸")+1)/2), "甲己干合", "乙庚干合", "丙辛干合", "丁壬干合", "戊癸干合"), ""), "")) | AU42: =INDEX('12運シート'!C:C, MATCH(1, INDEX(('12運シート'!A:A=TRIM($T$42)) * ('12運シート'!B:B=TRIM(RIGHT(AE42, 1))), 0), 0)) -> 立花 | AV42: =INDEX('12運シート'!$E:$E, MATCH(1, INDEX((TRIM('12運シート'!$A:$A)=TRIM($T$42)) * (TRIM('12運シート'!$B:$B)=TRIM(AE42)), 0), 0)) -> 弁財天 | AW42: =VLOOKUP(AV42,$V$6:$W$18, 2, FALSE) -> 才能がパッと花開き、今後の人生を左右する重要な決定を下す発展期。 | AZ42: =RIGHT(BC42, 1) -> 子 | BA42: =BA41+1 -> 46168 | BB42: =MOD(BA42 - DATE(2024, 1, 1), 60) + 1 -> 37 | BC42: =VLOOKUP(BB42,[1]大運!$B$31:$C$90,2,FALSE) -> 庚子 | BD42: =VLOOKUP($F$5 & "+" & (MOD(BA42 - DATE(2024, 1, 1), 60) + 1), [1]大運!$H$45:$K$3644, 3, FALSE) -> 鳳閣星 | BE42: =VLOOKUP($F$5 & "+" & (MOD(BA42 - DATE(2024, 1, 1), 60) + 1), [1]大運!$H$45:$K$3644, 4, FALSE) -> 天報星 | BF42: =VLOOKUP($F$5 & "+" & (MOD(BA42 - DATE(2024, 1, 1), 60) + 1), [1]大運!$H$45:$K$3644, 2, FALSE) -> 同 | BG42: =VLOOKUP($G$5 & "+" & (MOD(BA42 - DATE(2024, 1, 1), 60) + 1), [1]大運!$H$45:$K$3644, 2, FALSE) -> 半会 | BH42: =VLOOKUP($H$5 & "+" & (MOD(BA42 - DATE(2024, 1, 1), 60) + 1), [1]大運!$H$45:$K$3644, 2, FALSE) -> 破 | BI42: =IF($BC42="","", IFERROR(IF(COUNTIF($F$6, MID("己庚辛壬癸甲乙丙丁戊", FIND(LEFT($BC42,1), "甲乙丙丁戊己庚辛壬癸"), 1))>0, CHOOSE(INT((FIND(LEFT($BC42,1), "甲己乙庚丙辛丁壬戊癸")+1)/2), "甲己干合", "乙庚干合", "丙辛干合", "丁壬干合", "戊癸干合"), ""), "")) | BJ42: =IF($BC42="","", IFERROR(IF(COUNTIF($G$6, MID("己庚辛壬癸甲乙丙丁戊", FIND(LEFT($BC42,1), "甲乙丙丁戊己庚辛壬癸"), 1))>0, CHOOSE(INT((FIND(LEFT($BC42,1), "甲己乙庚丙辛丁壬戊癸")+1)/2), "甲己干合", "乙庚干合", "丙辛干合", "丁壬干合", "戊癸干合"), ""), "")) | BK42: =IF($BC42="","", IFERROR(IF(COUNTIF($H$6, MID("己庚辛壬癸甲乙丙丁戊", FIND(LEFT($BC42,1), "甲乙丙丁戊己庚辛壬癸"), 1))>0, CHOOSE(INT((FIND(LEFT($BC42,1), "甲己乙庚丙辛丁壬戊癸")+1)/2), "甲己干合", "乙庚干合", "丙辛干合", "丁壬干合", "戊癸干合"), ""), "")) | BL42: =INDEX('12運シート'!C:C, MATCH(1, INDEX(('12運シート'!A:A=TRIM($T$42)) * ('12運シート'!B:B=TRIM(RIGHT(AZ42, 1))), 0), 0)) -> 健弱 | BM42: =INDEX('12運シート'!$E:$E, MATCH(1, INDEX((TRIM('12運シート'!$A:$A)=TRIM($T$42)) * (TRIM('12運シート'!$B:$B)=TRIM(AZ42)), 0), 0)) -> 曇天 | BN42: =VLOOKUP(BM42,$V$6:$W$18, 2, FALSE) -> 運気の勢いに心身が追いつかない小休止。自己治癒の時期。 | CF42: 32
T43: =[1]五指裏干支占い!D2 -> 29836 | U43: 表星座 | V43: =IF(T43="","", VLOOKUP(VALUE(TEXT(T43,"mmdd")),{101,"やぎ座";120,"みずがめ座";219,"うお座";321,"おひつじ座";420,"おうし座";521,"ふたご座";622,"かに座";723,"しし座";823,"おとめ座";923,"てんびん座";1024,"さそり座";1123,"いて座";1222,"やぎ座"},2,TRUE)) -> おとめ座 | W43: =INDEX(表裏星座一覧!C:C, MATCH(1, INDEX((表裏星座一覧!A:A=$V$43) * (表裏星座一覧!B:B=$V$42), 0), 0)) -> 60°・120°（セクスタイル・トライン） | X43: =VLOOKUP(W43, 表裏星座一覧!A:B, 2, FALSE) -> 【ナチュラル・ハーモニー型】 | AE43: =RIGHT(AH43, 1) -> 子 | AF43: =IF(OR($E$6=RIGHT(AM43,1),$E$7=RIGHT(AM43,1)),"殺",AG43-$I$3) -> 27 | AG43: =AG42+1 -> 2008 | AH43: =VLOOKUP(AM43,[1]大運!$B$31:$C$90,2,FALSE) -> 戊子 | AI43: =VLOOKUP($F$5&"+"&AM43,[1]大運!$H$45:$K$3644,3,FALSE) -> 貫索星 | AK43: =VLOOKUP($F$5&"+"&AM43,[1]大運!$H$45:$K$3644,4,FALSE) -> 天報星 | AM43: =IF(MOD((AG43-1900+37),60)=0,60,MOD((AG43-1900+37),60)) -> 25 | AN43: =VLOOKUP($F$5&"+"&AM43,[1]大運!$H$45:$K$3644,2,FALSE) -> 律音 | AO43: =VLOOKUP($G$5&"+"&AM43,[1]大運!$H$45:$K$3644,2,FALSE) -> 半会 | AP43: =VLOOKUP($H$5&"+"&AM43,[1]大運!$H$45:$K$3644,2,FALSE) -> 破 | AQ43: =IF(OR(RIGHT(AH43,1)=$E$6,RIGHT(AH43,1)=$E$7),"殺","")&IF(ABS(RIGHT(AM43,1)-RIGHT($F$5,1))=5,"日","")&IF(ABS(RIGHT(AM43,1)-RIGHT($G$5,1))=5,"月","")&IF(ABS(RIGHT(AM43,1)-RIGHT($H$5,1))=5,"年","") | AR43: =IF($AH43="","", IFERROR(IF(COUNTIF($F$6, MID("己庚辛壬癸甲乙丙丁戊", FIND(LEFT($AH43,1), "甲乙丙丁戊己庚辛壬癸"), 1))>0, CHOOSE(INT((FIND(LEFT($AH43,1), "甲己乙庚丙辛丁壬戊癸")+1)/2), "甲己干合", "乙庚干合", "丙辛干合", "丁壬干合", "戊癸干合"), ""), "")) | AS43: =IF($AH43="","", IFERROR(IF(COUNTIF($G$6, MID("己庚辛壬癸甲乙丙丁戊", FIND(LEFT($AH43,1), "甲乙丙丁戊己庚辛壬癸"), 1))>0, CHOOSE(INT((FIND(LEFT($AH43,1), "甲己乙庚丙辛丁壬戊癸")+1)/2), "甲己干合", "乙庚干合", "丙辛干合", "丁壬干合", "戊癸干合"), ""), "")) | AT43: =IF($AH43="","", IFERROR(IF(COUNTIF($H$6, MID("己庚辛壬癸甲乙丙丁戊", FIND(LEFT($AH43,1), "甲乙丙丁戊己庚辛壬癸"), 1))>0, CHOOSE(INT((FIND(LEFT($AH43,1), "甲己乙庚丙辛丁壬戊癸")+1)/2), "甲己干合", "乙庚干合", "丙辛干合", "丁壬干合", "戊癸干合"), ""), "")) | AU43: =INDEX('12運シート'!C:C, MATCH(1, INDEX(('12運シート'!A:A=TRIM($T$42)) * ('12運シート'!B:B=TRIM(RIGHT(AE43, 1))), 0), 0)) -> 健弱 | AV43: =INDEX('12運シート'!$E:$E, MATCH(1, INDEX((TRIM('12運シート'!$A:$A)=TRIM($T$42)) * (TRIM('12運シート'!$B:$B)=TRIM(AE43)), 0), 0)) -> 曇天 | AW43: =VLOOKUP(AV43,$V$6:$W$18, 2, FALSE) -> 運気の勢いに心身が追いつかない小休止。自己治癒の時期。 | AZ43: =RIGHT(BC43, 1) -> 丑 | BA43: =BA42+1 -> 46169 | BB43: =MOD(BA43 - DATE(2024, 1, 1), 60) + 1 -> 38 | BC43: =VLOOKUP(BB43,[1]大運!$B$31:$C$90,2,FALSE) -> 辛丑 | BD43: =VLOOKUP($F$5 & "+" & (MOD(BA43 - DATE(2024, 1, 1), 60) + 1), [1]大運!$H$45:$K$3644, 3, FALSE) -> 調舒星 | BE43: =VLOOKUP($F$5 & "+" & (MOD(BA43 - DATE(2024, 1, 1), 60) + 1), [1]大運!$H$45:$K$3644, 4, FALSE) -> 天印星 | BF43: =VLOOKUP($F$5 & "+" & (MOD(BA43 - DATE(2024, 1, 1), 60) + 1), [1]大運!$H$45:$K$3644, 2, FALSE) -> 支合 | BG43: =VLOOKUP($G$5 & "+" & (MOD(BA43 - DATE(2024, 1, 1), 60) + 1), [1]大運!$H$45:$K$3644, 2, FALSE) -> － | BH43: =VLOOKUP($H$5 & "+" & (MOD(BA43 - DATE(2024, 1, 1), 60) + 1), [1]大運!$H$45:$K$3644, 2, FALSE) -> 大半会 | BI43: =IF($BC43="","", IFERROR(IF(COUNTIF($F$6, MID("己庚辛壬癸甲乙丙丁戊", FIND(LEFT($BC43,1), "甲乙丙丁戊己庚辛壬癸"), 1))>0, CHOOSE(INT((FIND(LEFT($BC43,1), "甲己乙庚丙辛丁壬戊癸")+1)/2), "甲己干合", "乙庚干合", "丙辛干合", "丁壬干合", "戊癸干合"), ""), "")) | BJ43: =IF($BC43="","", IFERROR(IF(COUNTIF($G$6, MID("己庚辛壬癸甲乙丙丁戊", FIND(LEFT($BC43,1), "甲乙丙丁戊己庚辛壬癸"), 1))>0, CHOOSE(INT((FIND(LEFT($BC43,1), "甲己乙庚丙辛丁壬戊癸")+1)/2), "甲己干合", "乙庚干合", "丙辛干合", "丁壬干合", "戊癸干合"), ""), "")) -> 丙辛干合 | BK43: =IF($BC43="","", IFERROR(IF(COUNTIF($H$6, MID("己庚辛壬癸甲乙丙丁戊", FIND(LEFT($BC43,1), "甲乙丙丁戊己庚辛壬癸"), 1))>0, CHOOSE(INT((FIND(LEFT($BC43,1), "甲己乙庚丙辛丁壬戊癸")+1)/2), "甲己干合", "乙庚干合", "丙辛干合", "丁壬干合", "戊癸干合"), ""), "")) | BL43: =INDEX('12運シート'!C:C, MATCH(1, INDEX(('12運シート'!A:A=TRIM($T$42)) * ('12運シート'!B:B=TRIM(RIGHT(AZ43, 1))), 0), 0)) -> 達成 | BM43: =INDEX('12運シート'!$E:$E, MATCH(1, INDEX((TRIM('12運シート'!$A:$A)=TRIM($T$42)) * (TRIM('12運シート'!$B:$B)=TRIM(AZ43)), 0), 0)) -> 韋駄天 | BN43: =VLOOKUP(BM43,$V$6:$W$18, 2, FALSE) -> 運気絶頂。これまでの努力が実を結び、最高のスポットライトを浴びる。
F44: 月運 | G44: 2025/6 | T44: =IF(MOD(YEAR(T43), 2)=0, "＋", "－") -> － | AE44: =RIGHT(AH44, 1) -> 丑 | AF44: =IF(OR($E$6=RIGHT(AM44,1),$E$7=RIGHT(AM44,1)),"殺",AG44-$I$3) -> 28 | AG44: =AG43+1 -> 2009 | AH44: =VLOOKUP(AM44,[1]大運!$B$31:$C$90,2,FALSE) -> 己丑 | AI44: =VLOOKUP($F$5&"+"&AM44,[1]大運!$H$45:$K$3644,3,FALSE) -> 石門星 | AK44: =VLOOKUP($F$5&"+"&AM44,[1]大運!$H$45:$K$3644,4,FALSE) -> 天印星 | AM44: =IF(MOD((AG44-1900+37),60)=0,60,MOD((AG44-1900+37),60)) -> 26 | AN44: =VLOOKUP($F$5&"+"&AM44,[1]大運!$H$45:$K$3644,2,FALSE) -> 支合 | AO44: =VLOOKUP($G$5&"+"&AM44,[1]大運!$H$45:$K$3644,2,FALSE) -> － | AP44: =VLOOKUP($H$5&"+"&AM44,[1]大運!$H$45:$K$3644,2,FALSE) -> 半会 | AQ44: =IF(OR(RIGHT(AH44,1)=$E$6,RIGHT(AH44,1)=$E$7),"殺","")&IF(ABS(RIGHT(AM44,1)-RIGHT($F$5,1))=5,"日","")&IF(ABS(RIGHT(AM44,1)-RIGHT($G$5,1))=5,"月","")&IF(ABS(RIGHT(AM44,1)-RIGHT($H$5,1))=5,"年","") | AR44: =IF($AH44="","", IFERROR(IF(COUNTIF($F$6, MID("己庚辛壬癸甲乙丙丁戊", FIND(LEFT($AH44,1), "甲乙丙丁戊己庚辛壬癸"), 1))>0, CHOOSE(INT((FIND(LEFT($AH44,1), "甲己乙庚丙辛丁壬戊癸")+1)/2), "甲己干合", "乙庚干合", "丙辛干合", "丁壬干合", "戊癸干合"), ""), "")) | AS44: =IF($AH44="","", IFERROR(IF(COUNTIF($G$6, MID("己庚辛壬癸甲乙丙丁戊", FIND(LEFT($AH44,1), "甲乙丙丁戊己庚辛壬癸"), 1))>0, CHOOSE(INT((FIND(LEFT($AH44,1), "甲己乙庚丙辛丁壬戊癸")+1)/2), "甲己干合", "乙庚干合", "丙辛干合", "丁壬干合", "戊癸干合"), ""), "")) | AT44: =IF($AH44="","", IFERROR(IF(COUNTIF($H$6, MID("己庚辛壬癸甲乙丙丁戊", FIND(LEFT($AH44,1), "甲乙丙丁戊己庚辛壬癸"), 1))>0, CHOOSE(INT((FIND(LEFT($AH44,1), "甲己乙庚丙辛丁壬戊癸")+1)/2), "甲己干合", "乙庚干合", "丙辛干合", "丁壬干合", "戊癸干合"), ""), "")) | AU44: =INDEX('12運シート'!C:C, MATCH(1, INDEX(('12運シート'!A:A=TRIM($T$42)) * ('12運シート'!B:B=TRIM(RIGHT(AE44, 1))), 0), 0)) -> 達成 | AV44: =INDEX('12運シート'!$E:$E, MATCH(1, INDEX((TRIM('12運シート'!$A:$A)=TRIM($T$42)) * (TRIM('12運シート'!$B:$B)=TRIM(AE44)), 0), 0)) -> 韋駄天 | AW44: =VLOOKUP(AV44,$V$6:$W$18, 2, FALSE) -> 運気絶頂。これまでの努力が実を結び、最高のスポットライトを浴びる。 | AZ44: =RIGHT(BC44, 1) -> 寅 | BA44: =BA43+1 -> 46170 | BB44: =MOD(BA44 - DATE(2024, 1, 1), 60) + 1 -> 39 | BC44: =VLOOKUP(BB44,[1]大運!$B$31:$C$90,2,FALSE) -> 壬寅 | BD44: =VLOOKUP($F$5 & "+" & (MOD(BA44 - DATE(2024, 1, 1), 60) + 1), [1]大運!$H$45:$K$3644, 3, FALSE) -> 禄存星 | BE44: =VLOOKUP($F$5 & "+" & (MOD(BA44 - DATE(2024, 1, 1), 60) + 1), [1]大運!$H$45:$K$3644, 4, FALSE) -> 天貴星 | BF44: =VLOOKUP($F$5 & "+" & (MOD(BA44 - DATE(2024, 1, 1), 60) + 1), [1]大運!$H$45:$K$3644, 2, FALSE) -> － | BG44: =VLOOKUP($G$5 & "+" & (MOD(BA44 - DATE(2024, 1, 1), 60) + 1), [1]大運!$H$45:$K$3644, 2, FALSE) -> 天剋地冲 | BH44: =VLOOKUP($H$5 & "+" & (MOD(BA44 - DATE(2024, 1, 1), 60) + 1), [1]大運!$H$45:$K$3644, 2, FALSE) -> － | BI44: =IF($BC44="","", IFERROR(IF(COUNTIF($F$6, MID("己庚辛壬癸甲乙丙丁戊", FIND(LEFT($BC44,1), "甲乙丙丁戊己庚辛壬癸"), 1))>0, CHOOSE(INT((FIND(LEFT($BC44,1), "甲己乙庚丙辛丁壬戊癸")+1)/2), "甲己干合", "乙庚干合", "丙辛干合", "丁壬干合", "戊癸干合"), ""), "")) | BJ44: =IF($BC44="","", IFERROR(IF(COUNTIF($G$6, MID("己庚辛壬癸甲乙丙丁戊", FIND(LEFT($BC44,1), "甲乙丙丁戊己庚辛壬癸"), 1))>0, CHOOSE(INT((FIND(LEFT($BC44,1), "甲己乙庚丙辛丁壬戊癸")+1)/2), "甲己干合", "乙庚干合", "丙辛干合", "丁壬干合", "戊癸干合"), ""), "")) | BK44: =IF($BC44="","", IFERROR(IF(COUNTIF($H$6, MID("己庚辛壬癸甲乙丙丁戊", FIND(LEFT($BC44,1), "甲乙丙丁戊己庚辛壬癸"), 1))>0, CHOOSE(INT((FIND(LEFT($BC44,1), "甲己乙庚丙辛丁壬戊癸")+1)/2), "甲己干合", "乙庚干合", "丙辛干合", "丁壬干合", "戊癸干合"), ""), "")) | BL44: =INDEX('12運シート'!C:C, MATCH(1, INDEX(('12運シート'!A:A=TRIM($T$42)) * ('12運シート'!B:B=TRIM(RIGHT(AZ44, 1))), 0), 0)) -> 乱気 | BM44: =INDEX('12運シート'!$E:$E, MATCH(1, INDEX((TRIM('12運シート'!$A:$A)=TRIM($T$42)) * (TRIM('12運シート'!$B:$B)=TRIM(AZ44)), 0), 0)) -> 伏魔天 | BN44: =VLOOKUP(BM44,$V$6:$W$18, 2, FALSE) -> 強すぎる運気の反動で迷いや摩擦が生じる。理性と現状維持が必要な嵐。
